Workbook

Sheet SPU监控与预算
A1: 分类 | B1: SPU | C1: 阶段 | D1: 监控标记 | E1: 销售额 | F1: 占公司比例 | G1: 毛利额 | H1: 毛利额占比 | I1: 广告花费 | J1: 广告占公司比例 | K1: 广告费率 | L1: 净毛利率 | M1: 广告前毛利率 | N1: SP | O1: SB | P1: SBV | Q1: SD | R1: 近30天销售额 | S1: 前30天销售额 | T1: 近30天环比 | U1: 可用库存 | V1: 建议广告费率 | W1: 当前月广告(估) | X1: 建议月预算 | Y1: 预算调整 | Z1: 触发原因 | AA1: 建议
A2: 电源逆变器 | B2: 逆变器-200W | C2: 清货 | D2: 维持 | E2: 3002859.9 | F2: =IFERROR(E2/规则参数!$B$8,0) -> 0.091899741 | G2: 279838.85 | H2: =IFERROR(G2/规则参数!$B$9,0) -> 0.06219869 | I2: 531781.26 | J2: =IFERROR(I2/规则参数!$B$10,0) -> 0.10983273 | K2: =IFERROR(I2/E2,0) -> 0.1770916 | L2: =IFERROR(G2/E2,0) -> 0.093190777 | M2: =K2+L2 -> 0.27028237 | N2: 435095.98 | O2: 32595.46 | P2: 24829.02 | Q2: 39260.8 | R2: 210946.21 | S2: 150852.89 | T2: =IFERROR(R2/S2-1,"") -> 0.3983571 | U2: 45966 | V2: 0.15 | W2: =R2*K2 -> 37356.801 | X2: =R2*V2 -> 31641.931 | Y2: =X2-W2 -> -5714.8697 | AA2: 按建议广告费率执行，月度复盘
A3: 充气泵 | B3: 充气泵-手持高配版 | C3: 成熟 | D3: 维持 | E3: 1863043 | F3: =IFERROR(E3/规则参数!$B$8,0) -> 0.057016701 | G3: 270693.47 | H3: =IFERROR(G3/规则参数!$B$9,0) -> 0.060165982 | I3: 286580.89 | J3: =IFERROR(I3/规则参数!$B$10,0) -> 0.059189675 | K3: =IFERROR(I3/E3,0) -> 0.15382409 | L3: =IFERROR(G3/E3,0) -> 0.14529642 | M3: =K3+L3 -> 0.29912051 | N3: 255309.58 | O3: 15385.78 | P3: 6838.55 | Q3: 9046.98 | R3: 169909.81 | S3: 144772.01 | T3: =IFERROR(R3/S3-1,"") -> 0.17363716 | U3: 41299 | V3: 0.1538 | W3: =R3*K3 -> 26136.222 | X3: =R3*V3 -> 26132.129 | Y3: =X3-W3 -> -4.093314 | AA3: 按建议广告费率执行，月度复盘
A4: 冲击扳手 | B4: 冲击扳手-1/2英寸1100N | C4: 成熟 | D4: 维持 | E4: 1212161.6 | F4: =IFERROR(E4/规则参数!$B$8,0) -> 0.037097082 | G4: 116793.55 | H4: =IFERROR(G4/规则参数!$B$9,0) -> 0.025959247 | I4: 185987.22 | J4: =IFERROR(I4/规则参数!$B$10,0) -> 0.038413319 | K4: =IFERROR(I4/E4,0) -> 0.15343434 | L4: =IFERROR(G4/E4,0) -> 0.096351466 | M4: =K4+L4 -> 0.24978581 | N4: 170933.16 | O4: 3891.84 | P4: 6511.8 | Q4: 4650.42 | R4: 95333.91 | S4: 82880.23 | T4: =IFERROR(R4/S4-1,"") -> 0.15026117 | U4: 7071 | V4: 0.1498 | W4: =R4*K4 -> 14627.496 | X4: =R4*V4 -> 14281.02 | Y4: =X4-W4 -> -346.47587 | AA4: 按建议广告费率执行，月度复盘
A5: 黄油枪 | B5: 黄油枪-直柄/手枪两用款 | C5: 成熟 | D5: 维持 | E5: 1035369.9 | F5: =IFERROR(E5/规则参数!$B$8,0) -> 0.031686536 | G5: 195638.66 | H5: =IFERROR(G5/规则参数!$B$9,0) -> 0.043483842 | I5: 180059.88 | J5: =IFERROR(I5/规则参数!$B$10,0) -> 0.037189102 | K5: =IFERROR(I5/E5,0) -> 0.17390874 | L5: =IFERROR(G5/E5,0) -> 0.18895532 | M5: =K5+L5 -> 0.36286406 | N5: 147037.02 | O5: 10697.21 | P5: 16736.13 | Q5: 5589.52 | R5: 57122.68 | S5: 69470.05 | T5: =IFERROR(R5/S5-1,"") -> -0.17773659 | U5: 6125 | V5: 0.1739 | W5: =R5*K5 -> 9934.1333 | X5: =R5*V5 -> 9933.6341 | Y5: =X5-W5 -> -0.49925442 | AA5: 按建议广告费率执行，月度复盘
A6: 灯具 | B6: 工作灯-薄款双开关16珠21W | C6: 成熟 | D6: 维持 | E6: 1105640.7 | F6: =IFERROR(E6/规则参数!$B$8,0) -> 0.033837108 | G6: 204102.62 | H6: =IFERROR(G6/规则参数!$B$9,0) -> 0.045365094 | I6: 172553.43 | J6: =IFERROR(I6/规则参数!$B$10,0) -> 0.035638739 | K6: =IFERROR(I6/E6,0) -> 0.15606646 | L6: =IFERROR(G6/E6,0) -> 0.18460122 | M6: =K6+L6 -> 0.34066768 | N6: 157884.26 | O6: 7752.39 | P6: 6130.52 | Q6: 786.26 | R6: 109488.77 | S6: 95953.42 | T6: =IFERROR(R6/S6-1,"") -> 0.14106167 | U6: 19230 | V6: 0.1561 | W6: =R6*K6 -> 17087.525 | X6: =R6*V6 -> 17091.197 | Y6: =X6-W6 -> 3.6722614 | AA6: 按建议广告费率执行，月度复盘
A7: 冲击扳手 | B7: 冲击扳手-1/2英寸1600N | C7: 成熟 | D7: 维持 | E7: 1162804.6 | F7: =IFERROR(E7/规则参数!$B$8,0) -> 0.035586554 | G7: 186226.9 | H7: =IFERROR(G7/规则参数!$B$9,0) -> 0.041391927 | I7: 140260.28 | J7: =IFERROR(I7/规则参数!$B$10,0) -> 0.028968995 | K7: =IFERROR(I7/E7,0) -> 0.1206224 | L7: =IFERROR(G7/E7,0) -> 0.16015322 | M7: =K7+L7 -> 0.28077563 | N7: 135851.54 | O7: 2007.85 | P7: 2300.17 | Q7: 100.72 | R7: 128875.55 | S7: 92475.09 | T7: =IFERROR(R7/S7-1,"") -> 0.39362449 | U7: 5078 | V7: 0.1206 | W7: =R7*K7 -> 15545.279 | X7: =R7*V7 -> 15542.391 | Y7: =X7-W7 -> -2.8871716 | AA7: 按建议广告费率执行，月度复盘
A8: 吹叶机 | B8: 手持吹叶机-无刷裸机 | C8: 成熟 | D8: 维持 | E8: 763528.92 | F8: =IFERROR(E8/规则参数!$B$8,0) -> 0.023367094 | G8: 122664.21 | H8: =IFERROR(G8/规则参数!$B$9,0) -> 0.027264096 | I8: 105902.97 | J8: =IFERROR(I8/规则参数!$B$10,0) -> 0.021872925 | K8: =IFERROR(I8/E8,0) -> 0.13870198 | L8: =IFERROR(G8/E8,0) -> 0.16065431 | M8: =K8+L8 -> 0.29935628 | N8: 102611.25 | O8: 2031.51 | P8: 869.82 | Q8: 390.39 | R8: 89317.92 | S8: 76713.07 | T8: =IFERROR(R8/S8-1,"") -> 0.16431164 | U8: 18931 | V8: 0.1387 | W8: =R8*K8 -> 12388.572 | X8: =R8*V8 -> 12388.396 | Y8: =X8-W8 -> -0.17649956 | AA8: 按建议广告费率执行，月度复盘
A9: 锂电油泵 | B9: 锂电油泵-感应自停 | C9: 清货 | D9: 观察 | E9: 1053256.3 | F9: =IFERROR(E9/规则参数!$B$8,0) -> 0.032233931 | G9: 291849.57 | H9: =IFERROR(G9/规则参数!$B$9,0) -> 0.064868266 | I9: 102995.78 | J9: =IFERROR(I9/规则参数!$B$10,0) -> 0.021272482 | K9: =IFERROR(I9/E9,0) -> 0.097787956 | L9: =IFERROR(G9/E9,0) -> 0.27709264 | M9: =K9+L9 -> 0.3748806 | N9: 78939.86 | O9: 13896.36 | P9: 9016.67 | Q9: 1142.89 | R9: 43899.05 | S9: 64088.88 | T9: =IFERROR(R9/S9-1,"") -> -0.3150286 | U9: 7721 | V9: 0.0978 | W9: =R9*K9 -> 4292.7984 | X9: =R9*V9 -> 4293.3271 | Y9: =X9-W9 -> 0.52870946 | Z9: 近 30 天销售环比下滑 ≥30% | AA9: 近 30 天销售环比 -32%，广告要跟着降：预算按近 30 天销售重算为 $4,293/月，排查排名、断货、差评或竞品降价
A10: 灯具 | B10: 锂电池工作灯-三头款 | C10: 成熟 | D10: 维持 | E10: 777879.19 | F10: =IFERROR(E10/规则参数!$B$8,0) -> 0.023806271 | G10: 211382.2 | H10: =IFERROR(G10/规则参数!$B$9,0) -> 0.046983097 | I10: 94014.51 | J10: =IFERROR(I10/规则参数!$B$10,0) -> 0.019417514 | K10: =IFERROR(I10/E10,0) -> 0.12086004 | L10: =IFERROR(G10/E10,0) -> 0.27174168 | M10: =K10+L10 -> 0.39260172 | N10: 87200.07 | O10: 3812.34 | P10: 2364.03 | Q10: 638.07 | R10: 253812.31 | S10: 156159.22 | T10: =IFERROR(R10/S10-1,"") -> 0.6253431 | U10: 41287 | V10: 0.1209 | W10: =R10*K10 -> 30675.766 | X10: =R10*V10 -> 30685.908 | Y10: =X10-W10 -> 10.142346 | AA10: 按建议广告费率执行，月度复盘
A11: 高压清洗机 | B11: 无线高压清洗机-无刷三速 | C11: 成熟 | D11: 维持 | E11: 532814.49 | F11: =IFERROR(E11/规则参数!$B$8,0) -> 0.016306293 | G11: 68026.06 | H11: =IFERROR(G11/规则参数!$B$9,0) -> 0.015119887 | I11: 91570.39 | J11: =IFERROR(I11/规则参数!$B$10,0) -> 0.018912711 | K11: =IFERROR(I11/E11,0) -> 0.17186167 | L11: =IFERROR(G11/E11,0) -> 0.12767307 | M11: =K11+L11 -> 0.29953474 | N11: 84458.78 | O11: 658.21 | P11: 4779.56 | Q11: 1673.84 | R11: 12087.9 | S11: 13547.46 | T11: =IFERROR(R11/S11-1,"") -> -0.1077368 | U11: 924 | V11: 0.1719 | W11: =R11*K11 -> 2077.4467 | X11: =R11*V11 -> 2077.91 | Y11: =X11-W11 -> 0.463285 | AA11: 按建议广告费率执行，月度复盘
A12: 充气泵 | B12: 充气泵-卧式高配版 | C12: 成熟 | D12: 维持 | E12: 527114.59 | F12: =IFERROR(E12/规则参数!$B$8,0) -> 0.016131853 | G12: 72088.91 | H12: =IFERROR(G12/规则参数!$B$9,0) -> 0.016022921 | I12: 83401.06 | J12: =IFERROR(I12/规则参数!$B$10,0) -> 0.017225439 | K12: =IFERROR(I12/E12,0) -> 0.15822188 | L12: =IFERROR(G12/E12,0) -> 0.13676136 | M12: =K12+L12 -> 0.29498324 | N12: 77421.4 | O12: 2870.89 | P12: 1404.13 | Q12: 1704.64 | R12: 51721.59 | S12: 47226.65 | T12: =IFERROR(R12/S12-1,"") -> 0.09517804 | U12: 9785 | V12: 0.1582 | W12: =R12*K12 -> 8183.4871 | X12: =R12*V12 -> 8182.3555 | Y12: =X12-W12 -> -1.1315305 | AA12: 按建议广告费率执行，月度复盘
A13: 木工钉枪 | B13: 新款大钉枪-两用无刷 | C13: 清货 | D13: 维持 | E13: 606981.62 | F13: =IFERROR(E13/规则参数!$B$8,0) -> 0.018576109 | G13: 71748.5 | H13: =IFERROR(G13/规则参数!$B$9,0) -> 0.015947259 | I13: 81071.07 | J13: =IFERROR(I13/规则参数!$B$10,0) -> 0.016744209 | K13: =IFERROR(I13/E13,0) -> 0.13356429 | L13: =IFERROR(G13/E13,0) -> 0.11820539 | M13: =K13+L13 -> 0.25176968 | N13: 65735.95 | O13: 3477.27 | P13: 11352.89 | Q13: 504.96 | R13: 53085.98 | S13: 32427.04 | T13: =IFERROR(R13/S13-1,"") -> 0.63708991 | U13: 1543 | V13: 0.1336 | W13: =R13*K13 -> 7090.3913 | X13: =R13*V13 -> 7092.2869 | Y13: =X13-W13 -> 1.8956232 | AA13: 按建议广告费率执行，月度复盘
A14: 锂电油泵 | B14: 锂电油泵-手提5GPM手动款 | C14: 成熟 | D14: 加投 | E14: 763675.52 | F14: =IFERROR(E14/规则参数!$B$8,0) -> 0.023371581 | G14: 201578.02 | H14: =IFERROR(G14/规则参数!$B$9,0) -> 0.044803961 | I14: 80015.46 | J14: =IFERROR(I14/规则参数!$B$10,0) -> 0.016526186 | K14: =IFERROR(I14/E14,0) -> 0.10477678 | L14: =IFERROR(G14/E14,0) -> 0.26395768 | M14: =K14+L14 -> 0.36873446 | N14: 59968.42 | O14: 17493.75 | P14: 1322.59 | Q14: 1230.7 | R14: 32841.45 | S14: 31176.88 | T14: =IFERROR(R14/S14-1,"") -> 0.053391167 | U14: 9283 | V14: 0.1362 | W14: =R14*K14 -> 3441.0213 | X14: =R14*V14 -> 4473.0055 | Y14: =X14-W14 -> 1031.9842 | Z14: 净毛利率 ≥15%、广告费率 ≤12%，有放量空间 | AA14: 利润空间充足：月预算可上调至 $4,473（单月增幅 ≤30%），优先加精准词与 SBV
A15: 锯片机 | B15: 万用宝锯片机-6挡 | C15: 成熟 | D15: 维持 | E15: 507494.1 | F15: =IFERROR(E15/规则参数!$B$8,0) -> 0.015531386 | G15: 38877.74 | H15: =IFERROR(G15/规则参数!$B$9,0) -> 0.0086412037 | I15: 78750.47 | J15: =IFERROR(I15/规则参数!$B$10,0) -> 0.016264918 | K15: =IFERROR(I15/E15,0) -> 0.15517514 | L15: =IFERROR(G15/E15,0) -> 0.076607275 | M15: =K15+L15 -> 0.23178242 | N15: 78617.05 | O15: -171.38 | P15: 302.37 | Q15: 2.43 | R15: 45064.46 | S15: 44682.53 | T15: =IFERROR(R15/S15-1,"") -> 0.008547636 | U15: 6975 | V15: 0.1318 | W15: =R15*K15 -> 6992.8841 | X15: =R15*V15 -> 5939.4958 | Y15: =X15-W15 -> -1053.3882 | AA15: 按建议广告费率执行，月度复盘
A16: 黄油枪 | B16: 黄油枪-无刷三速款 | C16: 成熟 | D16: 维持 | E16: 578968.87 | F16: =IFERROR(E16/规则参数!$B$8,0) -> 0.017718805 | G16: 111875.31 | H16: =IFERROR(G16/规则参数!$B$9,0) -> 0.024866089 | I16: 77924.03 | J16: =IFERROR(I16/规则参数!$B$10,0) -> 0.016094227 | K16: =IFERROR(I16/E16,0) -> 0.13459105 | L16: =IFERROR(G16/E16,0) -> 0.193232 | M16: =K16+L16 -> 0.32782305 | N16: 65339.67 | O16: 3005.09 | P16: 5711.58 | Q16: 3867.69 | R16: 66609.85 | S16: 62333.53 | T16: =IFERROR(R16/S16-1,"") -> 0.068603848 | U16: 4424 | V16: 0.1346 | W16: =R16*K16 -> 8965.0899 | X16: =R16*V16 -> 8965.6858 | Y16: =X16-W16 -> 0.59594309 | AA16: 按建议广告费率执行，月度复盘
A17: 充气泵 | B17: 充气泵-手持低价版 | C17: 成熟 | D17: 维持 | E17: 548585.89 | F17: =IFERROR(E17/规则参数!$B$8,0) -> 0.016788962 | G17: 89283.64 | H17: =IFERROR(G17/规则参数!$B$9,0) -> 0.019844727 | I17: 77263.64 | J17: =IFERROR(I17/规则参数!$B$10,0) -> 0.015957832 | K17: =IFERROR(I17/E17,0) -> 0.14084146 | L17: =IFERROR(G17/E17,0) -> 0.16275234 | M17: =K17+L17 -> 0.30359381 | N17: 67658.81 | O17: 6096.79 | P17: 2107.87 | Q17: 1400.17 | R17: 76791.18 | S17: 48707.94 | T17: =IFERROR(R17/S17-1,"") -> 0.5765639 | U17: 6169 | V17: 0.1408 | W17: =R17*K17 -> 10815.382 | X17: =R17*V17 -> 10812.198 | Y17: =X17-W17 -> -3.1840867 | AA17: 按建议广告费率执行，月度复盘
A18: 灯具 | B18: 工作灯-薄款双开关7寸29W | C18: 成熟 | D18: 维持 | E18: 482241.19 | F18: =IFERROR(E18/规则参数!$B$8,0) -> 0.014758544 | G18: 72155.78 | H18: =IFERROR(G18/规则参数!$B$9,0) -> 0.016037784 | I18: 71200.38 | J18: =IFERROR(I18/规则参数!$B$10,0) -> 0.014705542 | K18: =IFERROR(I18/E18,0) -> 0.14764475 | L18: =IFERROR(G18/E18,0) -> 0.14962592 | M18: =K18+L18 -> 0.29727067 | N18: 60381.21 | O18: 3624.64 | P18: 6637.99 | Q18: 556.54 | R18: 51367.23 | S18: 28856.42 | T18: =IFERROR(R18/S18-1,"") -> 0.78009712 | U18: 2534 | V18: 0.1476 | W18: =R18*K18 -> 7584.1018 | X18: =R18*V18 -> 7581.8031 | Y18: =X18-W18 -> -2.2986902 | AA18: 按建议广告费率执行，月度复盘
A19: 修边机 | B19: 修边机-6件刀头装 | C19: 成熟 | D19: 维持 | E19: 489511.78 | F19: =IFERROR(E19/规则参数!$B$8,0) -> 0.014981054 | G19: 78854.32 | H19: =IFERROR(G19/规则参数!$B$9,0) -> 0.017526642 | I19: 64664.87 | J19: =IFERROR(I19/规则参数!$B$10,0) -> 0.013355715 | K19: =IFERROR(I19/E19,0) -> 0.13210074 | L19: =IFERROR(G19/E19,0) -> 0.16108769 | M19: =K19+L19 -> 0.29318843 | N19: 63368.51 | O19: 195.31 | P19: 952.95 | Q19: 148.1 | R19: 18791.39 | S19: 23866.4 | T19: =IFERROR(R19/S19-1,"") -> -0.21264246 | U19: 1675 | V19: 0.1321 | W19: =R19*K19 -> 2482.3566 | X19: =R19*V19 -> 2482.3426 | Y19: =X19-W19 -> -0.013967943 | AA19: 按建议广告费率执行，月度复盘
A20: 木工钉枪 | B20: 大钉枪-两用款 | C20: 清货 | D20: 维持 | E20: 472895.11 | F20: =IFERROR(E20/规则参数!$B$8,0) -> 0.014472516 | G20: 65366.99 | H20: =IFERROR(G20/规则参数!$B$9,0) -> 0.014528866 | I20: 64382.1 | J20: =IFERROR(I20/规则参数!$B$10,0) -> 0.013297312 | K20: =IFERROR(I20/E20,0) -> 0.13614457 | L20: =IFERROR(G20/E20,0) -> 0.13822725 | M20: =K20+L20 -> 0.27437182 | N20: 59889.73 | O20: 3765.34 | P20: 704.9 | Q20: 22.13 | R20: 33634.63 | S20: 37885.15 | T20: =IFERROR(R20/S20-1,"") -> -0.11219488 | U20: 2029 | V20: 0.1361 | W20: =R20*K20 -> 4579.1721 | X20: =R20*V20 -> 4577.6731 | Y20: =X20-W20 -> -1.4989955 | AA20: 按建议广告费率执行，月度复盘
A21: 风扇 | B21: 风扇-6寸 | C21: 清货 | D21: 观察 | E21: 250330.47 | F21: =IFERROR(E21/规则参数!$B$8,0) -> 0.0076611317 | G21: 16450.35 | H21: =IFERROR(G21/规则参数!$B$9,0) -> 0.0036563552 | I21: 63163.35 | J21: =IFERROR(I21/规则参数!$B$10,0) -> 0.013045595 | K21: =IFERROR(I21/E21,0) -> 0.25231986 | L21: =IFERROR(G21/E21,0) -> 0.065714533 | M21: =K21+L21 -> 0.3180344 | N21: 54757.38 | O21: 1694.65 | P21: 4745.96 | Q21: 1965.36 | R21: 960.1 | S21: 14046.22 | T21: =IFERROR(R21/S21-1,"") -> -0.93164709 | U21: 11 | V21: 0.15 | W21: =R21*K21 -> 242.2523 | X21: =R21*V21 -> 144.015 | Y21: =X21-W21 -> -98.237301 | Z21: 广告费率 ≥20% | AA21: 广告费率 25.2% 偏高（保本 31.8%）：砍高花费 0 单词和 ACOS 超保本的投放，4 周内降到 15.0%；连续 4 周无改善转压缩
A22: 冲击扳手 | B22: 冲击扳手-3/4英寸2200N | C22: 成熟 | D22: 加投 | E22: 532873.06 | F22: =IFERROR(E22/规则参数!$B$8,0) -> 0.016308085 | G22: 124867.05 | H22: =IFERROR(G22/规则参数!$B$9,0) -> 0.027753712 | I22: 55922.91 | J22: =IFERROR(I22/规则参数!$B$10,0) -> 0.011550173 | K22: =IFERROR(I22/E22,0) -> 0.10494603 | L22: =IFERROR(G22/E22,0) -> 0.23432795 | M22: =K22+L22 -> 0.33927397 | N22: 53628.46 | O22: 371.77 | P22: -0.57 | Q22: 1923.25 | R22: 58386.69 | S22: 47492.73 | T22: =IFERROR(R22/S22-1,"") -> 0.22938163 | U22: 1072 | V22: 0.1364 | W22: =R22*K22 -> 6127.4511 | X22: =R22*V22 -> 7963.9445 | Y22: =X22-W22 -> 1836.4934 | Z22: 净毛利率 ≥15%、广告费率 ≤12%，有放量空间 | AA22: 利润空间充足：月预算可上调至 $7,966（单月增幅 ≤30%），优先加精准词与 SBV
A23: 热风枪 | B23: 热风枪-双温基础款5件套 | C23: 成熟 | D23: 维持 | E23: 274351.02 | F23: =IFERROR(E23/规则参数!$B$8,0) -> 0.0083962584 | G23: 37480.64 | H23: =IFERROR(G23/规则参数!$B$9,0) -> 0.0083306757 | I23: 53808 | J23: =IFERROR(I23/规则参数!$B$10,0) -> 0.011113365 | K23: =IFERROR(I23/E23,0) -> 0.1961283 | L23: =IFERROR(G23/E23,0) -> 0.13661564 | M23: =K23+L23 -> 0.33274394 | N23: 45781 | O23: 2207.73 | P23: 4418.98 | Q23: 1400.29 | R23: 27038.79 | S23: 15939.5 | T23: =IFERROR(R23/S23-1,"") -> 0.69633866 | U23: 2457 | V23: 0.18 | W23: =R23*K23 -> 5303.072 | X23: =R23*V23 -> 4866.9822 | Y23: =X23-W23 -> -436.0898 | AA23: 按建议广告费率执行，月度复盘
A24: 修枝剪 | B24: 修枝剪-数显3.0cm | C24: 清货 | D24: 加投 | E24: 449731.87 | F24: =IFERROR(E24/规则参数!$B$8,0) -> 0.013763627 | G24: 69979.54 | H24: =IFERROR(G24/规则参数!$B$9,0) -> 0.01555408 | I24: 50385.73 | J24: =IFERROR(I24/规则参数!$B$10,0) -> 0.010406538 | K24: =IFERROR(I24/E24,0) -> 0.11203504 | L24: =IFERROR(G24/E24,0) -> 0.1556028 | M24: =K24+L24 -> 0.26763785 | N24: 48072.72 | O24: -11.55 | P24: 919.62 | Q24: 1404.94 | R24: 38992.07 | S24: 39009.02 | T24: =IFERROR(R24/S24-1,"") -> -0.00043451489 | U24: 2715 | V24: 0.1456 | W24: =R24*K24 -> 4368.4783 | X24: =R24*V24 -> 5677.2454 | Y24: =X24-W24 -> 1308.7671 | Z24: 净毛利率 ≥15%、广告费率 ≤12%，有放量空间 | AA24: 利润空间充足：月预算可上调至 $5,679（单月增幅 ≤30%），优先加精准词与 SBV
A25: 圆锯 | B25: 电圆锯-7.25英寸新款 | C25: 清货 | D25: 维持 | E25: 283652.57 | F25: =IFERROR(E25/规则参数!$B$8,0) -> 0.0086809237 | G25: 39696.23 | H25: =IFERROR(G25/规则参数!$B$9,0) -> 0.0088231263 | I25: 46772.97 | J25: =IFERROR(I25/规则参数!$B$10,0) -> 0.0096603682 | K25: =IFERROR(I25/E25,0) -> 0.16489528 | L25: =IFERROR(G25/E25,0) -> 0.13994666 | M25: =K25+L25 -> 0.30484194 | N25: 44440.76 | O25: 412.59 | P25: 1905.14 | Q25: 14.48 | R25: 32921.92 | S25: 25838.31 | T25: =IFERROR(R25/S25-1,"") -> 0.27415144 | U25: 740 | V25: 0.15 | W25: =R25*K25 -> 5428.6692 | X25: =R25*V25 -> 4938.288 | Y25: =X25-W25 -> -490.38122 | AA25: 按建议广告费率执行，月度复盘
A26: 冲击起子 | B26: 冲击起子-280N | C26: 成熟 | D26: 观察 | E26: 148892.48 | F26: =IFERROR(E26/规则参数!$B$8,0) -> 0.0045567162 | G26: 18287.22 | H26: =IFERROR(G26/规则参数!$B$9,0) -> 0.0040646291 | I26: 44966.8 | J26: =IFERROR(I26/规则参数!$B$10,0) -> 0.0092873265 | K26: =IFERROR(I26/E26,0) -> 0.30200854 | L26: =IFERROR(G26/E26,0) -> 0.12282165 | M26: =K26+L26 -> 0.42483019 | N26: 44741.93 | O26: -75.96 | P26: -7.28 | Q26: 308.11 | R26: 15241.75 | S26: 13136.66 | T26: =IFERROR(R26/S26-1,"") -> 0.16024545 | U26: 793 | V26: 0.18 | W26: =R26*K26 -> 4603.1386 | X26: =R26*V26 -> 2743.515 | Y26: =X26-W26 -> -1859.6236 | Z26: 广告费率 ≥20% | AA26: 广告费率 30.2% 偏高（保本 42.5%）：砍高花费 0 单词和 ACOS 超保本的投放，4 周内降到 18.0%；连续 4 周无改善转压缩
A27: 割草机 | B27: 打草机-无刷800W | C27: 清货 | D27: 止损 | E27: 344145.18 | F27: =IFERROR(E27/规则参数!$B$8,0) -> 0.010532244 | G27: -36953.05 | H27: =IFERROR(G27/规则参数!$B$9,0) -> -0.0082134103 | I27: 44617.11 | J27: =IFERROR(I27/规则参数!$B$10,0) -> 0.0092151024 | K27: =IFERROR(I27/E27,0) -> 0.12964619 | L27: =IFERROR(G27/E27,0) -> -0.10737634 | M27: =K27+L27 -> 0.022269846 | N27: 40189.33 | O27: 2956.73 | P27: 1031.15 | Q27: 439.9 | R27: 15546.79 | S27: 37843.79 | T27: =IFERROR(R27/S27-1,"") -> -0.58918517 | U27: 1362 | V27: 0 | W27: =R27*K27 -> 2015.582 | X27: =R27*V27 -> 0 | Y27: =X27-W27 -> -2015.582 | Z27: 广告后毛利为负，广告费率 > 广告前毛利率 | AA27: 广告费率 13.0% 已超过广告前毛利率 2.2%：先停泛词/自动广告，只留品牌词与高转化精准词；同步复核定价与采购成本，2 周内毛利转正再恢复
A28: 喷雾器 | B28: 电动喷雾器-16L | C28: 成熟 | D28: 观察 | E28: 267894.4 | F28: =IFERROR(E28/规则参数!$B$8,0) -> 0.0081986595 | G28: 50441.16 | H28: =IFERROR(G28/规则参数!$B$9,0) -> 0.01121136 | I28: 44150.66 | J28: =IFERROR(I28/规则参数!$B$10,0) -> 0.009118763 | K28: =IFERROR(I28/E28,0) -> 0.16480621 | L28: =IFERROR(G28/E28,0) -> 0.18828747 | M28: =K28+L28 -> 0.35309368 | N28: 43214.98 | O28: 627.48 | P28: 308.2 | Q28: 0 | R28: 8225.49 | S28: 17942.28 | T28: =IFERROR(R28/S28-1,"") -> -0.54155826 | U28: 385 | V28: 0.1648 | W28: =R28*K28 -> 1355.6118 | X28: =R28*V28 -> 1355.5608 | Y28: =X28-W28 -> -0.051057442 | Z28: 近 30 天销售环比下滑 ≥30% | AA28: 近 30 天销售环比 -54%，广告要跟着降：预算按近 30 天销售重算为 $1,356/月，排查排名、断货、差评或竞品降价
A29: 热风枪 | B29: 热风枪-双温数显款5件套 | C29: 成熟 | D29: 维持 | E29: 301359.11 | F29: =IFERROR(E29/规则参数!$B$8,0) -> 0.0092228159 | G29: 59375.34 | H29: =IFERROR(G29/规则参数!$B$9,0) -> 0.013197125 | I29: 42076.55 | J29: =IFERROR(I29/规则参数!$B$10,0) -> 0.0086903817 | K29: =IFERROR(I29/E29,0) -> 0.13962262 | L29: =IFERROR(G29/E29,0) -> 0.1970252 | M29: =K29+L29 -> 0.33664783 | N29: 35737.81 | O29: 1343.09 | P29: 3751.72 | Q29: 1243.93 | R29: 30127.89 | S29: 24648.5 | T29: =IFERROR(R29/S29-1,"") -> 0.22230115 | U29: 2838 | V29: 0.1396 | W29: =R29*K29 -> 4206.5351 | X29: =R29*V29 -> 4205.8534 | Y29: =X29-W29 -> -0.68164293 | AA29: 按建议广告费率执行，月度复盘
A30: 微耕机 | B30: 微耕机-四折叠基础款 | C30: 成熟 | D30: 观察 | E30: 332642.57 | F30: =IFERROR(E30/规则参数!$B$8,0) -> 0.010180217 | G30: 37891.96 | H30: =IFERROR(G30/规则参数!$B$9,0) -> 0.0084220982 | I30: 39351.48 | J30: =IFERROR(I30/规则参数!$B$10,0) -> 0.0081275528 | K30: =IFERROR(I30/E30,0) -> 0.11829959 | L30: =IFERROR(G30/E30,0) -> 0.11391194 | M30: =K30+L30 -> 0.23221153 | N30: 33661.69 | O30: 3754.3 | P30: 1824.18 | Q30: 111.31 | R30: 7102.88 | S30: 11112.35 | T30: =IFERROR(R30/S30-1,"") -> -0.36081207 | U30: 162 | V30: 0.1183 | W30: =R30*K30 -> 840.2678 | X30: =R30*V30 -> 840.2707 | Y30: =X30-W30 -> 0.0029046549 | Z30: 近 30 天销售环比下滑 ≥30% | AA30: 近 30 天销售环比 -36%，广告要跟着降：预算按近 30 天销售重算为 $840/月，排查排名、断货、差评或竞品降价
A31: 锂电油泵 | B31: 锂电油泵-手提款-两用自动+手动5.0GPM | C31: 新品期 | D31: 观察 | E31: 260873.73 | F31: =IFERROR(E31/规则参数!$B$8,0) -> 0.0079837984 | G31: 43558.11 | H31: =IFERROR(G31/规则参数!$B$9,0) -> 0.0096814913 | I31: 38275.94 | J31: =IFERROR(I31/规则参数!$B$10,0) -> 0.0079054136 | K31: =IFERROR(I31/E31,0) -> 0.14672209 | L31: =IFERROR(G31/E31,0) -> 0.16697009 | M31: =K31+L31 -> 0.31369218 | N31: 27631.07 | O31: 6257.2 | P31: 2356.49 | Q31: 2031.18 | R31: 49285.26 | S31: 78687.53 | T31: =IFERROR(R31/S31-1,"") -> -0.37365857 | U31: 1926 | V31: 0.1467 | W31: =R31*K31 -> 7231.2366 | X31: =R31*V31 -> 7230.1476 | Y31: =X31-W31 -> -1.0889208 | Z31: 近 30 天销售环比下滑 ≥30% | AA31: 近 30 天销售环比 -37%，广告要跟着降：预算按近 30 天销售重算为 $7,231/月，排查排名、断货、差评或竞品降价
A32: 冲击电钻 | B32: 锂电钻-13mm 90N.m | C32: 成熟 | D32: 维持 | E32: 243673.24 | F32: =IFERROR(E32/规则参数!$B$8,0) -> 0.0074573934 | G32: 22373.83 | H32: =IFERROR(G32/规则参数!$B$9,0) -> 0.004972944 | I32: 36000.66 | J32: =IFERROR(I32/规则参数!$B$10,0) -> 0.0074354831 | K32: =IFERROR(I32/E32,0) -> 0.14774154 | L32: =IFERROR(G32/E32,0) -> 0.091818987 | M32: =K32+L32 -> 0.23956053 | N32: 35815.09 | O32: 17.89 | P32: 0.73 | Q32: 166.95 | R32: 43261 | S32: 40914.61 | T32: =IFERROR(R32/S32-1,"") -> 0.057348463 | U32: 3329 | V32: 0.1396 | W32: =R32*K32 -> 6391.4468 | X32: =R32*V32 -> 6039.2356 | Y32: =X32-W32 -> -352.21121 | AA32: 按建议广告费率执行，月度复盘
A33: 防辐射测试仪 | B33: 电磁辐射检测仪-手持款 | C33: 成熟 | D33: 维持 | E33: 297895.57 | F33: =IFERROR(E33/规则参数!$B$8,0) -> 0.0091168175 | G33: 53505.46 | H33: =IFERROR(G33/规则参数!$B$9,0) -> 0.01189245 | I33: 35945 | J33: =IFERROR(I33/规则参数!$B$10,0) -> 0.0074239873 | K33: =IFERROR(I33/E33,0) -> 0.12066309 | L33: =IFERROR(G33/E33,0) -> 0.17961147 | M33: =K33+L33 -> 0.30027456 | N33: 35945 | O33: 0 | P33: 0 | Q33: 0 | R33: 51265.33 | S33: 22961.83 | T33: =IFERROR(R33/S33-1,"") -> 1.2326326 | U33: 4813 | V33: 0.1207 | W33: =R33*K33 -> 6185.8331 | X33: =R33*V33 -> 6187.7253 | Y33: =X33-W33 -> 1.8921988 | AA33: 按建议广告费率执行，月度复盘
A34: 充气泵 | B34: 充气泵-卧式双供电26气缸 | C34: 新品期 | D34: 观察 | E34: 168703.85 | F34: =IFERROR(E34/规则参数!$B$8,0) -> 0.0051630248 | G34: 4916.72 | H34: =IFERROR(G34/规则参数!$B$9,0) -> 0.0010928202 | I34: 35581.83 | J34: =IFERROR(I34/规则参数!$B$10,0) -> 0.0073489791 | K34: =IFERROR(I34/E34,0) -> 0.21091297 | L34: =IFERROR(G34/E34,0) -> 0.029144089 | M34: =K34+L34 -> 0.24005706 | N34: 35234.85 | O34: 270.28 | P34: 76.7 | Q34: 0 | R34: 42183.49 | S34: 26869.06 | T34: =IFERROR(R34/S34-1,"") -> 0.56996523 | U34: 5636 | V34: 0.2109 | W34: =R34*K34 -> 8897.0451 | X34: =R34*V34 -> 8896.498 | Y34: =X34-W34 -> -0.54710638 | Z34: 新品期：净毛利 <5%，处于保本投放容忍期（≤90 天） | AA34: 新品保本期：广告费率不超过 21.1%（保本 24.0%）；90 天内净毛利未到 5% 转入压缩
A35: 刨木机 | B35: 刨木机-普通款 | C35: 成熟 | D35: 维持 | E35: 271360.02 | F35: =IFERROR(E35/规则参数!$B$8,0) -> 0.0083047216 | G35: 40097.51 | H35: =IFERROR(G35/规则参数!$B$9,0) -> 0.0089123172 | I35: 35422.04 | J35: =IFERROR(I35/规则参数!$B$10,0) -> 0.0073159765 | K35: =IFERROR(I35/E35,0) -> 0.13053522 | L35: =IFERROR(G35/E35,0) -> 0.14776499 | M35: =K35+L35 -> 0.27830021 | N35: 28331.72 | O35: 1692.01 | P35: 4537.09 | Q35: 861.22 | R35: 31161.98 | S35: 20224.36 | T35: =IFERROR(R35/S35-1,"") -> 0.54081415 | U35: 1286 | V35: 0.1305 | W35: =R35*K35 -> 4067.7359 | X35: =R35*V35 -> 4066.6384 | Y35: =X35-W35 -> -1.0975353 | AA35: 按建议广告费率执行，月度复盘
A36: 电源逆变器 | B36: 逆变器-550W | C36: 成熟 | D36: 加投 | E36: 393243.09 | F36: =IFERROR(E36/规则参数!$B$8,0) -> 0.01203484 | G36: 69042.97 | H36: =IFERROR(G36/规则参数!$B$9,0) -> 0.015345912 | I36: 35350.94 | J36: =IFERROR(I36/规则参数!$B$10,0) -> 0.0073012917 | K36: =IFERROR(I36/E36,0) -> 0.089895896 | L36: =IFERROR(G36/E36,0) -> 0.17557326 | M36: =K36+L36 -> 0.26546915 | N36: 31798.61 | O36: 1748.2 | P36: 194.48 | Q36: 1609.65 | R36: 33005.06 | S36: 26294.33 | T36: =IFERROR(R36/S36-1,"") -> 0.25521586 | U36: 955 | V36: 0.1169 | W36: =R36*K36 -> 2967.0194 | X36: =R36*V36 -> 3858.2915 | Y36: =X36-W36 -> 891.27207 | Z36: 净毛利率 ≥15%、广告费率 ≤12%，有放量空间 | AA36: 利润空间充足：月预算可上调至 $3,857（单月增幅 ≤30%），优先加精准词与 SBV
A37: 木工钉枪 | B37: 钉枪-小型两用 | C37: 清货 | D37: 观察 | E37: 181025.33 | F37: =IFERROR(E37/规则参数!$B$8,0) -> 0.0055401122 | G37: 28205.98 | H37: =IFERROR(G37/规则参数!$B$9,0) -> 0.0062692332 | I37: 34046.42 | J37: =IFERROR(I37/规则参数!$B$10,0) -> 0.0070318595 | K37: =IFERROR(I37/E37,0) -> 0.18807545 | L37: =IFERROR(G37/E37,0) -> 0.15581234 | M37: =K37+L37 -> 0.34388779 | N37: 32417.86 | O37: 1155.84 | P37: 472.72 | Q37: 0 | R37: 8492.32 | S37: 22702.27 | T37: =IFERROR(R37/S37-1,"") -> -0.62592639 | U37: 578 | V37: 0.15 | W37: =R37*K37 -> 1597.1969 | X37: =R37*V37 -> 1273.848 | Y37: =X37-W37 -> -323.34889 | Z37: 近 30 天销售环比下滑 ≥30% | AA37: 近 30 天销售环比 -63%，广告要跟着降：预算按近 30 天销售重算为 $1,274/月，排查排名、断货、差评或竞品降价
A38: 冲击扳手 | B38: 冲击扳手-3/8英寸340N | C38: 成熟 | D38: 观察 | E38: 145227.14 | F38: =IFERROR(E38/规则参数!$B$8,0) -> 0.0044445418 | G38: 33323.94 | H38: =IFERROR(G38/规则参数!$B$9,0) -> 0.0074067822 | I38: 32184.92 | J38: =IFERROR(I38/规则参数!$B$10,0) -> 0.0066473901 | K38: =IFERROR(I38/E38,0) -> 0.22161781 | L38: =IFERROR(G38/E38,0) -> 0.22946083 | M38: =K38+L38 -> 0.45107863 | N38: 32214.39 | O38: -76.64 | P38: 47.17 | Q38: 0 | R38: 13161.18 | S38: 13161.5 | T38: =IFERROR(R38/S38-1,"") -> -2.4313338e-05 | U38: 697 | V38: 0.18 | W38: =R38*K38 -> 2916.7518 | X38: =R38*V38 -> 2369.0124 | Y38: =X38-W38 -> -547.73942 | Z38: 广告费率 ≥20% | AA38: 广告费率 22.2% 偏高（保本 45.1%）：砍高花费 0 单词和 ACOS 超保本的投放，4 周内降到 18.0%；连续 4 周无改善转压缩
A39: 电源逆变器 | B39: 逆变器-350W PD20W | C39: 清货 | D39: 止损 | E39: 115886.94 | F39: =IFERROR(E39/规则参数!$B$8,0) -> 0.0035466122 | G39: -13300.19 | H39: =IFERROR(G39/规则参数!$B$9,0) -> -0.0029561814 | I39: 30462.31 | J39: =IFERROR(I39/规则参数!$B$10,0) -> 0.0062916067 | K39: =IFERROR(I39/E39,0) -> 0.26286232 | L39: =IFERROR(G39/E39,0) -> -0.11476867 | M39: =K39+L39 -> 0.14809365 | N39: 28196.77 | O39: 1860.54 | P39: 138.7 | Q39: 266.3 | R39: 3876.14 | S39: 3811.64 | T39: =IFERROR(R39/S39-1,"") -> 0.01692185 | U39: 499 | V39: 0.0981 | W39: =R39*K39 -> 1018.8912 | X39: =R39*V39 -> 380.24933 | Y39: =X39-W39 -> -638.64182 | Z39: 广告后毛利为负，广告费率 > 广告前毛利率 | AA39: 广告费率 26.3% 已超过广告前毛利率 14.8%：先停泛词/自动广告，只留品牌词与高转化精准词；同步复核定价与采购成本，2 周内毛利转正再恢复
A40: 吹尘枪 | B40: 吹尘枪-5个喷嘴+2条软管 | C40: 成熟 | D40: 维持 | E40: 241434.02 | F40: =IFERROR(E40/规则参数!$B$8,0) -> 0.0073888641 | G40: 30406.61 | H40: =IFERROR(G40/规则参数!$B$9,0) -> 0.0067583586 | I40: 29105.81 | J40: =IFERROR(I40/规则参数!$B$10,0) -> 0.0060114387 | K40: =IFERROR(I40/E40,0) -> 0.12055389 | L40: =IFERROR(G40/E40,0) -> 0.1259417 | M40: =K40+L40 -> 0.24649559 | N40: 28752.97 | O40: 39.74 | P40: 102.81 | Q40: 210.29 | R40: 17238.51 | S40: 16238.08 | T40: =IFERROR(R40/S40-1,"") -> 0.061610116 | U40: 6873 | V40: 0.1206 | W40: =R40*K40 -> 2078.1694 | X40: =R40*V40 -> 2078.9643 | Y40: =X40-W40 -> 0.79488835 | AA40: 按建议广告费率执行，月度复盘
A41: 充气泵 | B41: 充气泵-快充版 | C41: 成熟 | D41: 止损 | E41: 141065.16 | F41: =IFERROR(E41/规则参数!$B$8,0) -> 0.0043171683 | G41: -2184.47 | H41: =IFERROR(G41/规则参数!$B$9,0) -> -0.00048553363 | I41: 28758.32 | J41: =IFERROR(I41/规则参数!$B$10,0) -> 0.005939669 | K41: =IFERROR(I41/E41,0) -> 0.2038655 | L41: =IFERROR(G41/E41,0) -> -0.015485539 | M41: =K41+L41 -> 0.18837997 | N41: 28382.59 | O41: 196.14 | P41: 100.92 | Q41: 78.67 | R41: 15635.5 | S41: 13375.77 | T41: =IFERROR(R41/S41-1,"") -> 0.16894205 | U41: 1868 | V41: 0.0884 | W41: =R41*K41 -> 3187.5391 | X41: =R41*V41 -> 1382.1782 | Y41: =X41-W41 -> -1805.3609 | Z41: 广告后毛利为负，广告费率 > 广告前毛利率 | AA41: 广告费率 20.4% 已超过广告前毛利率 18.8%：先停泛词/自动广告，只留品牌词与高转化精准词；同步复核定价与采购成本，2 周内毛利转正再恢复
A42: 锯片机 | B42: 万用宝-套装 | C42: 成熟 | D42: 维持 | E42: 185849.76 | F42: =IFERROR(E42/规则参数!$B$8,0) -> 0.0056877594 | G42: 13420.86 | H42: =IFERROR(G42/规则参数!$B$9,0) -> 0.0029830022 | I42: 28323.76 | J42: =IFERROR(I42/规则参数!$B$10,0) -> 0.0058499161 | K42: =IFERROR(I42/E42,0) -> 0.15240138 | L42: =IFERROR(G42/E42,0) -> 0.072213491 | M42: =K42+L42 -> 0.22461487 | N42: 25804.88 | O42: 114.58 | P42: 2261.32 | Q42: 142.98 | R42: 20710.74 | S42: 16925.44 | T42: =IFERROR(R42/S42-1,"") -> 0.22364559 | U42: 2192 | V42: 0.1246 | W42: =R42*K42 -> 3156.3454 | X42: =R42*V42 -> 2580.5582 | Y42: =X42-W42 -> -575.78716 | AA42: 按建议广告费率执行，月度复盘
A43: 电源逆变器 | B43: 逆变器-350W修正波版 | C43: 新品期 | D43: 观察 | E43: 117874.23 | F43: =IFERROR(E43/规则参数!$B$8,0) -> 0.0036074314 | G43: -15546.22 | H43: =IFERROR(G43/规则参数!$B$9,0) -> -0.0034553977 | I43: 27354.75 | J43: =IFERROR(I43/规则参数!$B$10,0) -> 0.0056497793 | K43: =IFERROR(I43/E43,0) -> 0.23206726 | L43: =IFERROR(G43/E43,0) -> -0.1318882 | M43: =K43+L43 -> 0.10017906 | N43: 24947.12 | O43: 1126.57 | P43: 617.77 | Q43: 663.29 | R43: 18349.44 | S43: 27620.58 | T43: =IFERROR(R43/S43-1,"") -> -0.33566058 | U43: 4243 | V43: 0.1002 | W43: =R43*K43 -> 4258.3043 | X43: =R43*V43 -> 1838.6139 | Y43: =X43-W43 -> -2419.6904 | Z43: 新品期：净毛利 <5%，处于保本投放容忍期（≤90 天） | AA43: 新品保本期：广告费率不超过 10.0%（保本 10.0%）；90 天内净毛利未到 5% 转入压缩
A44: 锂电油泵 | B44: 锂电油泵-手提5GPM自动款 | C44: 成熟 | D44: 维持 | E44: 224928.06 | F44: =IFERROR(E44/规则参数!$B$8,0) -> 0.0068837145 | G44: 66449.88 | H44: =IFERROR(G44/规则参数!$B$9,0) -> 0.014769556 | I44: 27326.13 | J44: =IFERROR(I44/规则参数!$B$10,0) -> 0.0056438682 | K44: =IFERROR(I44/E44,0) -> 0.12148831 | L44: =IFERROR(G44/E44,0) -> 0.29542726 | M44: =K44+L44 -> 0.41691557 | N44: 19127.8 | O44: 7438.66 | P44: 320.59 | Q44: 439.08 | R44: 16723.39 | S44: 20314.73 | T44: =IFERROR(R44/S44-1,"") -> -0.17678502 | U44: 2860 | V44: 0.1215 | W44: =R44*K44 -> 2031.6964 | X44: =R44*V44 -> 2031.8919 | Y44: =X44-W44 -> 0.19548758 | AA44: 按建议广告费率执行，月度复盘
A45: 混凝土振动器 | B45: 混凝土振动器-震动棒1.2米 | C45: 成熟 | D45: 加投 | E45: 300917.23 | F45: =IFERROR(E45/规则参数!$B$8,0) -> 0.0092092926 | G45: 89554.13 | H45: =IFERROR(G45/规则参数!$B$9,0) -> 0.019904847 | I45: 26885.37 | J45: =IFERROR(I45/规则参数!$B$10,0) -> 0.0055528347 | K45: =IFERROR(I45/E45,0) -> 0.089344734 | L45: =IFERROR(G45/E45,0) -> 0.29760386 | M45: =K45+L45 -> 0.3869486 | N45: 19570.79 | O45: 425.38 | P45: 3935.52 | Q45: 2953.68 | R45: 31115.6 | S45: 30628.46 | T45: =IFERROR(R45/S45-1,"") -> 0.015904815 | U45: 1224 | V45: 0.1161 | W45: =R45*K45 -> 2780.015 | X45: =R45*V45 -> 3612.5212 | Y45: =X45-W45 -> 832.50614 | Z45: 净毛利率 ≥15%、广告费率 ≤12%，有放量空间 | AA45: 利润空间充足：月预算可上调至 $3,614（单月增幅 ≤30%），优先加精准词与 SBV
A46: 充气泵 | B46: 充气泵-12V+20V手持 | C46: 新品期 | D46: 观察 | E46: 90731.07 | F46: =IFERROR(E46/规则参数!$B$8,0) -> 0.0027767402 | G46: -1411.95 | H46: =IFERROR(G46/规则参数!$B$9,0) -> -0.00031382862 | I46: 24808.53 | J46: =IFERROR(I46/规则参数!$B$10,0) -> 0.0051238896 | K46: =IFERROR(I46/E46,0) -> 0.27342927 | L46: =IFERROR(G46/E46,0) -> -0.015561924 | M46: =K46+L46 -> 0.25786734 | N46: 24467.75 | O46: 253.1 | P46: 87.68 | Q46: 0 | R46: 18337.1 | S46: 18268.36 | T46: =IFERROR(R46/S46-1,"") -> 0.0037627899 | U46: 1259 | V46: 0.25 | W46: =R46*K46 -> 5013.8998 | X46: =R46*V46 -> 4584.275 | Y46: =X46-W46 -> -429.62482 | Z46: 新品期：净毛利 <5%，处于保本投放容忍期（≤90 天） | AA46: 新品保本期：广告费率不超过 25.0%（保本 25.8%）；90 天内净毛利未到 5% 转入压缩
A47: 风扇 | B47: 风扇-双开关8寸两档调节 | C47: 清货 | D47: 观察 | E47: 233620.13 | F47: =IFERROR(E47/规则参数!$B$8,0) -> 0.0071497273 | G47: 50017.09 | H47: =IFERROR(G47/规则参数!$B$9,0) -> 0.011117104 | I47: 24429.29 | J47: =IFERROR(I47/规则参数!$B$10,0) -> 0.0050455623 | K47: =IFERROR(I47/E47,0) -> 0.10456843 | L47: =IFERROR(G47/E47,0) -> 0.21409581 | M47: =K47+L47 -> 0.31866423 | N47: 17847.14 | O47: 1146.02 | P47: 3985.32 | Q47: 1450.81 | R47: 7184.02 | S47: 33455.98 | T47: =IFERROR(R47/S47-1,"") -> -0.78526948 | U47: 245 | V47: 0.1046 | W47: =R47*K47 -> 751.22169 | X47: =R47*V47 -> 751.44849 | Y47: =X47-W47 -> 0.22680598 | Z47: 近 30 天销售环比下滑 ≥30% | AA47: 近 30 天销售环比 -79%，广告要跟着降：预算按近 30 天销售重算为 $751/月，排查排名、断货、差评或竞品降价
A48: 冲击电钻 | B48: 锂电钻+起子机套装-组合套装款 | C48: 成熟 | D48: 观察 | E48: 91014.69 | F48: =IFERROR(E48/规则参数!$B$8,0) -> 0.0027854201 | G48: 5138.8 | H48: =IFERROR(G48/规则参数!$B$9,0) -> 0.001142181 | I48: 24318.37 | J48: =IFERROR(I48/规则参数!$B$10,0) -> 0.0050226532 | K48: =IFERROR(I48/E48,0) -> 0.2671917 | L48: =IFERROR(G48/E48,0) -> 0.056461215 | M48: =K48+L48 -> 0.32365292 | N48: 22611.88 | O48: -47.63 | P48: 12.23 | Q48: 1741.89 | R48: 15027.15 | S48: 6482.74 | T48: =IFERROR(R48/S48-1,"") -> 1.3180245 | U48: 1136 | V48: 0.18 | W48: =R48*K48 -> 4015.1298 | X48: =R48*V48 -> 2704.887 | Y48: =X48-W48 -> -1310.2428 | Z48: 广告费率 ≥20% | AA48: 广告费率 26.7% 偏高（保本 32.4%）：砍高花费 0 单词和 ACOS 超保本的投放，4 周内降到 18.0%；连续 4 周无改善转压缩
A49: 电源逆变器 | B49: 逆变器-尾插300W | C49: 清货 | D49: 止损 | E49: 111194.75 | F49: =IFERROR(E49/规则参数!$B$8,0) -> 0.0034030121 | G49: -9591.51 | H49: =IFERROR(G49/规则参数!$B$9,0) -> -0.0021318675 | I49: 23573.78 | J49: =IFERROR(I49/规则参数!$B$10,0) -> 0.0048688675 | K49: =IFERROR(I49/E49,0) -> 0.21200443 | L49: =IFERROR(G49/E49,0) -> -0.086258659 | M49: =K49+L49 -> 0.12574577 | N49: 22216.73 | O49: 577.94 | P49: 31.02 | Q49: 748.09 | R49: 2228.5 | S49: 4438.09 | T49: =IFERROR(R49/S49-1,"") -> -0.49786958 | U49: 466 | V49: 0.0757 | W49: =R49*K49 -> 472.45188 | X49: =R49*V49 -> 168.69745 | Y49: =X49-W49 -> -303.75443 | Z49: 广告后毛利为负，广告费率 > 广告前毛利率 | AA49: 广告费率 21.2% 已超过广告前毛利率 12.6%：先停泛词/自动广告，只留品牌词与高转化精准词；同步复核定价与采购成本，2 周内毛利转正再恢复
A50: 高枝锯 | B50: 高枝锯-单用有刷8寸 | C50: 清货 | D50: 止损 | E50: 102023.14 | F50: =IFERROR(E50/规则参数!$B$8,0) -> 0.0031223235 | G50: -7370.43 | H50: =IFERROR(G50/规则参数!$B$9,0) -> -0.0016381967 | I50: 22825.83 | J50: =IFERROR(I50/规则参数!$B$10,0) -> 0.0047143879 | K50: =IFERROR(I50/E50,0) -> 0.22373189 | L50: =IFERROR(G50/E50,0) -> -0.072242728 | M50: =K50+L50 -> 0.15148916 | N50: 12628.3 | O50: 1429.63 | P50: 8293.62 | Q50: 474.28 | R50: 13252.09 | S50: 10626.15 | T50: =IFERROR(R50/S50-1,"") -> 0.24712055 | U50: 593 | V50: 0.1015 | W50: =R50*K50 -> 2964.9152 | X50: =R50*V50 -> 1345.0871 | Y50: =X50-W50 -> -1619.828 | Z50: 广告后毛利为负，广告费率 > 广告前毛利率 | AA50: 广告费率 22.4% 已超过广告前毛利率 15.1%：先停泛词/自动广告，只留品牌词与高转化精准词；同步复核定价与采购成本，2 周内毛利转正再恢复
A51: 木工钉枪 | B51: 精加工钉枪-16GA直排 | C51: 清货 | D51: 压缩 | E51: 138701.98 | F51: =IFERROR(E51/规则参数!$B$8,0) -> 0.0042448454 | G51: 5441.42 | H51: =IFERROR(G51/规则参数!$B$9,0) -> 0.0012094432 | I51: 22579.33 | J51: =IFERROR(I51/规则参数!$B$10,0) -> 0.0046634764 | K51: =IFERROR(I51/E51,0) -> 0.16279025 | L51: =IFERROR(G51/E51,0) -> 0.039231019 | M51: =K51+L51 -> 0.20202127 | N51: 20776.37 | O51: 1792.86 | P51: 10.1 | Q51: 0 | R51: 13163.44 | S51: 20829.13 | T51: =IFERROR(R51/S51-1,"") -> -0.36802737 | U51: 561 | V51: 0.15 | W51: =R51*K51 -> 2142.8797 | X51: =R51*V51 -> 1974.516 | Y51: =X51-W51 -> -168.36369 | Z51: 净毛利率 <5% 且广告费率 ≥12% | AA51: 净毛利率 3.9%，广告费率压到 15.0% 以内：砍 ACOS 超保本的词，SB/SD 预算回收到 SP 精准
A52: 激光水平仪 | B52: 激光水平仪-16线4D配三脚支架 | C52: 成熟 | D52: 维持 | E52: 122184.99 | F52: =IFERROR(E52/规则参数!$B$8,0) -> 0.0037393582 | G52: 18750.58 | H52: =IFERROR(G52/规则参数!$B$9,0) -> 0.0041676183 | I52: 22300.42 | J52: =IFERROR(I52/规则参数!$B$10,0) -> 0.004605871 | K52: =IFERROR(I52/E52,0) -> 0.18251358 | L52: =IFERROR(G52/E52,0) -> 0.15346058 | M52: =K52+L52 -> 0.33597417 | N52: 21908.41 | O52: 6.42 | P52: 43.02 | Q52: 342.57 | R52: 27407.67 | S52: 15772.41 | T52: =IFERROR(R52/S52-1,"") -> 0.73769703 | U52: 1270 | V52: 0.18 | W52: =R52*K52 -> 5002.272 | X52: =R52*V52 -> 4933.3806 | Y52: =X52-W52 -> -68.891383 | AA52: 按建议广告费率执行，月度复盘
A53: 冲击扳手 | B53: 冲击扳手-3/8英寸700N | C53: 成熟 | D53: 维持 | E53: 168090.03 | F53: =IFERROR(E53/规则参数!$B$8,0) -> 0.0051442394 | G53: 24098.58 | H53: =IFERROR(G53/规则参数!$B$9,0) -> 0.0053562974 | I53: 21825.3 | J53: =IFERROR(I53/规则参数!$B$10,0) -> 0.004507741 | K53: =IFERROR(I53/E53,0) -> 0.12984292 | L53: =IFERROR(G53/E53,0) -> 0.1433671 | M53: =K53+L53 -> 0.27321002 | N53: 21913.21 | O53: -99.46 | P53: 11.55 | Q53: 0 | R53: 12179.18 | S53: 11598.67 | T53: =IFERROR(R53/S53-1,"") -> 0.050049704 | U53: 394 | V53: 0.1298 | W53: =R53*K53 -> 1581.3803 | X53: =R53*V53 -> 1580.8576 | Y53: =X53-W53 -> -0.52270736 | AA53: 按建议广告费率执行，月度复盘
A54: 水泵 | B54: 直立式输水泵-伸缩 | C54: 清货 | D54: 止损 | E54: 124950.14 | F54: =IFERROR(E54/规则参数!$B$8,0) -> 0.0038239831 | G54: -2967.17 | H54: =IFERROR(G54/规则参数!$B$9,0) -> -0.00065950131 | I54: 21523.54 | J54: =IFERROR(I54/规则参数!$B$10,0) -> 0.0044454162 | K54: =IFERROR(I54/E54,0) -> 0.17225703 | L54: =IFERROR(G54/E54,0) -> -0.023746832 | M54: =K54+L54 -> 0.1485102 | N54: 20206.78 | O54: 134.7 | P54: 1012.73 | Q54: 169.33 | R54: 5289.9 | S54: 7494.51 | T54: =IFERROR(R54/S54-1,"") -> -0.29416333 | U54: 889 | V54: 0.0985 | W54: =R54*K54 -> 911.22246 | X54: =R54*V54 -> 521.05515 | Y54: =X54-W54 -> -390.16731 | Z54: 广告后毛利为负，广告费率 > 广告前毛利率 | AA54: 广告费率 17.2% 已超过广告前毛利率 14.9%：先停泛词/自动广告，只留品牌词与高转化精准词；同步复核定价与采购成本，2 周内毛利转正再恢复
A55: 水泵 | B55: 卧式水泵-有刷款 | C55: 成熟 | D55: 维持 | E55: 131128.99 | F55: =IFERROR(E55/规则参数!$B$8,0) -> 0.004013081 | G55: 16273.02 | H55: =IFERROR(G55/规则参数!$B$9,0) -> 0.0036169407 | I55: 21152.13 | J55: =IFERROR(I55/规则参数!$B$10,0) -> 0.0043687062 | K55: =IFERROR(I55/E55,0) -> 0.16130781 | L55: =IFERROR(G55/E55,0) -> 0.12409933 | M55: =K55+L55 -> 0.28540714 | N55: 18236.42 | O55: 253.9 | P55: 2297.21 | Q55: 364.6 | R55: 16906.35 | S55: 16892.6 | T55: =IFERROR(R55/S55-1,"") -> 0.00081396588 | U55: 173 | V55: 0.1613 | W55: =R55*K55 -> 2727.1263 | X55: =R55*V55 -> 2726.9943 | Y55: =X55-W55 -> -0.13201224 | AA55: 按建议广告费率执行，月度复盘
A56: 管道压接工具 | B56: 电动管道压接工具-炮式 | C56: 成熟 | D56: 维持 | E56: 159128.32 | F56: =IFERROR(E56/规则参数!$B$8,0) -> 0.0048699746 | G56: 22147.03 | H56: =IFERROR(G56/规则参数!$B$9,0) -> 0.004922534 | I56: 20926.16 | J56: =IFERROR(I56/规则参数!$B$10,0) -> 0.0043220349 | K56: =IFERROR(I56/E56,0) -> 0.13150494 | L56: =IFERROR(G56/E56,0) -> 0.13917717 | M56: =K56+L56 -> 0.27068211 | N56: 20321.77 | O56: 28.25 | P56: 0.02 | Q56: 576.12 | R56: 12799.84 | S56: 5299.94 | T56: =IFERROR(R56/S56-1,"") -> 1.4150915 | U56: 29 | V56: 0.1315 | W56: =R56*K56 -> 1683.2422 | X56: =R56*V56 -> 1683.179 | Y56: =X56-W56 -> -0.063217222 | AA56: 按建议广告费率执行，月度复盘
A57: 高压清洗机 | B57: 高压清洗机-无刷带电显3档调速 | C57: 成熟 | D57: 维持 | E57: 187381.97 | F57: =IFERROR(E57/规则参数!$B$8,0) -> 0.0057346513 | G57: 25911.15 | H57: =IFERROR(G57/规则参数!$B$9,0) -> 0.0057591703 | I57: 20502.67 | J57: =IFERROR(I57/规则参数!$B$10,0) -> 0.0042345684 | K57: =IFERROR(I57/E57,0) -> 0.10941645 | L57: =IFERROR(G57/E57,0) -> 0.13827985 | M57: =K57+L57 -> 0.2476963 | N57: 20337.59 | O57: 49.06 | P57: 116.01 | Q57: 0.01 | R57: 10088.61 | S57: 5736.53 | T57: =IFERROR(R57/S57-1,"") -> 0.75866072 | U57: 1022 | V57: 0.1094 | W57: =R57*K57 -> 1103.8599 | X57: =R57*V57 -> 1103.6939 | Y57: =X57-W57 -> -0.16596025 | AA57: 按建议广告费率执行，月度复盘
A58: 风扇 | B58: 无绳风扇-夹式5寸款 | C58: 清货 | D58: 观察 | E58: 102130.96 | F58: =IFERROR(E58/规则参数!$B$8,0) -> 0.0031256232 | G58: 18002.25 | H58: =IFERROR(G58/规则参数!$B$9,0) -> 0.0040012899 | I58: 20423.83 | J58: =IFERROR(I58/规则参数!$B$10,0) -> 0.004218285 | K58: =IFERROR(I58/E58,0) -> 0.19997687 | L58: =IFERROR(G58/E58,0) -> 0.17626633 | M58: =K58+L58 -> 0.37624321 | N58: 14823.39 | O58: 1484.87 | P58: 2969.54 | Q58: 1146.03 | R58: 1024.3 | S58: 7384.03 | T58: =IFERROR(R58/S58-1,"") -> -0.86128171 | U58: 28 | V58: 0.15 | W58: =R58*K58 -> 204.83631 | X58: =R58*V58 -> 153.645 | Y58: =X58-W58 -> -51.191311 | Z58: 近 30 天销售环比下滑 ≥30% | AA58: 近 30 天销售环比 -86%，广告要跟着降：预算按近 30 天销售重算为 $154/月，排查排名、断货、差评或竞品降价
A59: 高枝锯 | B59: 高枝锯-两用无刷6寸 | C59: 清货 | D59: 止损 | E59: 102967.04 | F59: =IFERROR(E59/规则参数!$B$8,0) -> 0.0031512107 | G59: -7949.27 | H59: =IFERROR(G59/规则参数!$B$9,0) -> -0.0017668532 | I59: 19469.1 | J59: =IFERROR(I59/规则参数!$B$10,0) -> 0.0040210975 | K59: =IFERROR(I59/E59,0) -> 0.18908089 | L59: =IFERROR(G59/E59,0) -> -0.077202083 | M59: =K59+L59 -> 0.11187881 | N59: 13782.43 | O59: 1691.33 | P59: 3731.09 | Q59: 264.25 | R59: 3873.18 | S59: 7943.16 | T59: =IFERROR(R59/S59-1,"") -> -0.51238802 | U59: 23 | V59: 0.0619 | W59: =R59*K59 -> 732.34434 | X59: =R59*V59 -> 239.74984 | Y59: =X59-W59 -> -492.5945 | Z59: 广告后毛利为负，广告费率 > 广告前毛利率 | AA59: 广告费率 18.9% 已超过广告前毛利率 11.2%：先停泛词/自动广告，只留品牌词与高转化精准词；同步复核定价与采购成本，2 周内毛利转正再恢复
A60: 灯具 | B60: 锂电池工作灯-四叶草款 | C60: 新品期 | D60: 止损 | E60: 44858.96 | F60: =IFERROR(E60/规则参数!$B$8,0) -> 0.0013728668 | G60: -12963.6 | H60: =IFERROR(G60/规则参数!$B$9,0) -> -0.0028813688 | I60: 19101.62 | J60: =IFERROR(I60/规则参数!$B$10,0) -> 0.0039451992 | K60: =IFERROR(I60/E60,0) -> 0.42581504 | L60: =IFERROR(G60/E60,0) -> -0.28898575 | M60: =K60+L60 -> 0.1368293 | N60: 17830.62 | O60: 59.44 | P60: 1211.56 | Q60: 0 | R60: 15887.8 | S60: 7591.29 | T60: =IFERROR(R60/S60-1,"") -> 1.0928986 | U60: 3412 | V60: 0.1368 | W60: =R60*K60 -> 6765.2642 | X60: =R60*V60 -> 2173.451 | Y60: =X60-W60 -> -4591.8132 | Z60: 新品期：广告前毛利为负或广告费率 >30% | AA60: 广告费率 42.6% 已超过广告前毛利率 13.7%：先停泛词/自动广告，只留品牌词与高转化精准词；同步复核定价与采购成本，2 周内毛利转正再恢复
A61: 激光水平仪 | B61: 激光水平仪-16线4D | C61: 成熟 | D61: 压缩 | E61: 58510.01 | F61: =IFERROR(E61/规则参数!$B$8,0) -> 0.0017906446 | G61: 230.88 | H61: =IFERROR(G61/规则参数!$B$9,0) -> 5.1316797e-05 | I61: 19003.31 | J61: =IFERROR(I61/规则参数!$B$10,0) -> 0.0039248945 | K61: =IFERROR(I61/E61,0) -> 0.32478733 | L61: =IFERROR(G61/E61,0) -> 0.0039459915 | M61: =K61+L61 -> 0.32873332 | N61: 17797.04 | O61: -70.34 | P61: 1254.58 | Q61: 22.03 | R61: 5777.11 | S61: 4114.39 | T61: =IFERROR(R61/S61-1,"") -> 0.40412309 | U61: 259 | V61: 0.18 | W61: =R61*K61 -> 1876.3321 | X61: =R61*V61 -> 1039.8798 | Y61: =X61-W61 -> -836.45234 | Z61: 净毛利率 <5% 且广告费率 ≥12% | AA61: 净毛利率 0.4%，广告费率压到 18.0% 以内：砍 ACOS 超保本的词，SB/SD 预算回收到 SP 精准
A62: 金属铁皮剪 | B62: 金属冲剪-替换针头 | C62: 成熟 | D62: 加投 | E62: 164879.1 | F62: =IFERROR(E62/规则参数!$B$8,0) -> 0.0050459718 | G62: 27998.83 | H62: =IFERROR(G62/规则参数!$B$9,0) -> 0.0062231908 | I62: 18842.87 | J62: =IFERROR(I62/规则参数!$B$10,0) -> 0.0038917576 | K62: =IFERROR(I62/E62,0) -> 0.11428295 | L62: =IFERROR(G62/E62,0) -> 0.16981431 | M62: =K62+L62 -> 0.28409726 | N62: 15298.96 | O62: 1587.96 | P62: 1916.61 | Q62: 39.34 | R62: 12218.56 | S62: 14113.78 | T62: =IFERROR(R62/S62-1,"") -> -0.13428153 | U62: 469 | V62: 0.1486 | W62: =R62*K62 -> 1396.3731 | X62: =R62*V62 -> 1815.678 | Y62: =X62-W62 -> 419.30493 | Z62: 净毛利率 ≥15%、广告费率 ≤12%，有放量空间 | AA62: 利润空间充足：月预算可上调至 $1,815（单月增幅 ≤30%），优先加精准词与 SBV
A63: 饼干榫机 | B63: 饼干榫机-手持 | C63: 成熟 | D63: 观察 | E63: 137287.78 | F63: =IFERROR(E63/规则参数!$B$8,0) -> 0.0042015651 | G63: 17043.6 | H63: =IFERROR(G63/规则参数!$B$9,0) -> 0.0037882145 | I63: 18119.99 | J63: =IFERROR(I63/规则参数!$B$10,0) -> 0.0037424558 | K63: =IFERROR(I63/E63,0) -> 0.13198545 | L63: =IFERROR(G63/E63,0) -> 0.12414506 | M63: =K63+L63 -> 0.25613052 | N63: 15986.64 | O63: 18.45 | P63: 2111.52 | Q63: 3.38 | R63: 14184.69 | S63: 21273.37 | T63: =IFERROR(R63/S63-1,"") -> -0.33321848 | U63: 315 | V63: 0.132 | W63: =R63*K63 -> 1872.1728 | X63: =R63*V63 -> 1872.3791 | Y63: =X63-W63 -> 0.2063276 | Z63: 近 30 天销售环比下滑 ≥30% | AA63: 近 30 天销售环比 -33%，广告要跟着降：预算按近 30 天销售重算为 $1,872/月，排查排名、断货、差评或竞品降价
A64: 灯具 | B64: 车库灯-6+1灯 | C64: 成熟 | D64: 维持 | E64: 124072.66 | F64: =IFERROR(E64/规则参数!$B$8,0) -> 0.0037971286 | G64: 22428.05 | H64: =IFERROR(G64/规则参数!$B$9,0) -> 0.0049849952 | I64: 17948.23 | J64: =IFERROR(I64/规则参数!$B$10,0) -> 0.003706981 | K64: =IFERROR(I64/E64,0) -> 0.14465902 | L64: =IFERROR(G64/E64,0) -> 0.18076545 | M64: =K64+L64 -> 0.32542447 | N64: 16229.43 | O64: 594.85 | P64: 1123.95 | Q64: 0 | R64: 13576.35 | S64: 10444.01 | T64: =IFERROR(R64/S64-1,"") -> 0.29991737 | U64: 1823 | V64: 0.1447 | W64: =R64*K64 -> 1963.9416 | X64: =R64*V64 -> 1964.4978 | Y64: =X64-W64 -> 0.55629365 | AA64: 按建议广告费率执行，月度复盘
A65: 微耕机 | B65: 微耕机-二合一两用款 | C65: 清货 | D65: 止损 | E65: 101077.64 | F65: =IFERROR(E65/规则参数!$B$8,0) -> 0.0030933874 | G65: -14514.06 | H65: =IFERROR(G65/规则参数!$B$9,0) -> -0.0032259835 | I65: 17279.52 | J65: =IFERROR(I65/规则参数!$B$10,0) -> 0.0035688673 | K65: =IFERROR(I65/E65,0) -> 0.17095294 | L65: =IFERROR(G65/E65,0) -> -0.14359318 | M65: =K65+L65 -> 0.02735976 | N65: 14256.67 | O65: 1291.27 | P65: 1517.83 | Q65: 213.75 | R65: 5181.8 | S65: 6256.34 | T65: =IFERROR(R65/S65-1,"") -> -0.17175217 | U65: 431 | V65: 0 | W65: =R65*K65 -> 885.84396 | X65: =R65*V65 -> 0 | Y65: =X65-W65 -> -885.84396 | Z65: 广告后毛利为负，广告费率 > 广告前毛利率 | AA65: 广告费率 17.1% 已超过广告前毛利率 2.7%：先停泛词/自动广告，只留品牌词与高转化精准词；同步复核定价与采购成本，2 周内毛利转正再恢复
A66: 角磨机 | B66: 角磨机-扁头角磨 | C66: 清货 | D66: 维持 | E66: 88913.59 | F66: =IFERROR(E66/规则参数!$B$8,0) -> 0.0027211179 | G66: 11902.57 | H66: =IFERROR(G66/规则参数!$B$9,0) -> 0.0026455378 | I66: 17009.34 | J66: =IFERROR(I66/规则参数!$B$10,0) -> 0.0035130651 | K66: =IFERROR(I66/E66,0) -> 0.19130191 | L66: =IFERROR(G66/E66,0) -> 0.13386671 | M66: =K66+L66 -> 0.32516863 | N66: 14244.09 | O66: 282.2 | P66: 2483.05 | Q66: 0 | R66: 14960.15 | S66: 13568.9 | T66: =IFERROR(R66/S66-1,"") -> 0.10253226 | U66: 160 | V66: 0.15 | W66: =R66*K66 -> 2861.9053 | X66: =R66*V66 -> 2244.0225 | Y66: =X66-W66 -> -617.88284 | AA66: 按建议广告费率执行，月度复盘
A67: 木工配件 | B67: 木工直角夹-4件套 | C67: 成熟 | D67: 维持 | E67: 108765.98 | F67: =IFERROR(E67/规则参数!$B$8,0) -> 0.0033286819 | G67: 8845.81 | H67: =IFERROR(G67/规则参数!$B$9,0) -> 0.0019661237 | I67: 16958 | J67: =IFERROR(I67/规则参数!$B$10,0) -> 0.0035024614 | K67: =IFERROR(I67/E67,0) -> 0.15591272 | L67: =IFERROR(G67/E67,0) -> 0.081328831 | M67: =K67+L67 -> 0.23724155 | N67: 14665.16 | O67: -5.2 | P67: 2298.04 | Q67: 0 | R67: 7159.45 | S67: 8674.7 | T67: =IFERROR(R67/S67-1,"") -> -0.17467463 | U67: 265 | V67: 0.1372 | W67: =R67*K67 -> 1116.2493 | X67: =R67*V67 -> 982.27654 | Y67: =X67-W67 -> -133.9728 | AA67: 按建议广告费率执行，月度复盘
A68: 抛光机 | B68: 转-抛光机-7寸7档调速 | C68: 新品期 | D68: 观察 | E68: 73748.16 | F68: =IFERROR(E68/规则参数!$B$8,0) -> 0.002256994 | G68: 7169.46 | H68: =IFERROR(G68/规则参数!$B$9,0) -> 0.0015935279 | I68: 16028.59 | J68: =IFERROR(I68/规则参数!$B$10,0) -> 0.0033105035 | K68: =IFERROR(I68/E68,0) -> 0.21734224 | L68: =IFERROR(G68/E68,0) -> 0.097215442 | M68: =K68+L68 -> 0.31455768 | N68: 15931.25 | O68: -5.5 | P68: -0.09 | Q68: 102.93 | R68: 13141.8 | S68: 12141.49 | T68: =IFERROR(R68/S68-1,"") -> 0.082387746 | U68: 391 | V68: 0.2173 | W68: =R68*K68 -> 2856.2682 | X68: =R68*V68 -> 2855.7131 | Y68: =X68-W68 -> -0.5550579 | Z68: 广告费率 ≥20% | AA68: 广告费率 21.7% 偏高（保本 31.5%）：砍高花费 0 单词和 ACOS 超保本的投放，4 周内降到 21.7%；连续 4 周无改善转压缩
A69: 木工钉枪 | B69: T50无绳订书机 | C69: 新品期 | D69: 观察 | E69: 72216.8 | F69: =IFERROR(E69/规则参数!$B$8,0) -> 0.0022101281 | G69: 2087.06 | H69: =IFERROR(G69/规则参数!$B$9,0) -> 0.00046388269 | I69: 15684.07 | J69: =IFERROR(I69/规则参数!$B$10,0) -> 0.0032393472 | K69: =IFERROR(I69/E69,0) -> 0.21718035 | L69: =IFERROR(G69/E69,0) -> 0.028899924 | M69: =K69+L69 -> 0.24608027 | N69: 15600.12 | O69: 33.81 | P69: 50.14 | Q69: 0 | R69: 19963.74 | S69: 16355.89 | T69: =IFERROR(R69/S69-1,"") -> 0.22058414 | U69: 3309 | V69: 0.2172 | W69: =R69*K69 -> 4335.7321 | X69: =R69*V69 -> 4336.1243 | Y69: =X69-W69 -> 0.39225981 | Z69: 新品期：净毛利 <5%，处于保本投放容忍期（≤90 天） | AA69: 新品保本期：广告费率不超过 21.7%（保本 24.6%）；90 天内净毛利未到 5% 转入压缩
A70: 圆锯 | B70: 切割机-4英寸带4pcs锯片 | C70: 成熟 | D70: 维持 | E70: 100138.85 | F70: =IFERROR(E70/规则参数!$B$8,0) -> 0.0030646566 | G70: 20930.93 | H70: =IFERROR(G70/规则参数!$B$9,0) -> 0.0046522362 | I70: 14664.49 | J70: =IFERROR(I70/规则参数!$B$10,0) -> 0.0030287658 | K70: =IFERROR(I70/E70,0) -> 0.14644157 | L70: =IFERROR(G70/E70,0) -> 0.20901908 | M70: =K70+L70 -> 0.35546064 | N70: 11601.92 | O70: 267.61 | P70: 2794.96 | Q70: 0 | R70: 13318.63 | S70: 8570.3 | T70: =IFERROR(R70/S70-1,"") -> 0.55404478 | U70: 192 | V70: 0.1464 | W70: =R70*K70 -> 1950.401 | X70: =R70*V70 -> 1949.8474 | Y70: =X70-W70 -> -0.55360065 | AA70: 按建议广告费率执行，月度复盘
A71: 吸尘器 | B71: 干湿吸尘器-无刷 | C71: 清货 | D71: 压缩 | E71: 114547.05 | F71: =IFERROR(E71/规则参数!$B$8,0) -> 0.0035056062 | G71: 4952.67 | H71: =IFERROR(G71/规则参数!$B$9,0) -> 0.0011008107 | I71: 14224.5 | J71: =IFERROR(I71/规则参数!$B$10,0) -> 0.0029378914 | K71: =IFERROR(I71/E71,0) -> 0.12418041 | L71: =IFERROR(G71/E71,0) -> 0.043236993 | M71: =K71+L71 -> 0.16741741 | N71: 14201.73 | O71: 6.65 | P71: 16.12 | Q71: 0 | R71: 10970.08 | S71: 17337.06 | T71: =IFERROR(R71/S71-1,"") -> -0.36724681 | U71: 22 | V71: 0.1174 | W71: =R71*K71 -> 1362.2691 | X71: =R71*V71 -> 1287.8874 | Y71: =X71-W71 -> -74.381675 | Z71: 净毛利率 <5% 且广告费率 ≥12% | AA71: 净毛利率 4.3%，广告费率压到 11.7% 以内：砍 ACOS 超保本的词，SB/SD 预算回收到 SP 精准
A72: 带锯 | B72: 转-便携式带锯2.5in-手持 | C72: 成熟 | D72: 维持 | E72: 107690.4 | F72: =IFERROR(E72/规则参数!$B$8,0) -> 0.0032957647 | G72: 8202.79 | H72: =IFERROR(G72/规则参数!$B$9,0) -> 0.0018232022 | I72: 13753.1 | J72: =IFERROR(I72/规则参数!$B$10,0) -> 0.0028405297 | K72: =IFERROR(I72/E72,0) -> 0.12770962 | L72: =IFERROR(G72/E72,0) -> 0.076170114 | M72: =K72+L72 -> 0.20387973 | N72: 12047.42 | O72: 96.53 | P72: 1609.15 | Q72: 0 | R72: 19331.7 | S72: 15516.7 | T72: =IFERROR(R72/S72-1,"") -> 0.24586413 | U72: 389 | V72: 0.1039 | W72: =R72*K72 -> 2468.844 | X72: =R72*V72 -> 2008.5636 | Y72: =X72-W72 -> -460.28042 | AA72: 按建议广告费率执行，月度复盘
A73: 往复锯 | B73: 往复锯-双手 | C73: 成熟 | D73: 加投 | E73: 121505.27 | F73: =IFERROR(E73/规则参数!$B$8,0) -> 0.003718556 | G73: 23853.15 | H73: =IFERROR(G73/规则参数!$B$9,0) -> 0.0053017466 | I73: 13170.88 | J73: =IFERROR(I73/规则参数!$B$10,0) -> 0.0027202795 | K73: =IFERROR(I73/E73,0) -> 0.1083976 | L73: =IFERROR(G73/E73,0) -> 0.19631371 | M73: =K73+L73 -> 0.30471131 | N73: 12872.19 | O73: 2.32 | P73: 296.37 | Q73: 0 | R73: 19758.35 | S73: 16139.67 | T73: =IFERROR(R73/S73-1,"") -> 0.22421028 | U73: 2223 | V73: 0.1409 | W73: =R73*K73 -> 2141.7578 | X73: =R73*V73 -> 2783.9515 | Y73: =X73-W73 -> 642.19374 | Z73: 净毛利率 ≥15%、广告费率 ≤12%，有放量空间 | AA73: 利润空间充足：月预算可上调至 $2,784（单月增幅 ≤30%），优先加精准词与 SBV
A74: 填缝胶枪 | B74: 填缝胶枪-4档调速 | C74: 成熟 | D74: 观察 | E74: 64579.38 | F74: =IFERROR(E74/规则参数!$B$8,0) -> 0.001976392 | G74: 4849.17 | H74: =IFERROR(G74/规则参数!$B$9,0) -> 0.0010778061 | I74: 13029.07 | J74: =IFERROR(I74/规则参数!$B$10,0) -> 0.0026909904 | K74: =IFERROR(I74/E74,0) -> 0.20175279 | L74: =IFERROR(G74/E74,0) -> 0.075088519 | M74: =K74+L74 -> 0.27684131 | N74: 13007.81 | O74: 10.36 | P74: 4.18 | Q74: 6.72 | R74: 2811.31 | S74: 2515.33 | T74: =IFERROR(R74/S74-1,"") -> 0.11767044 | U74: 984 | V74: 0.1768 | W74: =R74*K74 -> 567.18963 | X74: =R74*V74 -> 497.03961 | Y74: =X74-W74 -> -70.150024 | Z74: 广告费率 ≥20% | AA74: 广告费率 20.2% 偏高（保本 27.7%）：砍高花费 0 单词和 ACOS 超保本的投放，4 周内降到 17.7%；连续 4 周无改善转压缩
A75: 水泵 | B75: 潜水泵-线4米 软管2米 管箍1个 | C75: 成熟 | D75: 观察 | E75: 56207.83 | F75: =IFERROR(E75/规则参数!$B$8,0) -> 0.0017201885 | G75: 5266.49 | H75: =IFERROR(G75/规则参数!$B$9,0) -> 0.0011705622 | I75: 13011.03 | J75: =IFERROR(I75/规则参数!$B$10,0) -> 0.0026872645 | K75: =IFERROR(I75/E75,0) -> 0.23148074 | L75: =IFERROR(G75/E75,0) -> 0.093696732 | M75: =K75+L75 -> 0.32517747 | N75: 12519.4 | O75: 109.71 | P75: 373.19 | Q75: 8.73 | R75: 2987.59 | S75: 2488.74 | T75: =IFERROR(R75/S75-1,"") -> 0.20044279 | U75: 215 | V75: 0.18 | W75: =R75*K75 -> 691.56954 | X75: =R75*V75 -> 537.7662 | Y75: =X75-W75 -> -153.80334 | Z75: 广告费率 ≥20% | AA75: 广告费率 23.1% 偏高（保本 32.5%）：砍高花费 0 单词和 ACOS 超保本的投放，4 周内降到 18.0%；连续 4 周无改善转压缩
A76: 未分类 | B76: 品名缺失 | C76: 成熟 | D76: — | E76: 158519.6 | F76: =IFERROR(E76/规则参数!$B$8,0) -> 0.0048513452 | G76: 43497.82 | H76: =IFERROR(G76/规则参数!$B$9,0) -> 0.0096680909 | I76: 12962.33 | J76: =IFERROR(I76/规则参数!$B$10,0) -> 0.0026772061 | K76: =IFERROR(I76/E76,0) -> 0.08177115 | L76: =IFERROR(G76/E76,0) -> 0.27440026 | M76: =K76+L76 -> 0.35617141 | N76: 987.54 | O76: 4654.39 | P76: 7320.4 | Q76: 0 | R76: 237.18 | S76: 115.98 | T76: =IFERROR(R76/S76-1,"") -> 1.0450078 | U76: 387 | V76: 0.0818 | W76: =R76*K76 -> 19.394481 | X76: =R76*V76 -> 19.401324 | Y76: =X76-W76 -> 0.0068426273 | Z76: 品名缺失，需先补齐 SPU 归属 | AA76: 按建议广告费率执行，月度复盘
A77: 曲线锯 | B77: 曲线锯-锯条*6 | C77: 成熟 | D77: 维持 | E77: 123695.27 | F77: =IFERROR(E77/规则参数!$B$8,0) -> 0.0037855789 | G77: 17014.26 | H77: =IFERROR(G77/规则参数!$B$9,0) -> 0.0037816932 | I77: 12814.95 | J77: =IFERROR(I77/规则参数!$B$10,0) -> 0.0026467666 | K77: =IFERROR(I77/E77,0) -> 0.10360097 | L77: =IFERROR(G77/E77,0) -> 0.1375498 | M77: =K77+L77 -> 0.24115077 | N77: 12803.68 | O77: 0 | P77: 11.27 | Q77: 0 | R77: 17691.87 | S77: 10380.3 | T77: =IFERROR(R77/S77-1,"") -> 0.70436982 | U77: 1583 | V77: 0.1036 | W77: =R77*K77 -> 1832.8949 | X77: =R77*V77 -> 1832.8777 | Y77: =X77-W77 -> -0.017167348 | AA77: 按建议广告费率执行，月度复盘
A78: 灯具 | B78: 工作灯-双开关56珠19W | C78: 成熟 | D78: 维持 | E78: 68370.29 | F78: =IFERROR(E78/规则参数!$B$8,0) -> 0.0020924093 | G78: 6128.01 | H78: =IFERROR(G78/规则参数!$B$9,0) -> 0.0013620489 | I78: 12567.26 | J78: =IFERROR(I78/规则参数!$B$10,0) -> 0.0025956094 | K78: =IFERROR(I78/E78,0) -> 0.18381171 | L78: =IFERROR(G78/E78,0) -> 0.089629721 | M78: =K78+L78 -> 0.27344143 | N78: 11922.67 | O78: 175.09 | P78: 292.26 | Q78: 177.24 | R78: 6248.83 | S78: 6719.11 | T78: =IFERROR(R78/S78-1,"") -> -0.069991413 | U78: 618 | V78: 0.1734 | W78: =R78*K78 -> 1148.6081 | X78: =R78*V78 -> 1083.5471 | Y78: =X78-W78 -> -65.061013 | AA78: 按建议广告费率执行，月度复盘
A79: 管道压接工具 | B79: 电动管道压接工具-枪式 | C79: 清货 | D79: 维持 | E79: 63826.28 | F79: =IFERROR(E79/规则参数!$B$8,0) -> 0.0019533441 | G79: 6099.67 | H79: =IFERROR(G79/规则参数!$B$9,0) -> 0.0013557499 | I79: 12537.2 | J79: =IFERROR(I79/规则参数!$B$10,0) -> 0.0025894008 | K79: =IFERROR(I79/E79,0) -> 0.19642693 | L79: =IFERROR(G79/E79,0) -> 0.095566748 | M79: =K79+L79 -> 0.29199367 | N79: 12434.61 | O79: -3.75 | P79: 0 | Q79: 106.34 | R79: 10971.85 | S79: 6029.93 | T79: =IFERROR(R79/S79-1,"") -> 0.81956507 | U79: 16 | V79: 0.15 | W79: =R79*K79 -> 2155.1668 | X79: =R79*V79 -> 1645.7775 | Y79: =X79-W79 -> -509.38927 | AA79: 按建议广告费率执行，月度复盘
A80: 往复锯 | B80: 往复锯-单手款 | C80: 成熟 | D80: 维持 | E80: 89429.61 | F80: =IFERROR(E80/规则参数!$B$8,0) -> 0.0027369102 | G80: 14123.42 | H80: =IFERROR(G80/规则参数!$B$9,0) -> 0.0031391575 | I80: 12529.43 | J80: =IFERROR(I80/规则参数!$B$10,0) -> 0.002587796 | K80: =IFERROR(I80/E80,0) -> 0.14010382 | L80: =IFERROR(G80/E80,0) -> 0.15792778 | M80: =K80+L80 -> 0.2980316 | N80: 9940.57 | O80: 0 | P80: 1104.26 | Q80: 1484.6 | R80: 5813.29 | S80: 6872.92 | T80: =IFERROR(R80/S80-1,"") -> -0.15417464 | U80: 268 | V80: 0.1401 | W80: =R80*K80 -> 814.46414 | X80: =R80*V80 -> 814.44193 | Y80: =X80-W80 -> -0.022207931 | AA80: 按建议广告费率执行，月度复盘
A81: 泡沫切割刀 | B81: 锂电泡沫切割刀-7.5V尾插款带适配器 | C81: 成熟 | D81: 止损 | E81: 55678.72 | F81: =IFERROR(E81/规则参数!$B$8,0) -> 0.0017039956 | G81: -1195.17 | H81: =IFERROR(G81/规则参数!$B$9,0) -> -0.00026564578 | I81: 12325.73 | J81: =IFERROR(I81/规则参数!$B$10,0) -> 0.0025457244 | K81: =IFERROR(I81/E81,0) -> 0.22137237 | L81: =IFERROR(G81/E81,0) -> -0.021465472 | M81: =K81+L81 -> 0.19990689 | N81: 7969.4 | O81: 216.38 | P81: 3744.06 | Q81: 395.89 | R81: 8805.76 | S81: 6914.74 | T81: =IFERROR(R81/S81-1,"") -> 0.27347666 | U81: 627 | V81: 0.0999 | W81: =R81*K81 -> 1949.3519 | X81: =R81*V81 -> 879.69542 | Y81: =X81-W81 -> -1069.6565 | Z81: 广告后毛利为负，广告费率 > 广告前毛利率 | AA81: 广告费率 22.1% 已超过广告前毛利率 20.0%：先停泛词/自动广告，只留品牌词与高转化精准词；同步复核定价与采购成本，2 周内毛利转正再恢复
A82: 冲击扳手 | B82: 冲击扳手-1/2英寸900N | C82: 清货 | D82: 维持 | E82: 71912.54 | F82: =IFERROR(E82/规则参数!$B$8,0) -> 0.0022008165 | G82: 3981.19 | H82: =IFERROR(G82/规则参数!$B$9,0) -> 0.00088488358 | I82: 12008.74 | J82: =IFERROR(I82/规则参数!$B$10,0) -> 0.0024802541 | K82: =IFERROR(I82/E82,0) -> 0.1669909 | L82: =IFERROR(G82/E82,0) -> 0.055361554 | M82: =K82+L82 -> 0.22235246 | N82: 11952.98 | O82: 8.53 | P82: 41.47 | Q82: 5.76 | R82: 7497.77 | S82: 4687.61 | T82: =IFERROR(R82/S82-1,"") -> 0.59948673 | U82: 1401 | V82: 0.15 | W82: =R82*K82 -> 1252.0594 | X82: =R82*V82 -> 1124.6655 | Y82: =X82-W82 -> -127.39388 | AA82: 按建议广告费率执行，月度复盘
A83: 清洁刷 | B83: 单头清洁刷-裸机8个装刷头 | C83: 清货 | D83: 压缩 | E83: 55776.86 | F83: =IFERROR(E83/规则参数!$B$8,0) -> 0.001706999 | G83: 2761.19 | H83: =IFERROR(G83/规则参数!$B$9,0) -> 0.00061371894 | I83: 11627.54 | J83: =IFERROR(I83/规则参数!$B$10,0) -> 0.002401522 | K83: =IFERROR(I83/E83,0) -> 0.2084653 | L83: =IFERROR(G83/E83,0) -> 0.049504221 | M83: =K83+L83 -> 0.25796952 | N83: 10595.37 | O83: -2.63 | P83: 875.37 | Q83: 159.43 | R83: 9782.78 | S83: 7817.88 | T83: =IFERROR(R83/S83-1,"") -> 0.25133412 | U83: 339 | V83: 0.15 | W83: =R83*K83 -> 2039.3702 | X83: =R83*V83 -> 1467.417 | Y83: =X83-W83 -> -571.95319 | Z83: 净毛利率 <5% 且广告费率 ≥12% | AA83: 净毛利率 5.0%，广告费率压到 15.0% 以内：砍 ACOS 超保本的词，SB/SD 预算回收到 SP 精准
A84: 吹叶机 | B84: 手持吹叶机-无刷三速可旋转把手 | C84: 成熟 | D84: 止损 | E84: 41768.35 | F84: =IFERROR(E84/规则参数!$B$8,0) -> 0.0012782816 | G84: -13289.11 | H84: =IFERROR(G84/规则参数!$B$9,0) -> -0.0029537187 | I84: 11236.22 | J84: =IFERROR(I84/规则参数!$B$10,0) -> 0.0023206998 | K84: =IFERROR(I84/E84,0) -> 0.26901278 | L84: =IFERROR(G84/E84,0) -> -0.3181622 | M84: =K84+L84 -> -0.049149416 | N84: 10779.97 | O84: -10.37 | P84: 466.62 | Q84: 0 | R84: 3888.17 | S84: 2912.46 | T84: =IFERROR(R84/S84-1,"") -> 0.33501233 | U84: 552 | V84: 0 | W84: =R84*K84 -> 1045.9674 | X84: =R84*V84 -> 0 | Y84: =X84-W84 -> -1045.9674 | Z84: 广告后毛利为负，广告费率 > 广告前毛利率 | AA84: 广告费率 26.9% 已超过广告前毛利率 -4.9%：先停泛词/自动广告，只留品牌词与高转化精准词；同步复核定价与采购成本，2 周内毛利转正再恢复
A85: 灯具 | B85: 锂电池工作灯-三头支架款 | C85: 成熟 | D85: 维持 | E85: 92530.49 | F85: =IFERROR(E85/规则参数!$B$8,0) -> 0.0028318098 | G85: 25485.55 | H85: =IFERROR(G85/规则参数!$B$9,0) -> 0.0056645738 | I85: 11198.26 | J85: =IFERROR(I85/规则参数!$B$10,0) -> 0.0023128596 | K85: =IFERROR(I85/E85,0) -> 0.12102238 | L85: =IFERROR(G85/E85,0) -> 0.27542867 | M85: =K85+L85 -> 0.39645105 | N85: 9720.68 | O85: 483.38 | P85: 994.2 | Q85: 0 | R85: 53630.44 | S85: 6633.13 | T85: =IFERROR(R85/S85-1,"") -> 7.0852388 | U85: 4940 | V85: 0.121 | W85: =R85*K85 -> 6490.4834 | X85: =R85*V85 -> 6489.2832 | Y85: =X85-W85 -> -1.2001783 | AA85: 按建议广告费率执行，月度复盘
A86: 冲击扳手 | B86: 冲击扳手-1/2英寸1300N | C86: 新品期 | D86: 维持 | E86: 72218.78 | F86: =IFERROR(E86/规则参数!$B$8,0) -> 0.0022101887 | G86: 6700 | H86: =IFERROR(G86/规则参数!$B$9,0) -> 0.0014891829 | I86: 11195.33 | J86: =IFERROR(I86/规则参数!$B$10,0) -> 0.0023122545 | K86: =IFERROR(I86/E86,0) -> 0.15501965 | L86: =IFERROR(G86/E86,0) -> 0.092773653 | M86: =K86+L86 -> 0.2477933 | N86: 10964.75 | O86: 206.9 | P86: 17.05 | Q86: 6.63 | R86: 31456.08 | S86: 27477.03 | T86: =IFERROR(R86/S86-1,"") -> 0.14481369 | U86: 1567 | V86: 0.155 | W86: =R86*K86 -> 4876.3105 | X86: =R86*V86 -> 4875.6924 | Y86: =X86-W86 -> -0.6181124 | AA86: 按建议广告费率执行，月度复盘
A87: 磨刀器 | B87: 锂电磨刀器-尾插款 | C87: 成熟 | D87: 维持 | E87: 72026.24 | F87: =IFERROR(E87/规则参数!$B$8,0) -> 0.0022042962 | G87: 15040.52 | H87: =IFERROR(G87/规则参数!$B$9,0) -> 0.0033429977 | I87: 11112.4 | J87: =IFERROR(I87/规则参数!$B$10,0) -> 0.0022951263 | K87: =IFERROR(I87/E87,0) -> 0.15428266 | L87: =IFERROR(G87/E87,0) -> 0.20882001 | M87: =K87+L87 -> 0.36310267 | N87: 10209.23 | O87: 13.02 | P87: 599.18 | Q87: 290.97 | R87: 12364.31 | S87: 8804.94 | T87: =IFERROR(R87/S87-1,"") -> 0.40424693 | U87: 685 | V87: 0.1543 | W87: =R87*K87 -> 1907.5987 | X87: =R87*V87 -> 1907.813 | Y87: =X87-W87 -> 0.21437945 | AA87: 按建议广告费率执行，月度复盘
A88: 锯片机 | B88: 万用宝-裸机 | C88: 成熟 | D88: 压缩 | E88: 44866.46 | F88: =IFERROR(E88/规则参数!$B$8,0) -> 0.0013730964 | G88: 1525.09 | H88: =IFERROR(G88/规则参数!$B$9,0) -> 0.00033897581 | I88: 11067.62 | J88: =IFERROR(I88/规则参数!$B$10,0) -> 0.0022858776 | K88: =IFERROR(I88/E88,0) -> 0.24667915 | L88: =IFERROR(G88/E88,0) -> 0.033991761 | M88: =K88+L88 -> 0.28067091 | N88: 10863.35 | O88: 188.31 | P88: 15.96 | Q88: 0 | R88: 6464.14 | S88: 6364.74 | T88: =IFERROR(R88/S88-1,"") -> 0.015617292 | U88: 91 | V88: 0.18 | W88: =R88*K88 -> 1594.5685 | X88: =R88*V88 -> 1163.5452 | Y88: =X88-W88 -> -431.02333 | Z88: 净毛利率 <5% 且广告费率 ≥12% | AA88: 净毛利率 3.4%，广告费率压到 18.0% 以内：砍 ACOS 超保本的词，SB/SD 预算回收到 SP 精准
A89: 木工钉枪 | B89: 大钉枪-两用有刷 | C89: 清货 | D89: 维持 | E89: 72851.03 | F89: =IFERROR(E89/规则参数!$B$8,0) -> 0.0022295382 | G89: 8594.9 | H89: =IFERROR(G89/规则参数!$B$9,0) -> 0.0019103549 | I89: 10921.06 | J89: =IFERROR(I89/规则参数!$B$10,0) -> 0.0022556075 | K89: =IFERROR(I89/E89,0) -> 0.14990948 | L89: =IFERROR(G89/E89,0) -> 0.11797911 | M89: =K89+L89 -> 0.26788859 | N89: 11072.38 | O89: -138.68 | P89: -12.64 | Q89: 0 | R89: 5748.48 | S89: 4149.45 | T89: =IFERROR(R89/S89-1,"") -> 0.38535951 | U89: 39 | V89: 0.1499 | W89: =R89*K89 -> 861.75165 | X89: =R89*V89 -> 861.69715 | Y89: =X89-W89 -> -0.054493636 | AA89: 按建议广告费率执行，月度复盘
A90: 铆钉枪 | B90: 铆钉枪-无刷铝钉 | C90: 成熟 | D90: 维持 | E90: 81251.41 | F90: =IFERROR(E90/规则参数!$B$8,0) -> 0.002486624 | G90: 12315.83 | H90: =IFERROR(G90/规则参数!$B$9,0) -> 0.0027373915 | I90: 10823.53 | J90: =IFERROR(I90/规则参数!$B$10,0) -> 0.0022354639 | K90: =IFERROR(I90/E90,0) -> 0.13321037 | L90: =IFERROR(G90/E90,0) -> 0.15157682 | M90: =K90+L90 -> 0.28478718 | N90: 10698.85 | O90: 0 | P90: 0 | Q90: 124.68 | R90: 5148.72 | S90: 6942.35 | T90: =IFERROR(R90/S90-1,"") -> -0.25836064 | U90: 1698 | V90: 0.1332 | W90: =R90*K90 -> 685.86287 | X90: =R90*V90 -> 685.8095 | Y90: =X90-W90 -> -0.053367569 | AA90: 按建议广告费率执行，月度复盘
A91: 木工钉枪 | B91: 钉枪-大型两用款 | C91: 清货 | D91: 维持 | E91: 85681.22 | F91: =IFERROR(E91/规则参数!$B$8,0) -> 0.0026221942 | G91: 12929.54 | H91: =IFERROR(G91/规则参数!$B$9,0) -> 0.0028737984 | I91: 10620.7 | J91: =IFERROR(I91/规则参数!$B$10,0) -> 0.0021935719 | K91: =IFERROR(I91/E91,0) -> 0.12395598 | L91: =IFERROR(G91/E91,0) -> 0.15090285 | M91: =K91+L91 -> 0.27485883 | N91: 8040.41 | O91: 25.33 | P91: 2554.9 | Q91: 0.06 | R91: 0 | S91: 0 | T91: =IFERROR(R91/S91-1,"") | U91: 0 | V91: 0.124 | W91: =R91*K91 -> 0 | X91: =R91*V91 -> 0 | Y91: =X91-W91 -> 0 | AA91: 按建议广告费率执行，月度复盘
A92: 平铺机 | B92: 平铺机-普通款 | C92: 成熟 | D92: 加投 | E92: 100544.31 | F92: =IFERROR(E92/规则参数!$B$8,0) -> 0.0030770653 | G92: 25482.43 | H92: =IFERROR(G92/规则参数!$B$9,0) -> 0.0056638804 | I92: 10477.19 | J92: =IFERROR(I92/规则参数!$B$10,0) -> 0.0021639317 | K92: =IFERROR(I92/E92,0) -> 0.1042047 | L92: =IFERROR(G92/E92,0) -> 0.25344477 | M92: =K92+L92 -> 0.35764948 | N92: 8882.49 | O92: 687.74 | P92: 585.35 | Q92: 321.61 | R92: 6530.63 | S92: 6396 | T92: =IFERROR(R92/S92-1,"") -> 0.021049093 | U92: 454 | V92: 0.1355 | W92: =R92*K92 -> 680.52236 | X92: =R92*V92 -> 884.90036 | Y92: =X92-W92 -> 204.378 | Z92: 净毛利率 ≥15%、广告费率 ≤12%，有放量空间 | AA92: 利润空间充足：月预算可上调至 $885（单月增幅 ≤30%），优先加精准词与 SBV
A93: 石膏板切割机 | B93: 开孔机-六档调节 | C93: 清货 | D93: 维持 | E93: 71081.94 | F93: =IFERROR(E93/规则参数!$B$8,0) -> 0.0021753968 | G93: 7402.44 | H93: =IFERROR(G93/规则参数!$B$9,0) -> 0.0016453115 | I93: 10417.03 | J93: =IFERROR(I93/规则参数!$B$10,0) -> 0.0021515064 | K93: =IFERROR(I93/E93,0) -> 0.1465496 | L93: =IFERROR(G93/E93,0) -> 0.10413953 | M93: =K93+L93 -> 0.25068913 | N93: 9667.62 | O93: 477.29 | P93: 269.85 | Q93: 2.27 | R93: 8859.4 | S93: 11197.91 | T93: =IFERROR(R93/S93-1,"") -> -0.20883451 | U93: 180 | V93: 0.1465 | W93: =R93*K93 -> 1298.3415 | X93: =R93*V93 -> 1297.9021 | Y93: =X93-W93 -> -0.43944192 | AA93: 按建议广告费率执行，月度复盘
A94: 电锤钻 | B94: 电锤钻-1英寸 | C94: 新品期 | D94: 维持 | E94: 68043.78 | F94: =IFERROR(E94/规则参数!$B$8,0) -> 0.0020824167 | G94: 5163.48 | H94: =IFERROR(G94/规则参数!$B$9,0) -> 0.0011476666 | I94: 10392.45 | J94: =IFERROR(I94/规则参数!$B$10,0) -> 0.0021464297 | K94: =IFERROR(I94/E94,0) -> 0.15273181 | L94: =IFERROR(G94/E94,0) -> 0.075884673 | M94: =K94+L94 -> 0.22861649 | N94: 8489.41 | O94: 831.69 | P94: 539.41 | Q94: 531.94 | R94: 16448.13 | S94: 11680.23 | T94: =IFERROR(R94/S94-1,"") -> 0.40820258 | U94: 518 | V94: 0.1527 | W94: =R94*K94 -> 2512.1527 | X94: =R94*V94 -> 2511.6295 | Y94: =X94-W94 -> -0.5232927 | AA94: 按建议广告费率执行，月度复盘
A95: 链锯 | B95: 电链锯-6&8寸 | C95: 清货 | D95: 止损 | E95: 51321.16 | F95: =IFERROR(E95/规则参数!$B$8,0) -> 0.0015706365 | G95: -985.94 | H95: =IFERROR(G95/规则参数!$B$9,0) -> -0.00021914104 | I95: 10121.34 | J95: =IFERROR(I95/规则参数!$B$10,0) -> 0.0020904354 | K95: =IFERROR(I95/E95,0) -> 0.19721573 | L95: =IFERROR(G95/E95,0) -> -0.019211179 | M95: =K95+L95 -> 0.17800455 | N95: 8277.89 | O95: 296.77 | P95: 1522.76 | Q95: 23.92 | R95: 9763.52 | S95: 5646.37 | T95: =IFERROR(R95/S95-1,"") -> 0.72916759 | U95: 655 | V95: 0.128 | W95: =R95*K95 -> 1925.5197 | X95: =R95*V95 -> 1249.7306 | Y95: =X95-W95 -> -675.78916 | Z95: 广告后毛利为负，广告费率 > 广告前毛利率 | AA95: 广告费率 19.7% 已超过广告前毛利率 17.8%：先停泛词/自动广告，只留品牌词与高转化精准词；同步复核定价与采购成本，2 周内毛利转正再恢复
A96: 角磨机 | B96: 角磨机-桨式开关 | C96: 清货 | D96: 观察 | E96: 44167.06 | F96: =IFERROR(E96/规则参数!$B$8,0) -> 0.0013516919 | G96: 3801.41 | H96: =IFERROR(G96/规则参数!$B$9,0) -> 0.00084492458 | I96: 9899.06 | J96: =IFERROR(I96/规则参数!$B$10,0) -> 0.0020445262 | K96: =IFERROR(I96/E96,0) -> 0.22412766 | L96: =IFERROR(G96/E96,0) -> 0.086068894 | M96: =K96+L96 -> 0.31019656 | N96: 8182.21 | O96: 217.32 | P96: 1435.22 | Q96: 64.31 | R96: 3275.88 | S96: 3355.89 | T96: =IFERROR(R96/S96-1,"") -> -0.023841663 | U96: 337 | V96: 0.15 | W96: =R96*K96 -> 734.21533 | X96: =R96*V96 -> 491.382 | Y96: =X96-W96 -> -242.83333 | Z96: 广告费率 ≥20% | AA96: 广告费率 22.4% 偏高（保本 31.0%）：砍高花费 0 单词和 ACOS 超保本的投放，4 周内降到 15.0%；连续 4 周无改善转压缩
A97: 风扇 | B97: 无绳风扇-落地式10寸款 | C97: 清货 | D97: 止损 | E97: 57451.83 | F97: =IFERROR(E97/规则参数!$B$8,0) -> 0.0017582599 | G97: -2019.66 | H97: =IFERROR(G97/规则参数!$B$9,0) -> -0.00044890195 | I97: 9855.99 | J97: =IFERROR(I97/规则参数!$B$10,0) -> 0.0020356307 | K97: =IFERROR(I97/E97,0) -> 0.17155224 | L97: =IFERROR(G97/E97,0) -> -0.035153972 | M97: =K97+L97 -> 0.13639827 | N97: 8161.2 | O97: 543.09 | P97: 762.26 | Q97: 389.44 | R97: 0 | S97: 51.99 | T97: =IFERROR(R97/S97-1,"") -> -1 | U97: 0 | V97: 0.0864 | W97: =R97*K97 -> 0 | X97: =R97*V97 -> 0 | Y97: =X97-W97 -> 0 | Z97: 广告后毛利为负，广告费率 > 广告前毛利率 | AA97: 广告费率 17.2% 已超过广告前毛利率 13.6%：先停泛词/自动广告，只留品牌词与高转化精准词；同步复核定价与采购成本，2 周内毛利转正再恢复
A98: 直磨机 | B98: 直磨机-三档调节无刷电机 | C98: 清货 | D98: 观察 | E98: 48241.85 | F98: =IFERROR(E98/规则参数!$B$8,0) -> 0.001476397 | G98: 5574.51 | H98: =IFERROR(G98/规则参数!$B$9,0) -> 0.0012390246 | I98: 9816.64 | J98: =IFERROR(I98/规则参数!$B$10,0) -> 0.0020275034 | K98: =IFERROR(I98/E98,0) -> 0.20348805 | L98: =IFERROR(G98/E98,0) -> 0.1155534 | M98: =K98+L98 -> 0.31904145 | N98: 9067.59 | O98: 0 | P98: 505.83 | Q98: 243.22 | R98: 5517.75 | S98: 3897.08 | T98: =IFERROR(R98/S98-1,"") -> 0.41586778 | U98: 297 | V98: 0.15 | W98: =R98*K98 -> 1122.7962 | X98: =R98*V98 -> 827.6625 | Y98: =X98-W98 -> -295.13369 | Z98: 广告费率 ≥20% | AA98: 广告费率 20.3% 偏高（保本 31.9%）：砍高花费 0 单词和 ACOS 超保本的投放，4 周内降到 15.0%；连续 4 周无改善转压缩
A99: 吹叶机 | B99: 手持吹叶机-无刷两电一充套装 | C99: 清货 | D99: 维持 | E99: 95496.38 | F99: =IFERROR(E99/规则参数!$B$8,0) -> 0.0029225781 | G99: 8182.23 | H99: =IFERROR(G99/规则参数!$B$9,0) -> 0.0018186324 | I99: 9802.51 | J99: =IFERROR(I99/规则参数!$B$10,0) -> 0.002024585 | K99: =IFERROR(I99/E99,0) -> 0.10264797 | L99: =IFERROR(G99/E99,0) -> 0.085681049 | M99: =K99+L99 -> 0.18832902 | N99: 8717.79 | O99: 78.99 | P99: 966.21 | Q99: 39.52 | R99: 2737.81 | S99: 3562.88 | T99: =IFERROR(R99/S99-1,"") -> -0.2315739 | U99: 859 | V99: 0.1026 | W99: =R99*K99 -> 281.03065 | X99: =R99*V99 -> 280.89931 | Y99: =X99-W99 -> -0.13134567 | AA99: 按建议广告费率执行，月度复盘
A100: 绿篱机 | B100: 高枝绿篱机-有刷20寸 | C100: 新品期 | D100: 观察 | E100: 95927.05 | F100: =IFERROR(E100/规则参数!$B$8,0) -> 0.0029357583 | G100: 6930.01 | H100: =IFERROR(G100/规则参数!$B$9,0) -> 0.0015403063 | I100: 9751.96 | J100: =IFERROR(I100/规则参数!$B$10,0) -> 0.0020141446 | K100: =IFERROR(I100/E100,0) -> 0.10166017 | L100: =IFERROR(G100/E100,0) -> 0.072242501 | M100: =K100+L100 -> 0.17390267 | N100: 8553 | O100: 23.14 | P100: 1175.82 | Q100: 0 | R100: 8401 | S100: 22312.2 | T100: =IFERROR(R100/S100-1,"") -> -0.62347953 | U100: 181 | V100: 0.1017 | W100: =R100*K100 -> 854.04707 | X100: =R100*V100 -> 854.3817 | Y100: =X100-W100 -> 0.33463027 | Z100: 近 30 天销售环比下滑 ≥30% | AA100: 近 30 天销售环比 -62%，广告要跟着降：预算按近 30 天销售重算为 $854/月，排查排名、断货、差评或竞品降价
...

Sheet 分类汇总
A1: 品线（分类） | B1: 广告状态 | C1: 状态依据 | D1: 销售额 | E1: 占公司比例 | F1: 毛利额 | G1: 毛利额占比 | H1: 广告花费 | I1: 广告占公司比例 | J1: 广告费率 | K1: 净毛利率 | L1: SPU数 | M1: 当前月广告(估) | N1: 建议月预算
A2: 电源逆变器 | B2: 观察 | C2: 广告费率 17.3% ≥17% | D2: =SUMIFS(SPU监控与预算!$E:$E,SPU监控与预算!$A:$A,$A2) -> 3843776.1 | E2: =D2/规则参数!$B$8 -> 0.1176352 | F2: =SUMIFS(SPU监控与预算!$G:$G,SPU监控与预算!$A:$A,$A2) -> 319672.05 | G2: =F2/规则参数!$B$9 -> 0.07105226 | H2: =SUMIFS(SPU监控与预算!$I:$I,SPU监控与预算!$A:$A,$A2) -> 664904.02 | I2: =H2/规则参数!$B$10 -> 0.13732756 | J2: =IFERROR(H2/D2,0) -> 0.17298198 | K2: =IFERROR(F2/D2,0) -> 0.083166147 | L2: =COUNTIFS(SPU监控与预算!$A:$A,$A2) -> 8 | M2: =SUMIFS(SPU监控与预算!$W:$W,SPU监控与预算!$A:$A,$A2) -> 46907.596 | N2: =SUMIFS(SPU监控与预算!$X:$X,SPU监控与预算!$A:$A,$A2) -> 38639.006
A3: 充气泵 | B3: 维稳 | C3: 净毛利率 13.0%、广告费率 16.1%，在合理区间 | D3: =SUMIFS(SPU监控与预算!$E:$E,SPU监控与预算!$A:$A,$A3) -> 3339273.5 | E3: =D3/规则参数!$B$8 -> 0.10219537 | F3: =SUMIFS(SPU监控与预算!$G:$G,SPU监控与预算!$A:$A,$A3) -> 433332.62 | G3: =F3/规则参数!$B$9 -> 0.096315152 | H3: =SUMIFS(SPU监控与预算!$I:$I,SPU监控与预算!$A:$A,$A3) -> 536394.27 | I3: =H3/规则参数!$B$10 -> 0.11078548 | J3: =IFERROR(H3/D3,0) -> 0.16063203 | K3: =IFERROR(F3/D3,0) -> 0.12976853 | L3: =COUNTIFS(SPU监控与预算!$A:$A,$A3) -> 7 | M3: =SUMIFS(SPU监控与预算!$W:$W,SPU监控与预算!$A:$A,$A3) -> 62233.575 | N3: =SUMIFS(SPU监控与预算!$X:$X,SPU监控与预算!$A:$A,$A3) -> 59989.634
A4: 冲击扳手 | B4: 维稳 | C4: 净毛利率 14.5%、广告费率 13.7%，在合理区间 | D4: =SUMIFS(SPU监控与预算!$E:$E,SPU监控与预算!$A:$A,$A4) -> 3420029 | E4: =D4/规则参数!$B$8 -> 0.10466681 | F4: =SUMIFS(SPU监控与预算!$G:$G,SPU监控与预算!$A:$A,$A4) -> 495175.4 | G4: =F4/规则参数!$B$9 -> 0.11006071 | H4: =SUMIFS(SPU监控与预算!$I:$I,SPU监控与预算!$A:$A,$A4) -> 467865.13 | I4: =H4/规则参数!$B$10 -> 0.096631653 | J4: =IFERROR(H4/D4,0) -> 0.13680151 | K4: =IFERROR(F4/D4,0) -> 0.1447869 | L4: =COUNTIFS(SPU监控与预算!$A:$A,$A4) -> 10 | M4: =SUMIFS(SPU监控与预算!$W:$W,SPU监控与预算!$A:$A,$A4) -> 47876.77 | N4: =SUMIFS(SPU监控与预算!$X:$X,SPU监控与预算!$A:$A,$A4) -> 48329.874
A5: 灯具 | B5: 维稳 | C5: 净毛利率 19.0%、广告费率 14.7%，在合理区间 | D5: =SUMIFS(SPU监控与预算!$E:$E,SPU监控与预算!$A:$A,$A5) -> 3088508.1 | E5: =D5/规则参数!$B$8 -> 0.094520925 | F5: =SUMIFS(SPU监控与预算!$G:$G,SPU监控与预算!$A:$A,$A5) -> 586491.97 | G5: =F5/规则参数!$B$9 -> 0.13035728 | H5: =SUMIFS(SPU监控与预算!$I:$I,SPU监控与预算!$A:$A,$A5) -> 452612.54 | I5: =H5/规则参数!$B$10 -> 0.093481423 | J5: =IFERROR(H5/D5,0) -> 0.1465473 | K5: =IFERROR(F5/D5,0) -> 0.18989491 | L5: =COUNTIFS(SPU监控与预算!$A:$A,$A5) -> 38 | M5: =SUMIFS(SPU监控与预算!$W:$W,SPU监控与预算!$A:$A,$A5) -> 79835.446 | N5: =SUMIFS(SPU监控与预算!$X:$X,SPU监控与预算!$A:$A,$A5) -> 73515.557
A6: 锂电油泵 | B6: 维稳 | C6: 利润空间足（净毛利率 25.4%、广告费率 10.8%），但近 30 天销售环比 -16%，暂不加投 | D6: =SUMIFS(SPU监控与预算!$E:$E,SPU监控与预算!$A:$A,$A6) -> 2397143.9 | E6: =D6/规则参数!$B$8 -> 0.073362363 | F6: =SUMIFS(SPU监控与预算!$G:$G,SPU监控与预算!$A:$A,$A6) -> 609510.08 | G6: =F6/规则参数!$B$9 -> 0.13547343 | H6: =SUMIFS(SPU监控与预算!$I:$I,SPU监控与预算!$A:$A,$A6) -> 258949.19 | I6: =H6/规则参数!$B$10 -> 0.053482695 | J6: =IFERROR(H6/D6,0) -> 0.10802405 | K6: =IFERROR(F6/D6,0) -> 0.25426512 | L6: =COUNTIFS(SPU监控与预算!$A:$A,$A6) -> 8 | M6: =SUMIFS(SPU监控与预算!$W:$W,SPU监控与预算!$A:$A,$A6) -> 21227.979 | N6: =SUMIFS(SPU监控与预算!$X:$X,SPU监控与预算!$A:$A,$A6) -> 22260.964
A7: 黄油枪 | B7: 维稳 | C7: 净毛利率 19.0%、广告费率 16.0%，在合理区间 | D7: =SUMIFS(SPU监控与预算!$E:$E,SPU监控与预算!$A:$A,$A7) -> 1614868.7 | E7: =D7/规则参数!$B$8 -> 0.049421559 | F7: =SUMIFS(SPU监控与预算!$G:$G,SPU监控与预算!$A:$A,$A7) -> 307537.75 | G7: =F7/规则参数!$B$9 -> 0.068355217 | H7: =SUMIFS(SPU监控与预算!$I:$I,SPU监控与预算!$A:$A,$A7) -> 258145.76 | I7: =H7/规则参数!$B$10 -> 0.053316757 | J7: =IFERROR(H7/D7,0) -> 0.15985557 | K7: =IFERROR(F7/D7,0) -> 0.19044133 | L7: =COUNTIFS(SPU监控与预算!$A:$A,$A7) -> 3 | M7: =SUMIFS(SPU监控与预算!$W:$W,SPU监控与预算!$A:$A,$A7) -> 19085.925 | N7: =SUMIFS(SPU监控与预算!$X:$X,SPU监控与预算!$A:$A,$A7) -> 19052.145
A8: 木工钉枪 | B8: 维稳 | C8: 净毛利率 11.8%、广告费率 14.8%，在合理区间 | D8: =SUMIFS(SPU监控与预算!$E:$E,SPU监控与预算!$A:$A,$A8) -> 1710642.6 | E8: =D8/规则参数!$B$8 -> 0.05235263 | F8: =SUMIFS(SPU监控与预算!$G:$G,SPU监控与预算!$A:$A,$A8) -> 201720.85 | G8: =F8/规则参数!$B$9 -> 0.044835707 | H8: =SUMIFS(SPU监控与预算!$I:$I,SPU监控与预算!$A:$A,$A8) -> 253472.5 | I8: =H8/规则参数!$B$10 -> 0.052351554 | J8: =IFERROR(H8/D8,0) -> 0.14817385 | K8: =IFERROR(F8/D8,0) -> 0.11792109 | L8: =COUNTIFS(SPU监控与预算!$A:$A,$A8) -> 14 | M8: =SUMIFS(SPU监控与预算!$W:$W,SPU监控与预算!$A:$A,$A8) -> 22900.408 | N8: =SUMIFS(SPU监控与预算!$X:$X,SPU监控与预算!$A:$A,$A8) -> 22327.654
A9: 吹叶机 | B9: 维稳 | C9: 净毛利率 13.1%、广告费率 14.1%，在合理区间 | D9: =SUMIFS(SPU监控与预算!$E:$E,SPU监控与预算!$A:$A,$A9) -> 900793.65 | E9: =D9/规则参数!$B$8 -> 0.027567954 | F9: =SUMIFS(SPU监控与预算!$G:$G,SPU监控与预算!$A:$A,$A9) -> 117557.33 | G9: =F9/规则参数!$B$9 -> 0.026129009 | H9: =SUMIFS(SPU监控与预算!$I:$I,SPU监控与预算!$A:$A,$A9) -> 126941.7 | I9: =H9/规则参数!$B$10 -> 0.02621821 | J9: =IFERROR(H9/D9,0) -> 0.14092206 | K9: =IFERROR(F9/D9,0) -> 0.13050417 | L9: =COUNTIFS(SPU监控与预算!$A:$A,$A9) -> 3 | M9: =SUMIFS(SPU监控与预算!$W:$W,SPU监控与预算!$A:$A,$A9) -> 13715.57 | N9: =SUMIFS(SPU监控与预算!$X:$X,SPU监控与预算!$A:$A,$A9) -> 12669.295
A10: 锯片机 | B10: 收缩 | C10: 净毛利率 7.6% <8% | D10: =SUMIFS(SPU监控与预算!$E:$E,SPU监控与预算!$A:$A,$A10) -> 779130.84 | E10: =D10/规则参数!$B$8 -> 0.023844576 | F10: =SUMIFS(SPU监控与预算!$G:$G,SPU监控与预算!$A:$A,$A10) -> 59132.01 | G10: =F10/规则参数!$B$9 -> 0.013143041 | H10: =SUMIFS(SPU监控与预算!$I:$I,SPU监控与预算!$A:$A,$A10) -> 123318.19 | I10: =H10/规则参数!$B$10 -> 0.02546982 | J10: =IFERROR(H10/D10,0) -> 0.15827661 | K10: =IFERROR(F10/D10,0) -> 0.075894839 | L10: =COUNTIFS(SPU监控与预算!$A:$A,$A10) -> 4 | M10: =SUMIFS(SPU监控与预算!$W:$W,SPU监控与预算!$A:$A,$A10) -> 11988.285 | N10: =SUMIFS(SPU监控与预算!$X:$X,SPU监控与预算!$A:$A,$A10) -> 9928.0908
A11: 风扇 | B11: 观察 | C11: 广告费率 17.9% ≥17%；近 30 天销售环比 -81% | D11: =SUMIFS(SPU监控与预算!$E:$E,SPU监控与预算!$A:$A,$A11) -> 684738.95 | E11: =D11/规则参数!$B$8 -> 0.0209558 | F11: =SUMIFS(SPU监控与预算!$G:$G,SPU监控与预算!$A:$A,$A11) -> 82943.24 | G11: =F11/规则参数!$B$9 -> 0.018435471 | H11: =SUMIFS(SPU监控与预算!$I:$I,SPU监控与预算!$A:$A,$A11) -> 122781.12 | I11: =H11/规则参数!$B$10 -> 0.025358895 | J11: =IFERROR(H11/D11,0) -> 0.17931085 | K11: =IFERROR(F11/D11,0) -> 0.12113118 | L11: =COUNTIFS(SPU监控与预算!$A:$A,$A11) -> 7 | M11: =SUMIFS(SPU监控与预算!$W:$W,SPU监控与预算!$A:$A,$A11) -> 1374.8444 | N11: =SUMIFS(SPU监控与预算!$X:$X,SPU监控与预算!$A:$A,$A11) -> 1178.458
A12: 热风枪 | B12: 维稳 | C12: 净毛利率 18.3%、广告费率 14.8%，在合理区间 | D12: =SUMIFS(SPU监控与预算!$E:$E,SPU监控与预算!$A:$A,$A12) -> 766016.84 | E12: =D12/规则参数!$B$8 -> 0.023443234 | F12: =SUMIFS(SPU监控与预算!$G:$G,SPU监控与预算!$A:$A,$A12) -> 140298.33 | G12: =F12/规则参数!$B$9 -> 0.031183563 | H12: =SUMIFS(SPU监控与预算!$I:$I,SPU监控与预算!$A:$A,$A12) -> 113146.81 | I12: =H12/规则参数!$B$10 -> 0.023369049 | J12: =IFERROR(H12/D12,0) -> 0.14770799 | K12: =IFERROR(F12/D12,0) -> 0.18315306 | L12: =COUNTIFS(SPU监控与预算!$A:$A,$A12) -> 6 | M12: =SUMIFS(SPU监控与预算!$W:$W,SPU监控与预算!$A:$A,$A12) -> 12152.771 | N12: =SUMIFS(SPU监控与预算!$X:$X,SPU监控与预算!$A:$A,$A12) -> 11917.108
A13: 高压清洗机 | B13: 维稳 | C13: 净毛利率 13.0%、广告费率 15.6%，在合理区间 | D13: =SUMIFS(SPU监控与预算!$E:$E,SPU监控与预算!$A:$A,$A13) -> 721986.1 | E13: =D13/规则参数!$B$8 -> 0.022095715 | F13: =SUMIFS(SPU监控与预算!$G:$G,SPU监控与预算!$A:$A,$A13) -> 93554.34 | G13: =F13/规则参数!$B$9 -> 0.020793958 | H13: =SUMIFS(SPU监控与预算!$I:$I,SPU监控与预算!$A:$A,$A13) -> 112367.96 | I13: =H13/规则参数!$B$10 -> 0.023208188 | J13: =IFERROR(H13/D13,0) -> 0.15563729 | K13: =IFERROR(F13/D13,0) -> 0.12957914 | L13: =COUNTIFS(SPU监控与预算!$A:$A,$A13) -> 4 | M13: =SUMIFS(SPU监控与预算!$W:$W,SPU监控与预算!$A:$A,$A13) -> 3181.3066 | N13: =SUMIFS(SPU监控与预算!$X:$X,SPU监控与预算!$A:$A,$A13) -> 3181.6039
... A88: 园林配件 | B88: 维稳 | C88: 广告花费 <$2,000，影响小 | D88: =SUMIFS(SPU监控与预算!$E:$E,SPU监控与预算!$A:$A,$A88) -> 2193.1 | E88: =D88/规则参数!$B$8 -> 6.711779e-05 | F88: =SUMIFS(SPU监控与预算!$G:$G,SPU监控与预算!$A:$A,$A88) -> 886.22 | G88: =F88/规则参数!$B$9 -> 0.00019697666 | H88: =SUMIFS(SPU监控与预算!$I:$I,SPU监控与预算!$A:$A,$A88) -> -0.5 | I88: =H88/规则参数!$B$10 -> -1.0326871e-07 | J88: =IFERROR(H88/D88,0) -> -0.00022798778 | K88: =IFERROR(F88/D88,0) -> 0.40409466 | L88: =COUNTIFS(SPU监控与预算!$A:$A,$A88) -> 2 | M88: =SUMIFS(SPU监控与预算!$W:$W,SPU监控与预算!$A:$A,$A88) -> -0.072436087 | N88: =SUMIFS(SPU监控与预算!$X:$X,SPU监控与预算!$A:$A,$A88) -> -0.085443
A90: 广告状态判定（按顺序）：收缩＝净毛利率<8% 或 止损/压缩/清理 SPU 占广告≥30% 或 建议预算较当前≤−20%；观察＝广告费率≥17% 或 异常 SPU 占广告≥15% 或 近30天销售环比≤−20%；加投＝净毛利率≥15%、广告费率≤13%、近30天环比>−10% 且建议预算高于当前；其余维稳；广告<$2,000 的小分类维稳。

Sheet 规则参数
A1: 参数 | B1: 值 | C1: 说明
A2: 成熟品最低净毛利率 | B2: 0.1 | C2: 建议广告费率 = 广告前毛利率 − 该值
A3: 成熟品费率上限 | B3: 0.18
A4: 新品期费率上限 | B4: 0.25 | C4: 新品期按保本投放，最长 90 天
A5: 清货品让利 | B5: 0.05 | C5: 建议费率 = 广告前毛利率 − 该值
A6: 清货品费率上限 | B6: 0.15
A7: 加投单月最大增幅 | B7: 0.3 | C7: 仅「加投」标记可上调
A8: 公司销售额（1–10/24） | B8: 32675390 | C8: 利润报表-MSKU
A9: 公司毛利额 | B9: 4499111.6
A10: 公司广告花费 | B10: 4841737.8
