Workbook

Sheet 参数
A1: ACC + 社媒KOL 岗位产值测算 · 参数
A2: 图例：黄底蓝字 = 需要你填/可调的参数；黑字 = 公式；绿字 = 引用其他表。改参数后「月度测算」自动更新。
A4: 基础参数 | B4: 数值 | E4: 说明 / 来源
A5: 账号月销售额（$） | B5: =SUM(B19:B24) -> 1380000 | E5: 取下方6个核心品线月均GMV合计（美国站，用户提供）。也可在「月度测算」第6行逐月覆盖以体现淡旺季。
A6: 现有ACC基线占比 | B6: 0.0525 | E6: 来自你对ACC创作者计划数据的初步计算（5%–5.5%取中值）。基线是岗位到岗前就有的，不计入岗位产值。
A7: 毛利率（扣采购、头程、FBA、平台佣金后，未扣广告） | B7: 0.3 | E7: 示例值，请按品类实际毛利率替换。
A8: ACC加码佣金率（占ACC订单销售额） | B8: 0.1 | E8: 示例值，请按ACC后台实际设置的佣金率替换。
A9: 社媒KOL费用率（达人费+样品，占KOL带来的销售额） | B9: 0.2 | E9: 示例值，按实际报价/寄样成本校准。
A10: 搭建期每月寻找/测试投入（$，第1–6月） | B10: 1000 | E10: 示例值：社媒达人寄样、小额测试合作费。
A11: 岗位人力月成本（$，含社保） | B11: 2000 | E11: 示例值（约¥14k/月），请按实际薪资替换。
A13: 分阶段占比（占账号销售额） | B13: 第1–3月 | C13: 第4–6月 | D13: 第7–12月 | E13: 说明 / 来源
A14: ACC放量增量占比（在基线之上） | B14: 0.005 | C14: 0.01 | D14: 0.015 | E14: 【我的假设，需你确认】先激活已合作过的红人谈放量，见效最快，所以第1月起计；按+0.5%/+1.0%/+1.5%逐步放大，即ACC占比由5.25%升到约6.75%。
A15: 社媒KOL新增占比 | B15: 0 | C15: 0.01 | D15: 0.02 | E15: 按你的口径：前3月搭建无产出，第4–6月按销售额1%，第7–12月按2%。
A17: 核心品线（美国站） | B17: 月均GMV（$） | C17: 占比 | E17: 说明 / 来源
A18: （可增删品线，保持在第19–24行内）
A19: 油泵 | B19: 200000 | C19: =IFERROR(B19/$B$25,0) -> 0.14492754 | E19: 用户提供：美国站月均GMV
A20: 充气泵 | B20: 250000 | C20: =IFERROR(B20/$B$25,0) -> 0.18115942 | E20: 用户提供：美国站月均GMV
A21: 逆变器 | B21: 340000 | C21: =IFERROR(B21/$B$25,0) -> 0.24637681 | E21: 用户提供：美国站月均GMV
A22: 冲击扳手 | B22: 260000 | C22: =IFERROR(B22/$B$25,0) -> 0.1884058 | E22: 用户提供：美国站月均GMV
A23: 黄油枪 | B23: 130000 | C23: =IFERROR(B23/$B$25,0) -> 0.094202899 | E23: 用户提供：美国站月均GMV
A24: 工作灯 | B24: 200000 | C24: =IFERROR(B24/$B$25,0) -> 0.14492754 | E24: 用户提供：美国站月均GMV
A25: 合计 | B25: =SUM(B19:B24) -> 1380000 | C25: =SUM(C19:C24) -> 1

Sheet 月度测算
A1: 月度测算（第1–12月，到岗月=第1月）
A2: 第6行销售额默认引用参数表，可直接改成每月实际/预测值（改后变蓝字）。
A4: 项目 | B4: 第1月 | C4: 第2月 | D4: 第3月 | E4: 第4月 | F4: 第5月 | G4: 第6月 | H4: 第7月 | I4: 第8月 | J4: 第9月 | K4: 第10月 | L4: 第11月 | M4: 第12月 | N4: 全年
A5: 阶段 | B5: 搭建 | C5: 搭建 | D5: 搭建 | E5: 测试放量 | F5: 测试放量 | G5: 测试放量 | H5: 稳定 | I5: 稳定 | J5: 稳定 | K5: 稳定 | L5: 稳定 | M5: 稳定
A6: 账号月销售额（$） | B6: =参数!$B$5 -> 1380000 | C6: =参数!$B$5 -> 1380000 | D6: =参数!$B$5 -> 1380000 | E6: =参数!$B$5 -> 1380000 | F6: =参数!$B$5 -> 1380000 | G6: =参数!$B$5 -> 1380000 | H6: =参数!$B$5 -> 1380000 | I6: =参数!$B$5 -> 1380000 | ... M6: =参数!$B$5 -> 1380000 | N6: =SUM(B6:M6) -> 16560000
A7: 参考：现有ACC基线销售额（不计入） | B7: =B6*参数!$B$6 -> 72450 | C7: =C6*参数!$B$6 -> 72450 | D7: =D6*参数!$B$6 -> 72450 | E7: =E6*参数!$B$6 -> 72450 | F7: =F6*参数!$B$6 -> 72450 | G7: =G6*参数!$B$6 -> 72450 | H7: =H6*参数!$B$6 -> 72450 | I7: =I6*参数!$B$6 -> 72450 | ... M7: =M6*参数!$B$6 -> 72450 | N7: =SUM(B7:M7) -> 869400
A8: ① 岗位带来的增量销售额
A9: ACC放量增量占比 | B9: =IF(1<=3,参数!$B$14,IF(1<=6,参数!$C$14,参数!$D$14)) -> 0.005 | C9: =IF(2<=3,参数!$B$14,IF(2<=6,参数!$C$14,参数!$D$14)) -> 0.005 | D9: =IF(3<=3,参数!$B$14,IF(3<=6,参数!$C$14,参数!$D$14)) -> 0.005 | E9: =IF(4<=3,参数!$B$14,IF(4<=6,参数!$C$14,参数!$D$14)) -> 0.01 | F9: =IF(5<=3,参数!$B$14,IF(5<=6,参数!$C$14,参数!$D$14)) -> 0.01 | G9: =IF(6<=3,参数!$B$14,IF(6<=6,参数!$C$14,参数!$D$14)) -> 0.01 | H9: =IF(7<=3,参数!$B$14,IF(7<=6,参数!$C$14,参数!$D$14)) -> 0.015 | I9: =IF(8<=3,参数!$B$14,IF(8<=6,参数!$C$14,参数!$D$14)) -> 0.015 | J9: =IF(9<=3,参数!$B$14,IF(9<=6,参数!$C$14,参数!$D$14)) -> 0.015 | K9: =IF(10<=3,参数!$B$14,IF(10<=6,参数!$C$14,参数!$D$14)) -> 0.015 | L9: =IF(11<=3,参数!$B$14,IF(11<=6,参数!$C$14,参数!$D$14)) -> 0.015 | M9: =IF(12<=3,参数!$B$14,IF(12<=6,参数!$C$14,参数!$D$14)) -> 0.015 | N9: =IFERROR(N10/N6,0) -> 0.01125
A10: ACC放量增量销售额 | B10: =B6*B9 -> 6900 | C10: =C6*C9 -> 6900 | D10: =D6*D9 -> 6900 | E10: =E6*E9 -> 13800 | F10: =F6*F9 -> 13800 | G10: =G6*G9 -> 13800 | H10: =H6*H9 -> 20700 | I10: =I6*I9 -> 20700 | ... M10: =M6*M9 -> 20700 | N10: =SUM(B10:M10) -> 186300
A11: 社媒KOL新增占比 | B11: =IF(1<=3,参数!$B$15,IF(1<=6,参数!$C$15,参数!$D$15)) -> 0 | C11: =IF(2<=3,参数!$B$15,IF(2<=6,参数!$C$15,参数!$D$15)) -> 0 | D11: =IF(3<=3,参数!$B$15,IF(3<=6,参数!$C$15,参数!$D$15)) -> 0 | E11: =IF(4<=3,参数!$B$15,IF(4<=6,参数!$C$15,参数!$D$15)) -> 0.01 | F11: =IF(5<=3,参数!$B$15,IF(5<=6,参数!$C$15,参数!$D$15)) -> 0.01 | G11: =IF(6<=3,参数!$B$15,IF(6<=6,参数!$C$15,参数!$D$15)) -> 0.01 | H11: =IF(7<=3,参数!$B$15,IF(7<=6,参数!$C$15,参数!$D$15)) -> 0.02 | I11: =IF(8<=3,参数!$B$15,IF(8<=6,参数!$C$15,参数!$D$15)) -> 0.02 | J11: =IF(9<=3,参数!$B$15,IF(9<=6,参数!$C$15,参数!$D$15)) -> 0.02 | K11: =IF(10<=3,参数!$B$15,IF(10<=6,参数!$C$15,参数!$D$15)) -> 0.02 | L11: =IF(11<=3,参数!$B$15,IF(11<=6,参数!$C$15,参数!$D$15)) -> 0.02 | M11: =IF(12<=3,参数!$B$15,IF(12<=6,参数!$C$15,参数!$D$15)) -> 0.02 | N11: =IFERROR(N12/N6,0) -> 0.0125
A12: 社媒KOL新增销售额 | B12: =B6*B11 -> 0 | C12: =C6*C11 -> 0 | D12: =D6*D11 -> 0 | E12: =E6*E11 -> 13800 | F12: =F6*F11 -> 13800 | G12: =G6*G11 -> 13800 | H12: =H6*H11 -> 27600 | I12: =I6*I11 -> 27600 | ... M12: =M6*M11 -> 27600 | N12: =SUM(B12:M12) -> 207000
A13: 岗位增量销售额合计 | B13: =B10+B12 -> 6900 | C13: =C10+C12 -> 6900 | D13: =D10+D12 -> 6900 | E13: =E10+E12 -> 27600 | F13: =F10+F12 -> 27600 | G13: =G10+G12 -> 27600 | H13: =H10+H12 -> 48300 | I13: =I10+I12 -> 48300 | ... M13: =M10+M12 -> 48300 | N13: =SUM(B13:M13) -> 393300
A14: 增量占账号销售额 | B14: =IFERROR(B13/B6,0) -> 0.005 | C14: =IFERROR(C13/C6,0) -> 0.005 | D14: =IFERROR(D13/D6,0) -> 0.005 | E14: =IFERROR(E13/E6,0) -> 0.02 | F14: =IFERROR(F13/F6,0) -> 0.02 | G14: =IFERROR(G13/G6,0) -> 0.02 | H14: =IFERROR(H13/H6,0) -> 0.035 | I14: =IFERROR(I13/I6,0) -> 0.035 | ... N14: =IFERROR(N13/N6,0) -> 0.02375
A15: ACC总占比（基线+放量） | B15: =参数!$B$6+B9 -> 0.0575 | C15: =参数!$B$6+C9 -> 0.0575 | D15: =参数!$B$6+D9 -> 0.0575 | E15: =参数!$B$6+E9 -> 0.0625 | F15: =参数!$B$6+F9 -> 0.0625 | G15: =参数!$B$6+G9 -> 0.0625 | H15: =参数!$B$6+H9 -> 0.0675 | I15: =参数!$B$6+I9 -> 0.0675 | ... M15: =参数!$B$6+M9 -> 0.0675 | N15: =IFERROR((N7+N10)/N6,0) -> 0.06375
A17: ② 成本与净贡献
A18: 增量毛利 | B18: =B13*参数!$B$7 -> 2070 | C18: =C13*参数!$B$7 -> 2070 | D18: =D13*参数!$B$7 -> 2070 | E18: =E13*参数!$B$7 -> 8280 | F18: =F13*参数!$B$7 -> 8280 | G18: =G13*参数!$B$7 -> 8280 | H18: =H13*参数!$B$7 -> 14490 | I18: =I13*参数!$B$7 -> 14490 | ... M18: =M13*参数!$B$7 -> 14490 | N18: =SUM(B18:M18) -> 117990
A19: ACC加码佣金 | B19: =B10*参数!$B$8 -> 690 | C19: =C10*参数!$B$8 -> 690 | D19: =D10*参数!$B$8 -> 690 | E19: =E10*参数!$B$8 -> 1380 | F19: =F10*参数!$B$8 -> 1380 | G19: =G10*参数!$B$8 -> 1380 | H19: =H10*参数!$B$8 -> 2070 | I19: =I10*参数!$B$8 -> 2070 | ... M19: =M10*参数!$B$8 -> 2070 | N19: =SUM(B19:M19) -> 18630
A20: 社媒KOL达人费用 | B20: =B12*参数!$B$9 -> 0 | C20: =C12*参数!$B$9 -> 0 | D20: =D12*参数!$B$9 -> 0 | E20: =E12*参数!$B$9 -> 2760 | F20: =F12*参数!$B$9 -> 2760 | G20: =G12*参数!$B$9 -> 2760 | H20: =H12*参数!$B$9 -> 5520 | I20: =I12*参数!$B$9 -> 5520 | ... M20: =M12*参数!$B$9 -> 5520 | N20: =SUM(B20:M20) -> 41400
A21: 搭建期寻找/测试投入 | B21: =IF(1<=6,参数!$B$10,0) -> 1000 | C21: =IF(2<=6,参数!$B$10,0) -> 1000 | D21: =IF(3<=6,参数!$B$10,0) -> 1000 | E21: =IF(4<=6,参数!$B$10,0) -> 1000 | F21: =IF(5<=6,参数!$B$10,0) -> 1000 | G21: =IF(6<=6,参数!$B$10,0) -> 1000 | H21: =IF(7<=6,参数!$B$10,0) -> 0 | I21: =IF(8<=6,参数!$B$10,0) -> 0 | J21: =IF(9<=6,参数!$B$10,0) -> 0 | K21: =IF(10<=6,参数!$B$10,0) -> 0 | L21: =IF(11<=6,参数!$B$10,0) -> 0 | M21: =IF(12<=6,参数!$B$10,0) -> 0 | N21: =SUM(B21:M21) -> 6000
A22: 岗位人力成本 | B22: =参数!$B$11 -> 2000 | C22: =参数!$B$11 -> 2000 | D22: =参数!$B$11 -> 2000 | E22: =参数!$B$11 -> 2000 | F22: =参数!$B$11 -> 2000 | G22: =参数!$B$11 -> 2000 | H22: =参数!$B$11 -> 2000 | I22: =参数!$B$11 -> 2000 | ... M22: =参数!$B$11 -> 2000 | N22: =SUM(B22:M22) -> 24000
A23: 费用合计 | B23: =SUM(B19:B22) -> 3690 | C23: =SUM(C19:C22) -> 3690 | D23: =SUM(D19:D22) -> 3690 | E23: =SUM(E19:E22) -> 7140 | F23: =SUM(F19:F22) -> 7140 | G23: =SUM(G19:G22) -> 7140 | H23: =SUM(H19:H22) -> 9590 | I23: =SUM(I19:I22) -> 9590 | ... M23: =SUM(M19:M22) -> 9590 | N23: =SUM(B23:M23) -> 90030
A24: 净贡献（增量毛利−费用） | B24: =B18-B23 -> -1620 | C24: =C18-C23 -> -1620 | D24: =D18-D23 -> -1620 | E24: =E18-E23 -> 1140 | F24: =F18-F23 -> 1140 | G24: =G18-G23 -> 1140 | H24: =H18-H23 -> 4900 | I24: =I18-I23 -> 4900 | ... M24: =M18-M23 -> 4900 | N24: =SUM(B24:M24) -> 27960
A25: 累计净贡献 | B25: =B24 -> -1620 | C25: =B25+C24 -> -3240 | D25: =C25+D24 -> -4860 | E25: =D25+E24 -> -3720 | F25: =E25+F24 -> -2580 | G25: =F25+G24 -> -1440 | H25: =G25+H24 -> 3460 | I25: =H25+I24 -> 8360 | J25: =I25+J24 -> 13260 | ... M25: =L25+M24 -> 27960
A26: ROI（增量销售额÷费用合计） | B26: =IFERROR(B13/B23,0) -> 1.8699187 | C26: =IFERROR(C13/C23,0) -> 1.8699187 | D26: =IFERROR(D13/D23,0) -> 1.8699187 | E26: =IFERROR(E13/E23,0) -> 3.8655462 | F26: =IFERROR(F13/F23,0) -> 3.8655462 | G26: =IFERROR(G13/G23,0) -> 3.8655462 | H26: =IFERROR(H13/H23,0) -> 5.0364964 | I26: =IFERROR(I13/I23,0) -> 5.0364964 | ... N26: =IFERROR(N13/N23,0) -> 4.3685438
A28: ③ 关键结论
A29: 全年岗位增量销售额（$） | B29: =N13 -> 393300 | C29: 即 ACC放量 + 社媒KOL 两部分合计；不含现有ACC基线。
A30: 全年净贡献（$） | B30: =N24 -> 27960
A31: 首个单月净贡献转正的月份 | B31: =IFERROR(INDEX($B$4:$M$4,MATCH(TRUE(),INDEX($B$24:$M$24>0,0),0)),"12个月内未转正") -> 第4月 | C31: 前期为投入期，看这个月份判断何时开始回本。
A32: 全年保本所需账号月销售额（$） | B32: =IFERROR((参数!B11*12+参数!B10*6)/(SUMPRODUCT(B9:M9)*(参数!B7-参数!B8)+SUMPRODUCT(B11:M11)*(参数!B7-参数!B9)),0) -> 714285.71 | C32: 第一年整体不亏的门槛；用来判断这个岗位适合覆盖多大体量的账号。
A33: 稳定期（第7月起）单月保本销售额（$） | B33: =IFERROR(参数!B11/(参数!D14*(参数!B7-参数!B8)+参数!D15*(参数!B7-参数!B9)),0) -> 400000 | C33: 跑通之后的长期门槛，低于这个体量建议一人覆盖多个账号。

Sheet 品线拆分
A1: 全年增量按品线拆分（按GMV占比分摊，各品线占比口径相同）
A2: 如某品线达人资源更好/更差，可后续改为分品线占比；当前为平均口径。
A4: 品线 | B4: 全年GMV（$） | C4: 现有ACC基线（$） | D4: ACC放量增量（$） | E4: 社媒KOL新增（$） | F4: 岗位增量合计（$） | G4: 增量毛利（$） | H4: 增量占GMV
A5: =参数!A19 -> 油泵 | B5: =参数!B19*12 -> 2400000 | C5: =B5*参数!$B$6 -> 126000 | D5: =B5*月度测算!$N$9 -> 27000 | E5: =B5*月度测算!$N$11 -> 30000 | F5: =D5+E5 -> 57000 | G5: =F5*参数!$B$7 -> 17100 | H5: =IFERROR(F5/B5,0) -> 0.02375
A6: =参数!A20 -> 充气泵 | B6: =参数!B20*12 -> 3000000 | C6: =B6*参数!$B$6 -> 157500 | D6: =B6*月度测算!$N$9 -> 33750 | E6: =B6*月度测算!$N$11 -> 37500 | F6: =D6+E6 -> 71250 | G6: =F6*参数!$B$7 -> 21375 | H6: =IFERROR(F6/B6,0) -> 0.02375
A7: =参数!A21 -> 逆变器 | B7: =参数!B21*12 -> 4080000 | C7: =B7*参数!$B$6 -> 214200 | D7: =B7*月度测算!$N$9 -> 45900 | E7: =B7*月度测算!$N$11 -> 51000 | F7: =D7+E7 -> 96900 | G7: =F7*参数!$B$7 -> 29070 | H7: =IFERROR(F7/B7,0) -> 0.02375
A8: =参数!A22 -> 冲击扳手 | B8: =参数!B22*12 -> 3120000 | C8: =B8*参数!$B$6 -> 163800 | D8: =B8*月度测算!$N$9 -> 35100 | E8: =B8*月度测算!$N$11 -> 39000 | F8: =D8+E8 -> 74100 | G8: =F8*参数!$B$7 -> 22230 | H8: =IFERROR(F8/B8,0) -> 0.02375
A9: =参数!A23 -> 黄油枪 | B9: =参数!B23*12 -> 1560000 | C9: =B9*参数!$B$6 -> 81900 | D9: =B9*月度测算!$N$9 -> 17550 | E9: =B9*月度测算!$N$11 -> 19500 | F9: =D9+E9 -> 37050 | G9: =F9*参数!$B$7 -> 11115 | H9: =IFERROR(F9/B9,0) -> 0.02375
A10: =参数!A24 -> 工作灯 | B10: =参数!B24*12 -> 2400000 | C10: =B10*参数!$B$6 -> 126000 | D10: =B10*月度测算!$N$9 -> 27000 | E10: =B10*月度测算!$N$11 -> 30000 | F10: =D10+E10 -> 57000 | G10: =F10*参数!$B$7 -> 17100 | H10: =IFERROR(F10/B10,0) -> 0.02375
A11: 合计 | B11: =SUM(B5:B10) -> 16560000 | C11: =SUM(C5:C10) -> 869400 | D11: =SUM(D5:D10) -> 186300 | E11: =SUM(E5:E10) -> 207000 | F11: =SUM(F5:F10) -> 393300 | G11: =SUM(G5:G10) -> 117990 | H11: =IFERROR(F11/B11,0) -> 0.02375
A13: 校验：岗位增量合计应等于「月度测算」N13 → | F13: =F11-月度测算!N13 -> 0
