Workbook

Sheet 总览
A1: 逆变器广告 9月 vs 10月 汇总（数据：领星 ASIN 表现日报 2026-09-01 ~ 2026-10-26）
A2: 金额单位：美元（领星导出已统一折算为 $）。10月仅 26 天，花费/销量的环比按“日均”比较；比率指标（ACOS 等）直接比较。
A4: 阈值（蓝字可改，SPU/ASIN 表的高亮会随之更新） | F4: 广告跑飞 ASIN 摘要
A5: ACOS 偏高 | B5: 0.5 | C5: ACOS ≥ 此值标红 | F5: 风险等级 | G5: ASIN数 | H5: 10月花费 | I5: 10月超额花费
A6: TACOS 偏高 | B6: 0.25 | C6: TACOS ≥ 此值标红 | F6: 高 | G6: =COUNTIF(广告跑飞ASIN!$A$5:$A$21,F6) -> 13 | H6: =SUMIF(广告跑飞ASIN!$A$5:$A$21,F6,广告跑飞ASIN!$F$5:$F$21) -> 10957.66 | I6: =SUMIF(广告跑飞ASIN!$A$5:$A$21,F6,广告跑飞ASIN!$Q$5:$Q$21) -> 4350.8686
A7: CPC 偏高 | B7: 1 | C7: CPC ≥ 此值标黄 | F7: 中 | G7: =COUNTIF(广告跑飞ASIN!$A$5:$A$21,F7) -> 4 | H7: =SUMIF(广告跑飞ASIN!$A$5:$A$21,F7,广告跑飞ASIN!$F$5:$F$21) -> 6013.76 | I7: =SUMIF(广告跑飞ASIN!$A$5:$A$21,F7,广告跑飞ASIN!$Q$5:$Q$21) -> 870.65844
A8: 广告CVR 偏低 | B8: 0.03 | C8: 广告CVR < 此值标黄（点击 ≥ 100 时） | F8: 低 | G8: =COUNTIF(广告跑飞ASIN!$A$5:$A$21,F8) -> 0 | H8: =SUMIF(广告跑飞ASIN!$A$5:$A$21,F8,广告跑飞ASIN!$F$5:$F$21) -> 0 | I8: =SUMIF(广告跑飞ASIN!$A$5:$A$21,F8,广告跑飞ASIN!$Q$5:$Q$21) -> 0
A9: 日均花费环比 暴涨 | B9: 0.5 | C9: 10月日均花费比9月高出此比例标红
A10: ACOS 恶化(百分点) | B10: 0.1 | C10: 10月 ACOS − 9月 ACOS ≥ 此值标红 | F10: 详见「广告跑飞ASIN」页；价格变化见「SPU价格监控」「价格变动明细」。
A11: 价格变动阈值 | B11: 0.05 | C11: SPU 周均价/挂牌价 变动 ≥ 此值标色
A13: 说明：阈值为分析假设（非业务给定），可按目标利润率调整；“品类均值”行由各 SPU 汇总求和后计算。
A15: 品类核心指标
A16: 指标 | B16: 9月 | C16: 10月 | D16: 变化
A17: 广告花费 | B17: =SPU月度汇总!C21 -> 34165.36 | C17: =SPU月度汇总!X21 -> 32021.91 | D17: =IF(N(B17)=0,"",C17/B17-1) -> -0.062737521
A18: 日均花费 | B18: =SPU月度汇总!U21 -> 1138.8453 | C18: =SPU月度汇总!AP21 -> 1231.6119 | D18: =IF(N(B18)=0,"",C18/B18-1) -> 0.081456706
A19: 广告销售额 | B19: =SPU月度汇总!D21 -> 80180.77 | C19: =SPU月度汇总!Y21 -> 83159.75 | D19: =IF(N(B19)=0,"",C19/B19-1) -> 0.037153297
A20: 销售额 | B20: =SPU月度汇总!H21 -> 213471.15 | C20: =SPU月度汇总!AC21 -> 251392.03 | D20: =IF(N(B20)=0,"",C20/B20-1) -> 0.17763937
A21: 日均销量 | B21: =SPU月度汇总!V21 -> 202.13333 | C21: =SPU月度汇总!AQ21 -> 292.11538 | D21: =IF(N(B21)=0,"",C21/B21-1) -> 0.44516186
A22: ACOS | B22: =SPU月度汇总!M21 -> 0.42610416 | C22: =SPU月度汇总!AH21 -> 0.38506501 | D22: =C22-B22 -> -0.041039154
A23: TACOS | B23: =SPU月度汇总!N21 -> 0.16004673 | C23: =SPU月度汇总!AI21 -> 0.12737838 | D23: =C23-B23 -> -0.03266835
A24: CPC | B24: =SPU月度汇总!P21 -> 0.7535867 | C24: =SPU月度汇总!AK21 -> 0.74980472 | D24: =IF(N(B24)=0,"",C24/B24-1) -> -0.0050186387
A25: CTR | B25: =SPU月度汇总!Q21 -> 0.0073967784 | C25: =SPU月度汇总!AL21 -> 0.0076380945 | D25: =C25-B25 -> 0.00024131608
A26: 广告CVR | B26: =SPU月度汇总!R21 -> 0.047488806 | C26: =SPU月度汇总!AM21 -> 0.057554968 | D26: =C26-B26 -> 0.010066162
A27: 广告单占比 | B27: =SPU月度汇总!S21 -> 0.3855659 | C27: =SPU月度汇总!AN21 -> 0.35752727 | D27: =C27-B27 -> -0.02803863
A28: 成交均价 | B28: =SPU月度汇总!T21 -> 35.203026 | C28: =SPU月度汇总!AO21 -> 33.099675 | D28: =IF(N(B28)=0,"",C28/B28-1) -> -0.059749161
A29: 结算毛利润 | B29: =SPU月度汇总!L21 -> -25524.08 | C29: =SPU月度汇总!AG21 -> 4077.36 | D29: =C29-B29 -> 29601.44
A30: 变化列：金额类为环比%，比率类为百分点差；日均花费/销量为按天数折算。

Sheet 广告跑飞ASIN
A1: 广告跑飞 ASIN 重点清单
A2: 判定规则（满足任一即入列）：①10月花费≥$100 且 ACOS≥60% 或无广告出单；②ACOS 环比恶化≥15pp；③日均花费环比≥+50% 且 ACOS 未改善且高于品类均值；④TACOS≥30%；⑤近7天(10/20–10/26)花费≥$50 且 ACOS≥80% 或零出单；⑥点击≥200 且广告CVR<2%；⑦高ACOS且当月结算亏损。等级：≥3条规则 / ACOS≥100% / 超额花费≥$500 为「高」。超额花费 = 10月花费 − 10月广告销售额 × 品类10月平均ACOS（38.5%）。
A4: 风险等级 | B4: ASIN | C4: SPU | D4: 型号 | E4: 9月花费 | F4: 10月花费 | G4: 日均花费环比 | H4: 近7天日均花费 | I4: 9月ACOS | J4: 10月ACOS | K4: 近7天ACOS | L4: 10月TACOS | M4: 9月CPC | N4: 10月CPC | O4: 10月广告CVR | P4: 10月广告订单 | Q4: 10月超额花费 | R4: 10月结算毛利润 | S4: 触发规则 | T4: 花费店铺(10月) | U4: 建议动作
A5: 高 | B5: B0CQ2JJ51T | C5: SPU07022 | D5: 米沃奇-电源逆变器-200W | E5: 2645.07 | F5: 3852.8 | G5: 0.6806884 | H5: 70.052857 | I5: 0.48262417 | J5: 0.54329908 | K5: 0.50322746 | L5: 0.27517956 | M5: 0.6824226 | N5: 0.78039295 | O5: 0.046789548 | P5: 231 | Q5: 1122.1153 | R5: -1910.08 | S5: 日均花费 +68% 且ACOS未改善；广告高花费且结算亏损 | T5: HK8-US $3057/ACOS 54%；AMZ8-CA $796/ACOS 56%；AMZ8-US $0/无出单 | U5: 花费放量但产出未跟上：回收新增预算，按 ACOS 分层调价
A6: 高 | B6: B0GXHN35JL | C6: SPU50039 | D6: 米沃奇-单包逆变器350W-修正波版-美规-红色 | E6: 1799.96 | F6: 2071.66 | G6: 0.32801669 | H6: 71.367143 | I6: 0.67312381 | J6: 0.8168652 | K6: 1.7290946 | L6: 0.40774849 | M6: 1.1553017 | N6: 1.0938015 | O6: 0.033790919 | P6: 64 | Q6: 1095.0928 | R6: -2342.14 | S6: 10月ACOS 82%；TACOS 41%；近7天ACOS 173%；广告高花费且结算亏损 | T6: AMZ5-US $2072/ACOS 82% | U6: 收紧预算，降低宽泛/自动广告竞价，否定无效词
A7: 高 | B7: B0GXJ1P8X2 | C7: SPU50039 | D7: 牧田-单包逆变器350W-修正波版-美规-蓝色 | E7: 822.37 | F7: 861.16 | G7: 0.2082714 | H7: 26.105714 | I7: 0.6183512 | J7: 0.80520622 | K7: 1.3952814 | L7: 0.4441854 | M7: 0.8348934 | N7: 0.77933032 | O7: 0.022624434 | P7: 25 | Q7: 449.33682 | R7: -602.47 | S7: 10月ACOS 81%；ACOS恶化 62%→81%；TACOS 44%；近7天ACOS 140%；广告高花费且结算亏损 | T7: AMZ5-US $861/ACOS 81% | U7: 点击转化差：检查价格/评分/Listing 与竞品差距，先降竞价再优化转化
A8: 高 | B8: B0FHPXK8SM | C8: SPU07116 | D8: 米沃奇-电源逆变器-双插脚-350W | E8: 840.11 | F8: 594.43 | G8: -0.18358219 | H8: 0 | I8: 0.56142074 | J8: 1.3466618 | L8: 1.3524219 | M8: 1.082616 | N8: 1.2131224 | O8: 0.018367347 | P8: 9 | Q8: 424.45845 | R8: -3037.01 | S8: 10月ACOS 135%；ACOS恶化 56%→135%；TACOS 135%；广告CVR 1.8% | T8: AMZ5-US $594/ACOS 135% | U8: 立即暂停/大幅降预算，排查广告组与投放词；仅保留品牌词与核心精准词
A9: 高 | B9: B0G2B7W1WS | C9: SPU07130 | D9: 牧田-电源逆变器-双插脚-550W | E9: 607.85 | F9: 504.53 | G9: -0.042280168 | H9: 17.724286 | I9: 0.55105297 | J9: 1.4808195 | L9: 0.26598728 | M9: 1.0302542 | N9: 1.0192525 | O9: 0.0060606061 | P9: 3 | Q9: 373.3345 | R9: -189.21 | S9: 10月ACOS 148%；ACOS恶化 55%→148%；近7天花$124零广告出单；广告CVR 0.6%；广告高花费且结算亏损 | T9: AMZ8-US $505/ACOS 148% | U9: 立即暂停/大幅降预算，排查广告组与投放词；仅保留品牌词与核心精准词
A10: 高 | B10: B0D4DW8QV2 | C10: SPU07022 | D10: 米沃奇-电源逆变器-200W | E10: 561.4 | F10: 536.42 | G10: 0.10250473 | H10: 22.101429 | I10: 0.67867505 | J10: 0.61500539 | K10: 0.45030125 | L10: 0.30693262 | M10: 0.64013683 | N10: 0.68420918 | O10: 0.043367347 | P10: 34 | Q10: 200.5586 | R10: -215.73 | S10: 10月ACOS 62%；TACOS 31%；广告高花费且结算亏损 | T10: AMZ15-US $342/ACOS 55%；AMZ15-CA $194/ACOS 78% | U10: 收紧预算，降低宽泛/自动广告竞价，否定无效词
A11: 高 | B11: B0FLQ5Y1XM | C11: SPU07120 | D11: 得伟-电源逆变器-双插脚-550W | E11: 420.31 | F11: 617.27 | G11: 0.69454597 | H11: 20.854286 | I11: 0.20055924 | J11: 0.51650071 | K11: 0.49262646 | L11: 0.056241128 | M11: 0.43286303 | N11: 0.59182167 | O11: 0.014381592 | P11: 15 | Q11: 157.07881 | R11: 1848.17 | S11: ACOS恶化 20%→52%；日均花费 +69% 且ACOS未改善；广告CVR 1.4% | T11: AMZ8-US $494/ACOS 57%；AMZ8-CA $124/ACOS 37% | U11: CPC 上涨推高 ACOS：下调竞价 15–25%，否定高花费零单搜索词
A12: 高 | B12: B0FM2KM4CR | C12: SPU07051 | D12: 牧田-电源逆变器200W | E12: 196.39 | F12: 424.91 | G12: 1.496465 | H12: 15.282857 | I12: 0.50644695 | J12: 0.55641254 | K12: 1.3337489 | L12: 0.72955942 | M12: 0.55011204 | N12: 0.5959467 | O12: 0.029453015 | P12: 21 | Q12: 130.85125 | R12: -288.59 | S12: 日均花费 +150% 且ACOS未改善；TACOS 73%；近7天ACOS 133%；广告高花费且结算亏损 | T12: AMZ8-US $425/ACOS 56% | U12: 点击转化差：检查价格/评分/Listing 与竞品差距，先降竞价再优化转化
A13: 高 | B13: B0F2MN7KK8 | C13: SPU07055 | D13: 得伟-双向逆变器-65W | E13: 232.37 | F13: 221.31 | G13: 0.098927109 | H13: 7.19 | I13: 0.57129862 | J13: 0.69027791 | K13: 1.0989083 | L13: 0.50861831 | M13: 0.65089636 | N13: 0.63412607 | O13: 0.037249284 | P13: 13 | Q13: 97.854307 | R13: -88.24 | S13: 10月ACOS 69%；TACOS 51%；近7天ACOS 110%；广告高花费且结算亏损 | T13: AMZ15-CA $221/ACOS 69% | U13: 收紧预算，降低宽泛/自动广告竞价，否定无效词
A14: 高 | B14: B0GXHPWWL2 | C14: SPU50039 | D14: 得伟-单包逆变器350W-修正波版-美规-黄色 | E14: 165.43 | F14: 101.49 | G14: -0.29212449 | H14: 0.0014285714 | I14: 1.0607207 | J14: 2.6429688 | L14: 0.25059878 | M14: 0.52351266 | N14: 0.48793269 | O14: 0.0048076923 | P14: 1 | Q14: 86.703504 | R14: -48.59 | S14: 10月ACOS 264%；广告CVR 0.5% | T14: HK8-US $101/ACOS 264% | U14: 立即暂停/大幅降预算，排查广告组与投放词；仅保留品牌词与核心精准词
A15: 高 | B15: B0FLQ71NRS | C15: SPU07121 | D15: 米沃奇-电源逆变器-双插脚-550W | E15: 349.65 | F15: 764.77 | G15: 1.5237435 | H15: 30.47 | I15: 0.22957525 | J15: 0.43251574 | K15: 0.66746988 | L15: 0.10020033 | M15: 0.51723373 | N15: 0.51499663 | O15: 0.012121212 | P15: 18 | Q15: 83.901899 | R15: 2187.5 | S15: ACOS恶化 23%→43%；日均花费 +152% 且ACOS未改善；广告CVR 1.2% | T15: AMZ8-US $765/ACOS 43% | U15: 点击转化差：检查价格/评分/Listing 与竞品差距，先降竞价再优化转化
A16: 高 | B16: B0GXJ4276L | C16: SPU50039 | D16: 牧田-单包逆变器350W-修正波版-美规-蓝色 | E16: 775.8 | F16: 131.68 | G16: -0.80415254 | H16: 0.0014285714 | I16: 0.70635795 | J16: 1.0180131 | L16: 0.29012713 | M16: 0.60139535 | N16: 0.42070288 | O16: 0.012779553 | P16: 4 | Q16: 81.871841 | R16: -7.23 | S16: 10月ACOS 102%；广告CVR 1.3% | T16: HK8-US $132/ACOS 102% | U16: 立即暂停/大幅降预算，排查广告组与投放词；仅保留品牌词与核心精准词
A17: 高 | B17: B0FM7FTP4N | C17: SPU07051 | D17: 牧田-电源逆变器200W-2个装 | E17: 96.79 | F17: 275.23 | G17: 2.2810526 | H17: 15.511429 | I17: 0.24022138 | J17: 0.46581254 | K17: 0.38513106 | L17: 0.38288608 | M17: 0.88798165 | N17: 1.0626641 | O17: 0.054054054 | P17: 14 | Q17: 47.710488 | R17: -214.94 | S17: ACOS恶化 24%→47%；日均花费 +228% 且ACOS未改善；TACOS 38%；广告高花费且结算亏损 | T17: AMZ15-US $275/ACOS 47% | U17: CPC 上涨推高 ACOS：下调竞价 15–25%，否定高花费零单搜索词
A18: 中 | B18: B0DQKKF484 | C18: SPU07060 | D18: 利优比-电源逆变器-200W | E18: 2474.49 | F18: 1577.74 | G18: -0.26430528 | H18: 22.68 | I18: 0.36483827 | J18: 0.49552447 | L18: 0.28006788 | M18: 0.4483584 | N18: 0.46213825 | O18: 0.023140012 | P18: 79 | Q18: 351.70071 | R18: 498.91 | S18: 近7天花$159零广告出单 | T18: AMZ5-US $1578/ACOS 50%；HK5-US $0/无出单 | U18: 点击转化差：检查价格/评分/Listing 与竞品差距，先降竞价再优化转化
A19: 中 | B19: B0CQ4PFGH5 | C19: SPU07022 | D19: 米沃奇-电源逆变器-200W | E19: 2584.13 | F19: 3709 | G19: 0.65611459 | H19: 242.01714 | I19: 0.46512293 | J19: 0.41581603 | K19: 0.43166362 | L19: 0.19943562 | M19: 1.053457 | N19: 0.6941793 | O19: 0.066067752 | P19: 353 | Q19: 274.29327 | R19: -1758.54 | S19: 广告高花费且结算亏损 | T19: HK5-US $3156/ACOS 42%；AMZ5-US $553/ACOS 37% | U19: 花费放量但产出未跟上：回收新增预算，按 ACOS 分层调价
A20: 中 | B20: B0FG2CBW2F | C20: SPU07115 | D20: 得伟-电源逆变器-双插脚-350W,得伟-电源逆变器400W-双插脚AK47,正宗AC美标110V,PD20w-美规-黄黑 | E20: 648.75 | F20: 352.41 | G20: -0.37321476 | H20: 1.2057143 | I20: 0.72844968 | J20: 0.70539843 | K20: 0.13189561 | L20: 0.20511373 | M20: 0.63853346 | N20: 0.92496063 | O20: 0.034120735 | P20: 13 | Q20: 160.03537 | R20: -224.81 | S20: 10月ACOS 71%；广告高花费且结算亏损 | T20: AMZ5-US $352/ACOS 71% | U20: 收紧预算，降低宽泛/自动广告竞价，否定无效词
A21: 中 | B21: B0DB1YHDFZ | C21: SPU07055 | D21: 得伟-双向逆变器-65W | E21: 351.93 | F21: 374.61 | G21: 0.22820535 | H21: 8.2285714 | I21: 0.44897048 | J21: 0.4974438 | K21: 0.28849043 | L21: 0.72292016 | M21: 0.59347386 | N21: 0.61919008 | O21: 0.039669421 | P21: 24 | Q21: 84.629093 | R21: -226.13 | S21: TACOS 72%；广告高花费且结算亏损 | T21: AMZ5-US $375/ACOS 50% | U21: 收紧预算，降低宽泛/自动广告竞价，否定无效词
F22: =SUM(F5:F21) -> 16971.42 | P22: 合计 | Q22: =SUM(Q5:Q21) -> 5221.527

Sheet SPU月度汇总
A1: SPU 维度 · 9月 vs 10月 广告与销售汇总
A3: SPU | B3: 款名（品牌） | C3: 2026年9月（30天） | X3: 2026年10月（26天） | AS3: 10月 vs 9月
C4: 广告花费 | D4: 广告销售额 | E4: 广告订单量 | F4: 点击 | G4: 展示 | H4: 销售额 | I4: 销量 | J4: 订单量 | K4: Sessions-Total | L4: 结算毛利润 | M4: ACOS | N4: TACOS | O4: ROAS | P4: CPC | Q4: CTR | R4: 广告CVR | S4: 广告单占比 | T4: 成交均价 | U4: 日均花费 | V4: 日均销量 | W4: 毛利率 | X4: 广告花费 | Y4: 广告销售额 | Z4: 广告订单量 | AA4: 点击 | AB4: 展示 | AC4: 销售额 | AD4: 销量 | AE4: 订单量 | AF4: Sessions-Total | AG4: 结算毛利润 | AH4: ACOS | AI4: TACOS | AJ4: ROAS | AK4: CPC | AL4: CTR | AM4: 广告CVR | AN4: 广告单占比 | AO4: 成交均价 | AP4: 日均花费 | AQ4: 日均销量 | AR4: 毛利率 | AS4: 日均花费环比 | AT4: 广告销售额日均环比 | AU4: 日均销量环比 | AV4: ACOS变化(pp) | AW4: TACOS变化(pp) | AX4: CPC环比 | AY4: 广告CVR变化(pp) | AZ4: 成交均价环比
A5: SPU07021 | B5: 逆变器-200W（得伟） | C5: 6278.14 | D5: 13794.77 | E5: 456 | F5: 5664 | G5: 1017432 | H5: 48596.36 | I5: 1820 | J5: 1622 | K5: 57828 | L5: -1543.86 | M5: =IF(N(D5)=0,"",C5/D5) -> 0.45511016 | N5: =IF(N(H5)=0,"",C5/H5) -> 0.12918951 | O5: =IF(N(C5)=0,"",D5/C5) -> 2.1972702 | P5: =IF(N(F5)=0,"",C5/F5) -> 1.1084287 | Q5: =IF(N(G5)=0,"",F5/G5) -> 0.0055669568 | R5: =IF(N(F5)=0,"",E5/F5) -> 0.080508475 | S5: =IF(N(J5)=0,"",E5/J5) -> 0.2811344 | T5: =IF(N(I5)=0,"",H5/I5) -> 26.701297 | U5: =IF(N(30)=0,"",C5/30) -> 209.27133 | V5: =IF(N(30)=0,"",I5/30) -> 60.666667 | W5: =IF(N(H5)=0,"",L5/H5) -> -0.031769046 | X5: 9619.07 | Y5: 33108.67 | Z5: 1064 | AA5: 11315 | AB5: 1410010 | AC5: 92025.43 | AD5: 3320 | AE5: 2890 | AF5: 79851 | AG5: -816.98 | AH5: =IF(N(Y5)=0,"",X5/Y5) -> 0.29053024 | AI5: =IF(N(AC5)=0,"",X5/AC5) -> 0.10452622 | AJ5: =IF(N(X5)=0,"",Y5/X5) -> 3.4419824 | AK5: =IF(N(AA5)=0,"",X5/AA5) -> 0.85011666 | AL5: =IF(N(AB5)=0,"",AA5/AB5) -> 0.0080247658 | AM5: =IF(N(AA5)=0,"",Z5/AA5) -> 0.094034468 | AN5: =IF(N(AE5)=0,"",Z5/AE5) -> 0.36816609 | AO5: =IF(N(AD5)=0,"",AC5/AD5) -> 27.718503 | AP5: =IF(N(26)=0,"",X5/26) -> 369.96423 | AQ5: =IF(N(26)=0,"",AD5/26) -> 127.69231 | AR5: =IF(N(AC5)=0,"",AG5/AC5) -> -0.0088777635 | AS5: =IF(OR(U5="",AP5=""),"",IF(N(U5)=0,"",AP5/U5-1)) -> 0.76786866 | AT5: =IF(N(D5)=0,"",(Y5/26)/(D5/30)-1) -> 1.769333 | AU5: =IF(OR(V5="",AQ5=""),"",IF(N(V5)=0,"",AQ5/V5-1)) -> 1.1048183 | AV5: =IF(OR(M5="",AH5=""),"",AH5-M5) -> -0.16457992 | AW5: =IF(OR(N5="",AI5=""),"",AI5-N5) -> -0.024663295 | AX5: =IF(OR(P5="",AK5=""),"",IF(N(P5)=0,"",AK5/P5-1)) -> -0.23304342 | AY5: =IF(OR(R5="",AM5=""),"",AM5-R5) -> 0.013525993 | AZ5: =IF(OR(T5="",AO5=""),"",IF(N(T5)=0,"",AO5/T5-1)) -> 0.038095764
A6: SPU07022 | B6: 逆变器-200W（米沃奇） | C6: 6127.31 | D6: 14149.59 | E6: 486 | F6: 7661 | G6: 1418377 | H6: 35692.21 | I6: 1281 | J6: 1165 | K6: 34400 | L6: -1523.49 | M6: =IF(N(D6)=0,"",C6/D6) -> 0.43303799 | N6: =IF(N(H6)=0,"",C6/H6) -> 0.17167079 | O6: =IF(N(C6)=0,"",D6/C6) -> 2.3092662 | P6: =IF(N(F6)=0,"",C6/F6) -> 0.79980551 | Q6: =IF(N(G6)=0,"",F6/G6) -> 0.0054012438 | R6: =IF(N(F6)=0,"",E6/F6) -> 0.063438193 | S6: =IF(N(J6)=0,"",E6/J6) -> 0.41716738 | T6: =IF(N(I6)=0,"",H6/I6) -> 27.862771 | U6: =IF(N(30)=0,"",C6/30) -> 204.24367 | V6: =IF(N(30)=0,"",I6/30) -> 42.7 | W6: =IF(N(H6)=0,"",L6/H6) -> -0.042684104 | X6: 8643.51 | Y6: 21270.14 | Z6: 710 | AA6: 11822 | AB6: 2052166 | AC6: 46126.14 | AD6: 1718 | AE6: 1556 | AF6: 45311 | AG6: -3526.95 | AH6: =IF(N(Y6)=0,"",X6/Y6) -> 0.40636827 | AI6: =IF(N(AC6)=0,"",X6/AC6) -> 0.18738854 | AJ6: =IF(N(X6)=0,"",Y6/X6) -> 2.4608221 | AK6: =IF(N(AA6)=0,"",X6/AA6) -> 0.73113771 | AL6: =IF(N(AB6)=0,"",AA6/AB6) -> 0.0057607426 | AM6: =IF(N(AA6)=0,"",Z6/AA6) -> 0.06005752 | AN6: =IF(N(AE6)=0,"",Z6/AE6) -> 0.4562982 | AO6: =IF(N(AD6)=0,"",AC6/AD6) -> 26.848743 | AP6: =IF(N(26)=0,"",X6/26) -> 332.44269 | AQ6: =IF(N(26)=0,"",AD6/26) -> 66.076923 | AR6: =IF(N(AC6)=0,"",AG6/AC6) -> -0.076463151 | AS6: =IF(OR(U6="",AP6=""),"",IF(N(U6)=0,"",AP6/U6-1)) -> 0.62767687 | AT6: =IF(N(D6)=0,"",(Y6/26)/(D6/30)-1) -> 0.73450038 | AU6: =IF(OR(V6="",AQ6=""),"",IF(N(V6)=0,"",AQ6/V6-1)) -> 0.54746892 | AV6: =IF(OR(M6="",AH6=""),"",AH6-M6) -> -0.026669719 | AW6: =IF(OR(N6="",AI6=""),"",AI6-N6) -> 0.015717746 | AX6: =IF(OR(P6="",AK6=""),"",IF(N(P6)=0,"",AK6/P6-1)) -> -0.085855622 | AY6: =IF(OR(R6="",AM6=""),"",AM6-R6) -> -0.0033806736 | AZ6: =IF(OR(T6="",AO6=""),"",IF(N(T6)=0,"",AO6/T6-1)) -> -0.036393672
A7: SPU50039 | B7: 单包逆变器（得伟/米沃奇/牧田） | C7: 6794.83 | D7: 12233.82 | E7: 286 | F7: 7376 | G7: 762158 | H7: 24210.94 | I7: 584 | J7: 554 | K7: 19274 | L7: -3088.64 | M7: =IF(N(D7)=0,"",C7/D7) -> 0.5554136 | N7: =IF(N(H7)=0,"",C7/H7) -> 0.28065123 | O7: =IF(N(C7)=0,"",D7/C7) -> 1.8004601 | P7: =IF(N(F7)=0,"",C7/F7) -> 0.92120797 | Q7: =IF(N(G7)=0,"",F7/G7) -> 0.0096777833 | R7: =IF(N(F7)=0,"",E7/F7) -> 0.038774403 | S7: =IF(N(J7)=0,"",E7/J7) -> 0.51624549 | T7: =IF(N(I7)=0,"",H7/I7) -> 41.457089 | U7: =IF(N(30)=0,"",C7/30) -> 226.49433 | V7: =IF(N(30)=0,"",I7/30) -> 19.466667 | W7: =IF(N(H7)=0,"",L7/H7) -> -0.12757208 | X7: 4577.37 | Y7: 7518.68 | Z7: 183 | AA7: 5038 | AB7: 498105 | AC7: 15346.59 | AD7: 367 | AE7: 350 | AF7: 13394 | AG7: -3097.11 | AH7: =IF(N(Y7)=0,"",X7/Y7) -> 0.60879968 | AI7: =IF(N(AC7)=0,"",X7/AC7) -> 0.29826626 | AJ7: =IF(N(X7)=0,"",Y7/X7) -> 1.6425764 | AK7: =IF(N(AA7)=0,"",X7/AA7) -> 0.90856888 | AL7: =IF(N(AB7)=0,"",AA7/AB7) -> 0.010114333 | AM7: =IF(N(AA7)=0,"",Z7/AA7) -> 0.036323938 | AN7: =IF(N(AE7)=0,"",Z7/AE7) -> 0.52285714 | AO7: =IF(N(AD7)=0,"",AC7/AD7) -> 41.816322 | AP7: =IF(N(26)=0,"",X7/26) -> 176.05269 | AQ7: =IF(N(26)=0,"",AD7/26) -> 14.115385 | AR7: =IF(N(AC7)=0,"",AG7/AC7) -> -0.20181096 | AS7: =IF(OR(U7="",AP7=""),"",IF(N(U7)=0,"",AP7/U7-1)) -> -0.22270597 | AT7: =IF(N(D7)=0,"",(Y7/26)/(D7/30)-1) -> -0.29086745 | AU7: =IF(OR(V7="",AQ7=""),"",IF(N(V7)=0,"",AQ7/V7-1)) -> -0.27489463 | AV7: =IF(OR(M7="",AH7=""),"",AH7-M7) -> 0.053386084 | AW7: =IF(OR(N7="",AI7=""),"",AI7-N7) -> 0.017615034 | AX7: =IF(OR(P7="",AK7=""),"",IF(N(P7)=0,"",AK7/P7-1)) -> -0.013720132 | AY7: =IF(OR(R7="",AM7=""),"",AM7-R7) -> -0.0024504654 | AZ7: =IF(OR(T7="",AO7=""),"",IF(N(T7)=0,"",AO7/T7-1)) -> 0.0086651642
A8: SPU07060 | B8: 逆变器-200W（利优比） | C8: 6271.94 | D8: 19415.76 | E8: 495 | F8: 11899 | G8: 1390844 | H8: 47276.01 | I8: 1203 | J8: 1159 | K8: 38122 | L8: 4486.43 | M8: =IF(N(D8)=0,"",C8/D8) -> 0.32303345 | N8: =IF(N(H8)=0,"",C8/H8) -> 0.13266644 | O8: =IF(N(C8)=0,"",D8/C8) -> 3.0956546 | P8: =IF(N(F8)=0,"",C8/F8) -> 0.52709808 | Q8: =IF(N(G8)=0,"",F8/G8) -> 0.008555237 | R8: =IF(N(F8)=0,"",E8/F8) -> 0.041600134 | S8: =IF(N(J8)=0,"",E8/J8) -> 0.42709232 | T8: =IF(N(I8)=0,"",H8/I8) -> 39.298429 | U8: =IF(N(30)=0,"",C8/30) -> 209.06467 | V8: =IF(N(30)=0,"",I8/30) -> 40.1 | W8: =IF(N(H8)=0,"",L8/H8) -> 0.09489866 | X8: 2346.6 | Y8: 6844.74 | Z8: 172 | AA8: 4420 | AB8: 418774 | AC8: 49465.86 | AD8: 1217 | AE8: 1166 | AF8: 36883 | AG8: 11479.28 | AH8: =IF(N(Y8)=0,"",X8/Y8) -> 0.3428326 | AI8: =IF(N(AC8)=0,"",X8/AC8) -> 0.047438779 | AJ8: =IF(N(X8)=0,"",Y8/X8) -> 2.9168755 | AK8: =IF(N(AA8)=0,"",X8/AA8) -> 0.53090498 | AL8: =IF(N(AB8)=0,"",AA8/AB8) -> 0.010554619 | AM8: =IF(N(AA8)=0,"",Z8/AA8) -> 0.038914027 | AN8: =IF(N(AE8)=0,"",Z8/AE8) -> 0.14751286 | AO8: =IF(N(AD8)=0,"",AC8/AD8) -> 40.645735 | AP8: =IF(N(26)=0,"",X8/26) -> 90.253846 | AQ8: =IF(N(26)=0,"",AD8/26) -> 46.807692 | AR8: =IF(N(AC8)=0,"",AG8/AC8) -> 0.2320647 | AS8: =IF(OR(U8="",AP8=""),"",IF(N(U8)=0,"",AP8/U8-1)) -> -0.56829699 | AT8: =IF(N(D8)=0,"",(Y8/26)/(D8/30)-1) -> -0.59322855 | AU8: =IF(OR(V8="",AQ8=""),"",IF(N(V8)=0,"",AQ8/V8-1)) -> 0.16727412 | AV8: =IF(OR(M8="",AH8=""),"",AH8-M8) -> 0.019799145 | AW8: =IF(OR(N8="",AI8=""),"",AI8-N8) -> -0.085227662 | AX8: =IF(OR(P8="",AK8=""),"",IF(N(P8)=0,"",AK8/P8-1)) -> 0.0072223787 | AY8: =IF(OR(R8="",AM8=""),"",AM8-R8) -> -0.0026861073 | AZ8: =IF(OR(T8="",AO8=""),"",IF(N(T8)=0,"",AO8/T8-1)) -> 0.034283978
A9: SPU07051 | B9: 逆变器-200W（牧田款）（牧田/工匠） | C9: 3088.11 | D9: 7084.84 | E9: 192 | F9: 4198 | G9: 687156 | H9: 16435.4 | I9: 477 | J9: 421 | K9: 15853 | L9: 1354.99 | M9: =IF(N(D9)=0,"",C9/D9) -> 0.43587576 | N9: =IF(N(H9)=0,"",C9/H9) -> 0.18789381 | O9: =IF(N(C9)=0,"",D9/C9) -> 2.2942317 | P9: =IF(N(F9)=0,"",C9/F9) -> 0.73561458 | Q9: =IF(N(G9)=0,"",F9/G9) -> 0.0061092387 | R9: =IF(N(F9)=0,"",E9/F9) -> 0.045736065 | S9: =IF(N(J9)=0,"",E9/J9) -> 0.45605701 | T9: =IF(N(I9)=0,"",H9/I9) -> 34.455765 | U9: =IF(N(30)=0,"",C9/30) -> 102.937 | V9: =IF(N(30)=0,"",I9/30) -> 15.9 | W9: =IF(N(H9)=0,"",L9/H9) -> 0.082443384 | X9: 2360.78 | Y9: 5842.8 | Z9: 164 | AA9: 3580 | AB9: 563106 | AC9: 12961.03 | AD9: 384 | AE9: 357 | AF9: 13129 | AG9: 498.68 | AH9: =IF(N(Y9)=0,"",X9/Y9) -> 0.40404943 | AI9: =IF(N(AC9)=0,"",X9/AC9) -> 0.18214447 | AJ9: =IF(N(X9)=0,"",Y9/X9) -> 2.4749447 | AK9: =IF(N(AA9)=0,"",X9/AA9) -> 0.65943575 | AL9: =IF(N(AB9)=0,"",AA9/AB9) -> 0.0063575952 | AM9: =IF(N(AA9)=0,"",Z9/AA9) -> 0.045810056 | AN9: =IF(N(AE9)=0,"",Z9/AE9) -> 0.45938375 | AO9: =IF(N(AD9)=0,"",AC9/AD9) -> 33.752682 | AP9: =IF(N(26)=0,"",X9/26) -> 90.799231 | AQ9: =IF(N(26)=0,"",AD9/26) -> 14.769231 | AR9: =IF(N(AC9)=0,"",AG9/AC9) -> 0.038475337 | AS9: =IF(OR(U9="",AP9=""),"",IF(N(U9)=0,"",AP9/U9-1)) -> -0.11791454 | AT9: =IF(N(D9)=0,"",(Y9/26)/(D9/30)-1) -> -0.048434078 | AU9: =IF(OR(V9="",AQ9=""),"",IF(N(V9)=0,"",AQ9/V9-1)) -> -0.071117562 | AV9: =IF(OR(M9="",AH9=""),"",AH9-M9) -> -0.031826329 | AW9: =IF(OR(N9="",AI9=""),"",AI9-N9) -> -0.0057493399 | AX9: =IF(OR(P9="",AK9=""),"",IF(N(P9)=0,"",AK9/P9-1)) -> -0.10355807 | AY9: =IF(OR(R9="",AM9=""),"",AM9-R9) -> 7.3991073e-05 | AZ9: =IF(OR(T9="",AO9=""),"",IF(N(T9)=0,"",AO9/T9-1)) -> -0.020405378
A10: SPU07120 | B10: 逆变器-550W（得伟） | C10: 940.9 | D10: 3326.48 | E10: 43 | F10: 1426 | G10: 114221 | H10: 11977.08 | I10: 127 | J10: 124 | K10: 5956 | L10: -10430.65 | M10: =IF(N(D10)=0,"",C10/D10) -> 0.28285154 | N10: =IF(N(H10)=0,"",C10/H10) -> 0.07855838 | O10: =IF(N(C10)=0,"",D10/C10) -> 3.5354235 | P10: =IF(N(F10)=0,"",C10/F10) -> 0.65981767 | Q10: =IF(N(G10)=0,"",F10/G10) -> 0.012484569 | R10: =IF(N(F10)=0,"",E10/F10) -> 0.030154278 | S10: =IF(N(J10)=0,"",E10/J10) -> 0.34677419 | T10: =IF(N(I10)=0,"",H10/I10) -> 94.307717 | U10: =IF(N(30)=0,"",C10/30) -> 31.363333 | V10: =IF(N(30)=0,"",I10/30) -> 4.2333333 | W10: =IF(N(H10)=0,"",L10/H10) -> -0.87088422 | X10: 780.95 | Y10: 1528.41 | Z10: 26 | AA10: 1177 | AB10: 82939 | AC10: 11536.37 | AD10: 114 | AE10: 106 | AF10: 5211 | AG10: 2153.1 | AH10: =IF(N(Y10)=0,"",X10/Y10) -> 0.51095583 | AI10: =IF(N(AC10)=0,"",X10/AC10) -> 0.067694604 | AJ10: =IF(N(X10)=0,"",Y10/X10) -> 1.9571163 | AK10: =IF(N(AA10)=0,"",X10/AA10) -> 0.66350892 | AL10: =IF(N(AB10)=0,"",AA10/AB10) -> 0.014191153 | AM10: =IF(N(AA10)=0,"",Z10/AA10) -> 0.022090059 | AN10: =IF(N(AE10)=0,"",Z10/AE10) -> 0.24528302 | AO10: =IF(N(AD10)=0,"",AC10/AD10) -> 101.19623 | AP10: =IF(N(26)=0,"",X10/26) -> 30.036538 | AQ10: =IF(N(26)=0,"",AD10/26) -> 4.3846154 | AR10: =IF(N(AC10)=0,"",AG10/AC10) -> 0.18663583 | AS10: =IF(OR(U10="",AP10=""),"",IF(N(U10)=0,"",AP10/U10-1)) -> -0.042304013 | AT10: =IF(N(D10)=0,"",(Y10/26)/(D10/30)-1) -> -0.469845 | AU10: =IF(OR(V10="",AQ10=""),"",IF(N(V10)=0,"",AQ10/V10-1)) -> 0.035735918 | AV10: =IF(OR(M10="",AH10=""),"",AH10-M10) -> 0.22810429 | AW10: =IF(OR(N10="",AI10=""),"",AI10-N10) -> -0.010863776 | AX10: =IF(OR(P10="",AK10=""),"",IF(N(P10)=0,"",AK10/P10-1)) -> 0.0055943472 | AY10: =IF(OR(R10="",AM10=""),"",AM10-R10) -> -0.0080642182 | AZ10: =IF(OR(T10="",AO10=""),"",IF(N(T10)=0,"",AO10/T10-1)) -> 0.073042926
A11: SPU07121 | B11: 逆变器-550W（米沃奇） | C11: 647.67 | D11: 2431.26 | E11: 28 | F11: 947 | G11: 84718 | H11: 11943.21 | I11: 126 | J11: 120 | K11: 3577 | L11: -1756.35 | M11: =IF(N(D11)=0,"",C11/D11) -> 0.26639273 | N11: =IF(N(H11)=0,"",C11/H11) -> 0.054229139 | O11: =IF(N(C11)=0,"",D11/C11) -> 3.7538561 | P11: =IF(N(F11)=0,"",C11/F11) -> 0.68391763 | Q11: =IF(N(G11)=0,"",F11/G11) -> 0.011178262 | R11: =IF(N(F11)=0,"",E11/F11) -> 0.029567054 | S11: =IF(N(J11)=0,"",E11/J11) -> 0.23333333 | T11: =IF(N(I11)=0,"",H11/I11) -> 94.787381 | U11: =IF(N(30)=0,"",C11/30) -> 21.589 | V11: =IF(N(30)=0,"",I11/30) -> 4.2 | W11: =IF(N(H11)=0,"",L11/H11) -> -0.14705845 | X11: 1027.4 | Y11: 2387.99 | Z11: 26 | AA11: 1690 | AB11: 156231 | AC11: 10303.59 | AD11: 106 | AE11: 104 | AF11: 4300 | AG11: 2550.54 | AH11: =IF(N(Y11)=0,"",X11/Y11) -> 0.43023631 | AI11: =IF(N(AC11)=0,"",X11/AC11) -> 0.099712819 | AJ11: =IF(N(X11)=0,"",Y11/X11) -> 2.3243041 | AK11: =IF(N(AA11)=0,"",X11/AA11) -> 0.60792899 | AL11: =IF(N(AB11)=0,"",AA11/AB11) -> 0.010817315 | AM11: =IF(N(AA11)=0,"",Z11/AA11) -> 0.015384615 | AN11: =IF(N(AE11)=0,"",Z11/AE11) -> 0.25 | AO11: =IF(N(AD11)=0,"",AC11/AD11) -> 97.203679 | AP11: =IF(N(26)=0,"",X11/26) -> 39.515385 | AQ11: =IF(N(26)=0,"",AD11/26) -> 4.0769231 | AR11: =IF(N(AC11)=0,"",AG11/AC11) -> 0.24753896 | AS11: =IF(OR(U11="",AP11=""),"",IF(N(U11)=0,"",AP11/U11-1)) -> 0.83034808 | AT11: =IF(N(D11)=0,"",(Y11/26)/(D11/30)-1) -> 0.13331074 | AU11: =IF(OR(V11="",AQ11=""),"",IF(N(V11)=0,"",AQ11/V11-1)) -> -0.029304029 | AV11: =IF(OR(M11="",AH11=""),"",AH11-M11) -> 0.16384357 | AW11: =IF(OR(N11="",AI11=""),"",AI11-N11) -> 0.045483679 | AX11: =IF(OR(P11="",AK11=""),"",IF(N(P11)=0,"",AK11/P11-1)) -> -0.11110788 | AY11: =IF(OR(R11="",AM11=""),"",AM11-R11) -> -0.014182438 | AZ11: =IF(OR(T11="",AO11=""),"",IF(N(T11)=0,"",AO11/T11-1)) -> 0.025491772
A12: SPU07116 | B12: 电源逆变器350W-AC美标110V PD20W（米沃奇） | C12: 884.89 | D12: 1604.97 | E12: 25 | F12: 1005 | G12: 93601 | H12: 1431.16 | I12: 28 | J12: 27 | K12: 1945 | L12: -2584.79 | M12: =IF(N(D12)=0,"",C12/D12) -> 0.55134364 | N12: =IF(N(H12)=0,"",C12/H12) -> 0.61830264 | O12: =IF(N(C12)=0,"",D12/C12) -> 1.8137509 | P12: =IF(N(F12)=0,"",C12/F12) -> 0.88048756 | Q12: =IF(N(G12)=0,"",F12/G12) -> 0.010737065 | R12: =IF(N(F12)=0,"",E12/F12) -> 0.024875622 | S12: =IF(N(J12)=0,"",E12/J12) -> 0.92592593 | T12: =IF(N(I12)=0,"",H12/I12) -> 51.112857 | U12: =IF(N(30)=0,"",C12/30) -> 29.496333 | V12: =IF(N(30)=0,"",I12/30) -> 0.93333333 | W12: =IF(N(H12)=0,"",L12/H12) -> -1.8060804 | X12: 634.88 | Y12: 538.59 | Z12: 11 | AA12: 689 | AB12: 69389 | AC12: 705.89 | AD12: 13 | AE12: 12 | AF12: 1380 | AG12: -4480.38 | AH12: =IF(N(Y12)=0,"",X12/Y12) -> 1.1787816 | AI12: =IF(N(AC12)=0,"",X12/AC12) -> 0.89940359 | AJ12: =IF(N(X12)=0,"",Y12/X12) -> 0.84833354 | AK12: =IF(N(AA12)=0,"",X12/AA12) -> 0.92145138 | AL12: =IF(N(AB12)=0,"",AA12/AB12) -> 0.0099295277 | AM12: =IF(N(AA12)=0,"",Z12/AA12) -> 0.015965167 | AN12: =IF(N(AE12)=0,"",Z12/AE12) -> 0.91666667 | AO12: =IF(N(AD12)=0,"",AC12/AD12) -> 54.299231 | AP12: =IF(N(26)=0,"",X12/26) -> 24.418462 | AQ12: =IF(N(26)=0,"",AD12/26) -> 0.5 | AR12: =IF(N(AC12)=0,"",AG12/AC12) -> -6.3471362 | AS12: =IF(OR(U12="",AP12=""),"",IF(N(U12)=0,"",AP12/U12-1)) -> -0.17215264 | AT12: =IF(N(D12)=0,"",(Y12/26)/(D12/30)-1) -> -0.6127965 | AU12: =IF(OR(V12="",AQ12=""),"",IF(N(V12)=0,"",AQ12/V12-1)) -> -0.46428571 | AV12: =IF(OR(M12="",AH12=""),"",AH12-M12) -> 0.62743799 | AW12: =IF(OR(N12="",AI12=""),"",AI12-N12) -> 0.28110095 | AX12: =IF(OR(P12="",AK12=""),"",IF(N(P12)=0,"",AK12/P12-1)) -> 0.046524015 | AY12: =IF(OR(R12="",AM12=""),"",AM12-R12) -> -0.008910455 | AZ12: =IF(OR(T12="",AO12=""),"",IF(N(T12)=0,"",AO12/T12-1)) -> 0.062339963
A13: SPU07130 | B13: 电源逆变器-550W（牧田） | C13: 754.08 | D13: 1338.04 | E13: 16 | F13: 788 | G13: 67418 | H13: 4919.69 | I13: 51 | J13: 47 | K13: 2087 | L13: 564.85 | M13: =IF(N(D13)=0,"",C13/D13) -> 0.5635706 | N13: =IF(N(H13)=0,"",C13/H13) -> 0.15327795 | O13: =IF(N(C13)=0,"",D13/C13) -> 1.7744006 | P13: =IF(N(F13)=0,"",C13/F13) -> 0.95695431 | Q13: =IF(N(G13)=0,"",F13/G13) -> 0.011688273 | R13: =IF(N(F13)=0,"",E13/F13) -> 0.020304569 | S13: =IF(N(J13)=0,"",E13/J13) -> 0.34042553 | T13: =IF(N(I13)=0,"",H13/I13) -> 96.46451 | U13: =IF(N(30)=0,"",C13/30) -> 25.136 | V13: =IF(N(30)=0,"",I13/30) -> 1.7 | W13: =IF(N(H13)=0,"",L13/H13) -> 0.11481414 | X13: 543.62 | Y13: 387.7 | Z13: 4 | AA13: 540 | AB13: 43689 | AC13: 3150.09 | AD13: 31 | AE13: 31 | AF13: 1606 | AG13: -13.02 | AH13: =IF(N(Y13)=0,"",X13/Y13) -> 1.4021666 | AI13: =IF(N(AC13)=0,"",X13/AC13) -> 0.17257285 | AJ13: =IF(N(X13)=0,"",Y13/X13) -> 0.713182 | AK13: =IF(N(AA13)=0,"",X13/AA13) -> 1.0067037 | AL13: =IF(N(AB13)=0,"",AA13/AB13) -> 0.012360091 | AM13: =IF(N(AA13)=0,"",Z13/AA13) -> 0.0074074074 | AN13: =IF(N(AE13)=0,"",Z13/AE13) -> 0.12903226 | AO13: =IF(N(AD13)=0,"",AC13/AD13) -> 101.61581 | AP13: =IF(N(26)=0,"",X13/26) -> 20.908462 | AQ13: =IF(N(26)=0,"",AD13/26) -> 1.1923077 | AR13: =IF(N(AC13)=0,"",AG13/AC13) -> -0.0041332152 | AS13: =IF(OR(U13="",AP13=""),"",IF(N(U13)=0,"",AP13/U13-1)) -> -0.1681866 | AT13: =IF(N(D13)=0,"",(Y13/26)/(D13/30)-1) -> -0.66567057 | AU13: =IF(OR(V13="",AQ13=""),"",IF(N(V13)=0,"",AQ13/V13-1)) -> -0.29864253 | AV13: =IF(OR(M13="",AH13=""),"",AH13-M13) -> 0.83859603 | AW13: =IF(OR(N13="",AI13=""),"",AI13-N13) -> 0.019294897 | AX13: =IF(OR(P13="",AK13=""),"",IF(N(P13)=0,"",AK13/P13-1)) -> 0.051987214 | AY13: =IF(OR(R13="",AM13=""),"",AM13-R13) -> -0.012897161 | AZ13: =IF(OR(T13="",AO13=""),"",IF(N(T13)=0,"",AO13/T13-1)) -> 0.053400952
A14: SPU07055 | B14: 逆变器-双向65W（得伟） | C14: 641.88 | D14: 1218.98 | E14: 42 | F14: 1115 | G14: 166518 | H14: 1471.75 | I14: 61 | J14: 58 | K14: 2087 | L14: -348.81 | M14: =IF(N(D14)=0,"",C14/D14) -> 0.5265714 | N14: =IF(N(H14)=0,"",C14/H14) -> 0.43613385 | O14: =IF(N(C14)=0,"",D14/C14) -> 1.8990777 | P14: =IF(N(F14)=0,"",C14/F14) -> 0.57567713 | Q14: =IF(N(G14)=0,"",F14/G14) -> 0.0066959728 | R14: =IF(N(F14)=0,"",E14/F14) -> 0.037668161 | S14: =IF(N(J14)=0,"",E14/J14) -> 0.72413793 | T14: =IF(N(I14)=0,"",H14/I14) -> 24.127049 | U14: =IF(N(30)=0,"",C14/30) -> 21.396 | V14: =IF(N(30)=0,"",I14/30) -> 2.0333333 | W14: =IF(N(H14)=0,"",L14/H14) -> -0.23700357 | X14: 595.97 | Y14: 1073.72 | Z14: 37 | AA14: 954 | AB14: 119856 | AC14: 1316.56 | AD14: 58 | AE14: 53 | AF14: 1642 | AG14: -305.44 | AH14: =IF(N(Y14)=0,"",X14/Y14) -> 0.5550516 | AI14: =IF(N(AC14)=0,"",X14/AC14) -> 0.45267212 | AJ14: =IF(N(X14)=0,"",Y14/X14) -> 1.8016343 | AK14: =IF(N(AA14)=0,"",X14/AA14) -> 0.6247065 | AL14: =IF(N(AB14)=0,"",AA14/AB14) -> 0.0079595515 | AM14: =IF(N(AA14)=0,"",Z14/AA14) -> 0.038784067 | AN14: =IF(N(AE14)=0,"",Z14/AE14) -> 0.69811321 | AO14: =IF(N(AD14)=0,"",AC14/AD14) -> 22.69931 | AP14: =IF(N(26)=0,"",X14/26) -> 22.921923 | AQ14: =IF(N(26)=0,"",AD14/26) -> 2.2307692 | AR14: =IF(N(AC14)=0,"",AG14/AC14) -> -0.23199854 | AS14: =IF(OR(U14="",AP14=""),"",IF(N(U14)=0,"",AP14/U14-1)) -> 0.071318147 | AT14: =IF(N(D14)=0,"",(Y14/26)/(D14/30)-1) -> 0.016347842 | AU14: =IF(OR(V14="",AQ14=""),"",IF(N(V14)=0,"",AQ14/V14-1)) -> 0.097099622 | AV14: =IF(OR(M14="",AH14=""),"",AH14-M14) -> 0.028480201 | AW14: =IF(OR(N14="",AI14=""),"",AI14-N14) -> 0.016538261 | AX14: =IF(OR(P14="",AK14=""),"",IF(N(P14)=0,"",AK14/P14-1)) -> 0.085168172 | AY14: =IF(OR(R14="",AM14=""),"",AM14-R14) -> 0.0011159057 | AZ14: =IF(OR(T14="",AO14=""),"",IF(N(T14)=0,"",AO14/T14-1)) -> -0.059175858
A15: SPU07115 | B15: 电源逆变器350W-AC美标110V PD20W（得伟） | C15: 769.84 | D15: 1455.43 | E15: 24 | F15: 1591 | G15: 97977 | H15: 2056.15 | I15: 40 | J15: 40 | K15: 3348 | L15: -2463.18 | M15: =IF(N(D15)=0,"",C15/D15) -> 0.52894334 | N15: =IF(N(H15)=0,"",C15/H15) -> 0.37440848 | O15: =IF(N(C15)=0,"",D15/C15) -> 1.8905617 | P15: =IF(N(F15)=0,"",C15/F15) -> 0.48387178 | Q15: =IF(N(G15)=0,"",F15/G15) -> 0.016238505 | R15: =IF(N(F15)=0,"",E15/F15) -> 0.015084852 | S15: =IF(N(J15)=0,"",E15/J15) -> 0.6 | T15: =IF(N(I15)=0,"",H15/I15) -> 51.40375 | U15: =IF(N(30)=0,"",C15/30) -> 25.661333 | V15: =IF(N(30)=0,"",I15/30) -> 1.3333333 | W15: =IF(N(H15)=0,"",L15/H15) -> -1.1979573 | X15: 417.26 | Y15: 992.06 | Z15: 20 | AA15: 683 | AB15: 52419 | AC15: 2715.7 | AD15: 57 | AE15: 57 | AF15: 2160 | AG15: -463.88 | AH15: =IF(N(Y15)=0,"",X15/Y15) -> 0.42059956 | AI15: =IF(N(AC15)=0,"",X15/AC15) -> 0.15364731 | AJ15: =IF(N(X15)=0,"",Y15/X15) -> 2.3775584 | AK15: =IF(N(AA15)=0,"",X15/AA15) -> 0.6109224 | AL15: =IF(N(AB15)=0,"",AA15/AB15) -> 0.013029627 | AM15: =IF(N(AA15)=0,"",Z15/AA15) -> 0.029282577 | AN15: =IF(N(AE15)=0,"",Z15/AE15) -> 0.35087719 | AO15: =IF(N(AD15)=0,"",AC15/AD15) -> 47.64386 | AP15: =IF(N(26)=0,"",X15/26) -> 16.048462 | AQ15: =IF(N(26)=0,"",AD15/26) -> 2.1923077 | AR15: =IF(N(AC15)=0,"",AG15/AC15) -> -0.17081415 | AS15: =IF(OR(U15="",AP15=""),"",IF(N(U15)=0,"",AP15/U15-1)) -> -0.37460531 | AT15: =IF(N(D15)=0,"",(Y15/26)/(D15/30)-1) -> -0.21350761 | AU15: =IF(OR(V15="",AQ15=""),"",IF(N(V15)=0,"",AQ15/V15-1)) -> 0.64423077 | AV15: =IF(OR(M15="",AH15=""),"",AH15-M15) -> -0.10834378 | AW15: =IF(OR(N15="",AI15=""),"",AI15-N15) -> -0.22076117 | AX15: =IF(OR(P15="",AK15=""),"",IF(N(P15)=0,"",AK15/P15-1)) -> 0.26257085 | AY15: =IF(OR(R15="",AM15=""),"",AM15-R15) -> 0.014197725 | AZ15: =IF(OR(T15="",AO15=""),"",IF(N(T15)=0,"",AO15/T15-1)) -> -0.073144281
A16: SPU07104 | B16: 车载逆变器-300W（米沃奇） | C16: 440.67 | D16: 1074.28 | E16: 28 | F16: 880 | G16: 124457 | H16: 2381.9 | I16: 89 | J16: 83 | K16: 1850 | L16: -539.49 | M16: =IF(N(D16)=0,"",C16/D16) -> 0.41020032 | N16: =IF(N(H16)=0,"",C16/H16) -> 0.18500777 | O16: =IF(N(C16)=0,"",D16/C16) -> 2.4378333 | P16: =IF(N(F16)=0,"",C16/F16) -> 0.50076136 | Q16: =IF(N(G16)=0,"",F16/G16) -> 0.0070707152 | R16: =IF(N(F16)=0,"",E16/F16) -> 0.031818182 | S16: =IF(N(J16)=0,"",E16/J16) -> 0.3373494 | T16: =IF(N(I16)=0,"",H16/I16) -> 26.762921 | U16: =IF(N(30)=0,"",C16/30) -> 14.689 | V16: =IF(N(30)=0,"",I16/30) -> 2.9666667 | W16: =IF(N(H16)=0,"",L16/H16) -> -0.22649565 | X16: 272.6 | Y16: 854.67 | Z16: 21 | AA16: 472 | AB16: 65425 | AC16: 1917.4 | AD16: 81 | AE16: 75 | AF16: 1322 | AG16: -286.45 | AH16: =IF(N(Y16)=0,"",X16/Y16) -> 0.31895351 | AI16: =IF(N(AC16)=0,"",X16/AC16) -> 0.14217169 | AJ16: =IF(N(X16)=0,"",Y16/X16) -> 3.1352531 | AK16: =IF(N(AA16)=0,"",X16/AA16) -> 0.57754237 | AL16: =IF(N(AB16)=0,"",AA16/AB16) -> 0.0072143676 | AM16: =IF(N(AA16)=0,"",Z16/AA16) -> 0.044491525 | AN16: =IF(N(AE16)=0,"",Z16/AE16) -> 0.28 | AO16: =IF(N(AD16)=0,"",AC16/AD16) -> 23.671605 | AP16: =IF(N(26)=0,"",X16/26) -> 10.484615 | AQ16: =IF(N(26)=0,"",AD16/26) -> 3.1153846 | AR16: =IF(N(AC16)=0,"",AG16/AC16) -> -0.14939501 | AS16: =IF(OR(U16="",AP16=""),"",IF(N(U16)=0,"",AP16/U16-1)) -> -0.28622674 | AT16: =IF(N(D16)=0,"",(Y16/26)/(D16/30)-1) -> -0.08202918 | AU16: =IF(OR(V16="",AQ16=""),"",IF(N(V16)=0,"",AQ16/V16-1)) -> 0.050129646 | AV16: =IF(OR(M16="",AH16=""),"",AH16-M16) -> -0.091246806 | AW16: =IF(OR(N16="",AI16=""),"",AI16-N16) -> -0.042836076 | AX16: =IF(OR(P16="",AK16=""),"",IF(N(P16)=0,"",AK16/P16-1)) -> 0.15332854 | AY16: =IF(OR(R16="",AM16=""),"",AM16-R16) -> 0.012673344 | AZ16: =IF(OR(T16="",AO16=""),"",IF(N(T16)=0,"",AO16/T16-1)) -> -0.11550744
... A20: SPU070117 | B20: 车载逆变器-300W（牧田） | C20: 0 | D20: 0 | E20: 0 | F20: 0 | G20: 0 | H20: 0 | I20: 0 | J20: 0 | K20: 78 | L20: 11.93 | M20: =IF(N(D20)=0,"",C20/D20) | N20: =IF(N(H20)=0,"",C20/H20) | O20: =IF(N(C20)=0,"",D20/C20) | P20: =IF(N(F20)=0,"",C20/F20) | Q20: =IF(N(G20)=0,"",F20/G20) | R20: =IF(N(F20)=0,"",E20/F20) | S20: =IF(N(J20)=0,"",E20/J20) | T20: =IF(N(I20)=0,"",H20/I20) | U20: =IF(N(30)=0,"",C20/30) -> 0 | V20: =IF(N(30)=0,"",I20/30) -> 0 | W20: =IF(N(H20)=0,"",L20/H20) | X20: 0 | Y20: 0 | Z20: 0 | AA20: 0 | AB20: 0 | AC20: 0 | AD20: 0 | AE20: 0 | AF20: 0 | AG20: -12.04 | AH20: =IF(N(Y20)=0,"",X20/Y20) | AI20: =IF(N(AC20)=0,"",X20/AC20) | AJ20: =IF(N(X20)=0,"",Y20/X20) | AK20: =IF(N(AA20)=0,"",X20/AA20) | AL20: =IF(N(AB20)=0,"",AA20/AB20) | AM20: =IF(N(AA20)=0,"",Z20/AA20) | AN20: =IF(N(AE20)=0,"",Z20/AE20) | AO20: =IF(N(AD20)=0,"",AC20/AD20) | AP20: =IF(N(26)=0,"",X20/26) -> 0 | AQ20: =IF(N(26)=0,"",AD20/26) -> 0 | AR20: =IF(N(AC20)=0,"",AG20/AC20) | AS20: =IF(OR(U20="",AP20=""),"",IF(N(U20)=0,"",AP20/U20-1)) | AT20: =IF(N(D20)=0,"",(Y20/26)/(D20/30)-1) | AU20: =IF(OR(V20="",AQ20=""),"",IF(N(V20)=0,"",AQ20/V20-1)) | AV20: =IF(OR(M20="",AH20=""),"",AH20-M20) | AW20: =IF(OR(N20="",AI20=""),"",AI20-N20) | AX20: =IF(OR(P20="",AK20=""),"",IF(N(P20)=0,"",AK20/P20-1)) | AY20: =IF(OR(R20="",AM20=""),"",AM20-R20) | AZ20: =IF(OR(T20="",AO20=""),"",IF(N(T20)=0,"",AO20/T20-1))
A21: 品类合计/均值 | C21: =SUM(C5:C20) -> 34165.36 | D21: =SUM(D5:D20) -> 80180.77 | E21: =SUM(E5:E20) -> 2153 | F21: =SUM(F5:F20) -> 45337 | G21: =SUM(G5:G20) -> 6129290 | H21: =SUM(H5:H20) -> 213471.15 | I21: =SUM(I5:I20) -> 6064 | J21: =SUM(J5:J20) -> 5584 | ... L21: =SUM(L5:L20) -> -25524.08 | M21: =IF(N(D21)=0,"",C21/D21) -> 0.42610416 | N21: =IF(N(H21)=0,"",C21/H21) -> 0.16004673 | O21: =IF(N(C21)=0,"",D21/C21) -> 2.346844 | P21: =IF(N(F21)=0,"",C21/F21) -> 0.7535867 | Q21: =IF(N(G21)=0,"",F21/G21) -> 0.0073967784 | R21: =IF(N(F21)=0,"",E21/F21) -> 0.047488806 | S21: =IF(N(J21)=0,"",E21/J21) -> 0.3855659 | T21: =IF(N(I21)=0,"",H21/I21) -> 35.203026 | U21: =IF(N(30)=0,"",C21/30) -> 1138.8453 | V21: =IF(N(30)=0,"",I21/30) -> 202.13333 | W21: =IF(N(H21)=0,"",L21/H21) -> -0.11956688 | X21: =SUM(X5:X20) -> 32021.91 | Y21: =SUM(Y5:Y20) -> 83159.75 | Z21: =SUM(Z5:Z20) -> 2458 | AA21: =SUM(AA5:AA20) -> 42707 | AB21: =SUM(AB5:AB20) -> 5591316 | AC21: =SUM(AC5:AC20) -> 251392.03 | AD21: =SUM(AD5:AD20) -> 7595 | AE21: =SUM(AE5:AE20) -> 6875 | ... AG21: =SUM(AG5:AG20) -> 4077.36 | AH21: =IF(N(Y21)=0,"",X21/Y21) -> 0.38506501 | AI21: =IF(N(AC21)=0,"",X21/AC21) -> 0.12737838 | AJ21: =IF(N(X21)=0,"",Y21/X21) -> 2.5969641 | AK21: =IF(N(AA21)=0,"",X21/AA21) -> 0.74980472 | AL21: =IF(N(AB21)=0,"",AA21/AB21) -> 0.0076380945 | AM21: =IF(N(AA21)=0,"",Z21/AA21) -> 0.057554968 | AN21: =IF(N(AE21)=0,"",Z21/AE21) -> 0.35752727 | AO21: =IF(N(AD21)=0,"",AC21/AD21) -> 33.099675 | AP21: =IF(N(26)=0,"",X21/26) -> 1231.6119 | AQ21: =IF(N(26)=0,"",AD21/26) -> 292.11538 | AR21: =IF(N(AC21)=0,"",AG21/AC21) -> 0.01621913 | AS21: =IF(OR(U21="",AP21=""),"",IF(N(U21)=0,"",AP21/U21-1)) -> 0.081456706 | AT21: =IF(N(D21)=0,"",(Y21/26)/(D21/30)-1) -> 0.19671534 | AU21: =IF(OR(V21="",AQ21=""),"",IF(N(V21)=0,"",AQ21/V21-1)) -> 0.44516186 | AV21: =IF(OR(M21="",AH21=""),"",AH21-M21) -> -0.041039154 | AW21: =IF(OR(N21="",AI21=""),"",AI21-N21) -> -0.03266835 | AX21: =IF(OR(P21="",AK21=""),"",IF(N(P21)=0,"",AK21/P21-1)) -> -0.0050186387 | AY21: =IF(OR(R21="",AM21=""),"",AM21-R21) -> 0.010066162 | AZ21: =IF(OR(T21="",AO21=""),"",IF(N(T21)=0,"",AO21/T21-1)) -> -0.059749161
A23: 高亮规则：红=ACOS/TACOS 超阈值、毛利为负、日均花费暴涨、ACOS 恶化；黄=CPC 偏高、广告CVR 偏低、价格变动超阈值、日均销量下滑≥20%；绿=ACOS 改善。阈值见「总览」。结算毛利润受回款结算时点影响，单月波动大，仅作参考。

Sheet ASIN月度汇总
A1: ASIN 维度 · 9月 vs 10月 广告与销售汇总（按两月广告花费降序）
A3: ASIN | B3: SPU | C3: 型号 | D3: 主要店铺 | E3: 2026年9月（30天） | Z3: 2026年10月（26天） | AU3: 10月 vs 9月
E4: 广告花费 | F4: 广告销售额 | G4: 广告订单量 | H4: 点击 | I4: 展示 | J4: 销售额 | K4: 销量 | L4: 订单量 | M4: Sessions-Total | N4: 结算毛利润 | O4: ACOS | P4: TACOS | Q4: ROAS | R4: CPC | S4: CTR | T4: 广告CVR | U4: 广告单占比 | V4: 成交均价 | W4: 日均花费 | X4: 日均销量 | Y4: 毛利率 | Z4: 广告花费 | AA4: 广告销售额 | AB4: 广告订单量 | AC4: 点击 | AD4: 展示 | AE4: 销售额 | AF4: 销量 | AG4: 订单量 | AH4: Sessions-Total | AI4: 结算毛利润 | AJ4: ACOS | AK4: TACOS | AL4: ROAS | AM4: CPC | AN4: CTR | AO4: 广告CVR | AP4: 广告单占比 | AQ4: 成交均价 | AR4: 日均花费 | AS4: 日均销量 | AT4: 毛利率 | AU4: 日均花费环比 | AV4: 广告销售额日均环比 | AW4: 日均销量环比 | AX4: ACOS变化(pp) | AY4: TACOS变化(pp) | AZ4: CPC环比 | BA4: 广告CVR变化(pp) | BB4: 成交均价环比
A5: B0CQ4Q6WB9 | B5: SPU07021 | C5: 得伟-电源逆变器-200W | D5: AMZ5-US/HK5-US/HK5-MX/HK5-CA | E5: 3423.07 | F5: 7766.49 | G5: 283 | H5: 3529 | I5: 597060 | J5: 27952.33 | K5: 1230 | L5: 1101 | M5: 39828 | N5: -2342.3 | O5: =IF(N(F5)=0,"",E5/F5) -> 0.44074865 | P5: =IF(N(J5)=0,"",E5/J5) -> 0.12246099 | Q5: =IF(N(E5)=0,"",F5/E5) -> 2.2688668 | R5: =IF(N(H5)=0,"",E5/H5) -> 0.969983 | S5: =IF(N(I5)=0,"",H5/I5) -> 0.0059106287 | T5: =IF(N(H5)=0,"",G5/H5) -> 0.080192689 | U5: =IF(N(L5)=0,"",G5/L5) -> 0.25703906 | V5: =IF(N(K5)=0,"",J5/K5) -> 22.725472 | W5: =IF(N(30)=0,"",E5/30) -> 114.10233 | X5: =IF(N(30)=0,"",K5/30) -> 41 | Y5: =IF(N(J5)=0,"",N5/J5) -> -0.083796235 | Z5: 4170.25 | AA5: 15523.62 | AB5: 554 | AC5: 6136 | AD5: 736643 | AE5: 40461.89 | AF5: 1865 | AG5: 1589 | AH5: 46587 | AI5: -373.97 | AJ5: =IF(N(AA5)=0,"",Z5/AA5) -> 0.26863902 | AK5: =IF(N(AE5)=0,"",Z5/AE5) -> 0.10306612 | AL5: =IF(N(Z5)=0,"",AA5/Z5) -> 3.7224675 | AM5: =IF(N(AC5)=0,"",Z5/AC5) -> 0.67963657 | AN5: =IF(N(AD5)=0,"",AC5/AD5) -> 0.0083296794 | AO5: =IF(N(AC5)=0,"",AB5/AC5) -> 0.090286832 | AP5: =IF(N(AG5)=0,"",AB5/AG5) -> 0.34864695 | AQ5: =IF(N(AF5)=0,"",AE5/AF5) -> 21.695383 | AR5: =IF(N(26)=0,"",Z5/26) -> 160.39423 | AS5: =IF(N(26)=0,"",AF5/26) -> 71.730769 | AT5: =IF(N(AE5)=0,"",AI5/AE5) -> -0.0092425243 | AU5: =IF(OR(W5="",AR5=""),"",IF(N(W5)=0,"",AR5/W5-1)) -> 0.40570509 | AV5: =IF(N(F5)=0,"",(AA5/26)/(F5/30)-1) -> 1.3063017 | AW5: =IF(OR(X5="",AS5=""),"",IF(N(X5)=0,"",AS5/X5-1)) -> 0.74953096 | AX5: =IF(OR(O5="",AJ5=""),"",AJ5-O5) -> -0.17210964 | AY5: =IF(OR(P5="",AK5=""),"",AK5-P5) -> -0.01939487 | AZ5: =IF(OR(R5="",AM5=""),"",IF(N(R5)=0,"",AM5/R5-1)) -> -0.29933146 | BA5: =IF(OR(T5="",AO5=""),"",AO5-T5) -> 0.010094143 | BB5: =IF(OR(V5="",AQ5=""),"",IF(N(V5)=0,"",AQ5/V5-1)) -> -0.045327472
A6: B0CQ2JJ51T | B6: SPU07022 | C6: 米沃奇-电源逆变器-200W | D6: AMZ8-CA/HK8-US/AMZ8-US/HK8-MX | E6: 2645.07 | F6: 5480.6 | G6: 176 | H6: 3876 | I6: 581971 | J6: 10895.86 | K6: 380 | L6: 368 | M6: 13375 | N6: -692.36 | O6: =IF(N(F6)=0,"",E6/F6) -> 0.48262417 | P6: =IF(N(J6)=0,"",E6/J6) -> 0.24275918 | Q6: =IF(N(E6)=0,"",F6/E6) -> 2.0720057 | R6: =IF(N(H6)=0,"",E6/H6) -> 0.6824226 | S6: =IF(N(I6)=0,"",H6/I6) -> 0.0066601257 | T6: =IF(N(H6)=0,"",G6/H6) -> 0.045407637 | U6: =IF(N(L6)=0,"",G6/L6) -> 0.47826087 | V6: =IF(N(K6)=0,"",J6/K6) -> 28.673316 | W6: =IF(N(30)=0,"",E6/30) -> 88.169 | X6: =IF(N(30)=0,"",K6/30) -> 12.666667 | Y6: =IF(N(J6)=0,"",N6/J6) -> -0.063543401 | Z6: 3852.8 | AA6: 7091.49 | AB6: 231 | AC6: 4937 | AD6: 681001 | AE6: 14001.04 | AF6: 500 | AG6: 472 | AH6: 18880 | AI6: -1910.08 | AJ6: =IF(N(AA6)=0,"",Z6/AA6) -> 0.54329908 | AK6: =IF(N(AE6)=0,"",Z6/AE6) -> 0.27517956 | AL6: =IF(N(Z6)=0,"",AA6/Z6) -> 1.8406068 | AM6: =IF(N(AC6)=0,"",Z6/AC6) -> 0.78039295 | AN6: =IF(N(AD6)=0,"",AC6/AD6) -> 0.0072496222 | AO6: =IF(N(AC6)=0,"",AB6/AC6) -> 0.046789548 | AP6: =IF(N(AG6)=0,"",AB6/AG6) -> 0.48940678 | AQ6: =IF(N(AF6)=0,"",AE6/AF6) -> 28.00208 | AR6: =IF(N(26)=0,"",Z6/26) -> 148.18462 | AS6: =IF(N(26)=0,"",AF6/26) -> 19.230769 | AT6: =IF(N(AE6)=0,"",AI6/AE6) -> -0.13642415 | AU6: =IF(OR(W6="",AR6=""),"",IF(N(W6)=0,"",AR6/W6-1)) -> 0.6806884 | AV6: =IF(N(F6)=0,"",(AA6/26)/(F6/30)-1) -> 0.49299136 | AW6: =IF(OR(X6="",AS6=""),"",IF(N(X6)=0,"",AS6/X6-1)) -> 0.51821862 | AX6: =IF(OR(O6="",AJ6=""),"",AJ6-O6) -> 0.060674916 | AY6: =IF(OR(P6="",AK6=""),"",AK6-P6) -> 0.032420382 | AZ6: =IF(OR(R6="",AM6=""),"",IF(N(R6)=0,"",AM6/R6-1)) -> 0.14356258 | BA6: =IF(OR(T6="",AO6=""),"",AO6-T6) -> 0.0013819116 | BB6: =IF(OR(V6="",AQ6=""),"",IF(N(V6)=0,"",AQ6/V6-1)) -> -0.023409772
A7: B0CQ4PFGH5 | B7: SPU07022 | C7: 米沃奇-电源逆变器-200W | D7: AMZ5-US/HK5-US | E7: 2584.13 | F7: 5555.8 | G7: 222 | H7: 2453 | I7: 561693 | J7: 13831.65 | K7: 618 | L7: 560 | M7: 16296 | N7: 71.18 | O7: =IF(N(F7)=0,"",E7/F7) -> 0.46512293 | P7: =IF(N(J7)=0,"",E7/J7) -> 0.18682731 | Q7: =IF(N(E7)=0,"",F7/E7) -> 2.1499692 | R7: =IF(N(H7)=0,"",E7/H7) -> 1.053457 | S7: =IF(N(I7)=0,"",H7/I7) -> 0.0043671543 | T7: =IF(N(H7)=0,"",G7/H7) -> 0.090501427 | U7: =IF(N(L7)=0,"",G7/L7) -> 0.39642857 | V7: =IF(N(K7)=0,"",J7/K7) -> 22.381311 | W7: =IF(N(30)=0,"",E7/30) -> 86.137667 | X7: =IF(N(30)=0,"",K7/30) -> 20.6 | Y7: =IF(N(J7)=0,"",N7/J7) -> 0.0051461684 | Z7: 3709 | AA7: 8919.81 | AB7: 353 | AC7: 5343 | AD7: 1096274 | AE7: 18597.48 | AF7: 856 | AG7: 760 | AH7: 20832 | AI7: -1758.54 | AJ7: =IF(N(AA7)=0,"",Z7/AA7) -> 0.41581603 | AK7: =IF(N(AE7)=0,"",Z7/AE7) -> 0.19943562 | AL7: =IF(N(Z7)=0,"",AA7/Z7) -> 2.4049097 | AM7: =IF(N(AC7)=0,"",Z7/AC7) -> 0.6941793 | AN7: =IF(N(AD7)=0,"",AC7/AD7) -> 0.0048737816 | AO7: =IF(N(AC7)=0,"",AB7/AC7) -> 0.066067752 | AP7: =IF(N(AG7)=0,"",AB7/AG7) -> 0.46447368 | AQ7: =IF(N(AF7)=0,"",AE7/AF7) -> 21.726028 | AR7: =IF(N(26)=0,"",Z7/26) -> 142.65385 | AS7: =IF(N(26)=0,"",AF7/26) -> 32.923077 | AT7: =IF(N(AE7)=0,"",AI7/AE7) -> -0.094557972 | AU7: =IF(OR(W7="",AR7=""),"",IF(N(W7)=0,"",AR7/W7-1)) -> 0.65611459 | AV7: =IF(N(F7)=0,"",(AA7/26)/(F7/30)-1) -> 0.85249441 | AW7: =IF(OR(X7="",AS7=""),"",IF(N(X7)=0,"",AS7/X7-1)) -> 0.59820762 | AX7: =IF(OR(O7="",AJ7=""),"",AJ7-O7) -> -0.049306903 | AY7: =IF(OR(P7="",AK7=""),"",AK7-P7) -> 0.01260831 | AZ7: =IF(OR(R7="",AM7=""),"",IF(N(R7)=0,"",AM7/R7-1)) -> -0.34104638 | BA7: =IF(OR(T7="",AO7=""),"",AO7-T7) -> -0.024433675 | BB7: =IF(OR(V7="",AQ7=""),"",IF(N(V7)=0,"",AQ7/V7-1)) -> -0.029278117
A8: B0CQ2MHKJ5 | B8: SPU07021 | C8: 得伟-电源逆变器-200W | D8: HK8-US/AMZ8-US/AMZ8-CA/HK8-CA | E8: 1808.4 | F8: 3416.67 | G8: 103 | H8: 1107 | I8: 285328 | J8: 10213.97 | K8: 356 | L8: 319 | M8: 9847 | N8: 455.48 | O8: =IF(N(F8)=0,"",E8/F8) -> 0.52928729 | P8: =IF(N(J8)=0,"",E8/J8) -> 0.17705163 | Q8: =IF(N(E8)=0,"",F8/E8) -> 1.8893331 | R8: =IF(N(H8)=0,"",E8/H8) -> 1.6336043 | S8: =IF(N(I8)=0,"",H8/I8) -> 0.0038797454 | T8: =IF(N(H8)=0,"",G8/H8) -> 0.093044264 | U8: =IF(N(L8)=0,"",G8/L8) -> 0.32288401 | V8: =IF(N(K8)=0,"",J8/K8) -> 28.690927 | W8: =IF(N(30)=0,"",E8/30) -> 60.28 | X8: =IF(N(30)=0,"",K8/30) -> 11.866667 | Y8: =IF(N(J8)=0,"",N8/J8) -> 0.044593826 | Z8: 4484.7 | AA8: 14286.01 | AB8: 418 | AC8: 4163 | AD8: 512713 | AE8: 25577.47 | AF8: 891 | AG8: 843 | AH8: 23302 | AI8: -1217.16 | AJ8: =IF(N(AA8)=0,"",Z8/AA8) -> 0.3139225 | AK8: =IF(N(AE8)=0,"",Z8/AE8) -> 0.1753379 | AL8: =IF(N(Z8)=0,"",AA8/Z8) -> 3.1854996 | AM8: =IF(N(AC8)=0,"",Z8/AC8) -> 1.077276 | AN8: =IF(N(AD8)=0,"",AC8/AD8) -> 0.0081195523 | AO8: =IF(N(AC8)=0,"",AB8/AC8) -> 0.10040836 | AP8: =IF(N(AG8)=0,"",AB8/AG8) -> 0.49584816 | AQ8: =IF(N(AF8)=0,"",AE8/AF8) -> 28.706476 | AR8: =IF(N(26)=0,"",Z8/26) -> 172.48846 | AS8: =IF(N(26)=0,"",AF8/26) -> 34.269231 | AT8: =IF(N(AE8)=0,"",AI8/AE8) -> -0.047587193 | AU8: =IF(OR(W8="",AR8=""),"",IF(N(W8)=0,"",AR8/W8-1)) -> 1.8614542 | AV8: =IF(N(F8)=0,"",(AA8/26)/(F8/30)-1) -> 3.824539 | AW8: =IF(OR(X8="",AS8=""),"",IF(N(X8)=0,"",AS8/X8-1)) -> 1.8878565 | AX8: =IF(OR(O8="",AJ8=""),"",AJ8-O8) -> -0.21536479 | AY8: =IF(OR(P8="",AK8=""),"",AK8-P8) -> -0.0017137215 | AZ8: =IF(OR(R8="",AM8=""),"",IF(N(R8)=0,"",AM8/R8-1)) -> -0.34055268 | BA8: =IF(OR(T8="",AO8=""),"",AO8-T8) -> 0.0073640956 | BB8: =IF(OR(V8="",AQ8=""),"",IF(N(V8)=0,"",AQ8/V8-1)) -> 0.00054194497
A9: B0DQKKF484 | B9: SPU07060 | C9: 利优比-电源逆变器-200W | D9: AMZ5-US/HK5-US | E9: 2474.49 | F9: 6782.43 | G9: 186 | H9: 5519 | I9: 739233 | J9: 8881.15 | K9: 256 | L9: 246 | M9: 11827 | N9: -6698.67 | O9: =IF(N(F9)=0,"",E9/F9) -> 0.36483827 | P9: =IF(N(J9)=0,"",E9/J9) -> 0.2786227 | Q9: =IF(N(E9)=0,"",F9/E9) -> 2.7409406 | R9: =IF(N(H9)=0,"",E9/H9) -> 0.4483584 | S9: =IF(N(I9)=0,"",H9/I9) -> 0.0074658464 | T9: =IF(N(H9)=0,"",G9/H9) -> 0.033701758 | U9: =IF(N(L9)=0,"",G9/L9) -> 0.75609756 | V9: =IF(N(K9)=0,"",J9/K9) -> 34.691992 | W9: =IF(N(30)=0,"",E9/30) -> 82.483 | X9: =IF(N(30)=0,"",K9/30) -> 8.5333333 | Y9: =IF(N(J9)=0,"",N9/J9) -> -0.75425705 | Z9: 1577.74 | AA9: 3183.98 | AB9: 79 | AC9: 3414 | AD9: 261524 | AE9: 5633.42 | AF9: 168 | AG9: 165 | AH9: 12544 | AI9: 498.91 | AJ9: =IF(N(AA9)=0,"",Z9/AA9) -> 0.49552447 | AK9: =IF(N(AE9)=0,"",Z9/AE9) -> 0.28006788 | AL9: =IF(N(Z9)=0,"",AA9/Z9) -> 2.0180638 | AM9: =IF(N(AC9)=0,"",Z9/AC9) -> 0.46213825 | AN9: =IF(N(AD9)=0,"",AC9/AD9) -> 0.013054251 | AO9: =IF(N(AC9)=0,"",AB9/AC9) -> 0.023140012 | AP9: =IF(N(AG9)=0,"",AB9/AG9) -> 0.47878788 | AQ9: =IF(N(AF9)=0,"",AE9/AF9) -> 33.532262 | AR9: =IF(N(26)=0,"",Z9/26) -> 60.682308 | AS9: =IF(N(26)=0,"",AF9/26) -> 6.4615385 | AT9: =IF(N(AE9)=0,"",AI9/AE9) -> 0.088562543 | AU9: =IF(OR(W9="",AR9=""),"",IF(N(W9)=0,"",AR9/W9-1)) -> -0.26430528 | AV9: =IF(N(F9)=0,"",(AA9/26)/(F9/30)-1) -> -0.45833233 | AW9: =IF(OR(X9="",AS9=""),"",IF(N(X9)=0,"",AS9/X9-1)) -> -0.24278846 | AX9: =IF(OR(O9="",AJ9=""),"",AJ9-O9) -> 0.1306862 | AY9: =IF(OR(P9="",AK9=""),"",AK9-P9) -> 0.0014451797 | AZ9: =IF(OR(R9="",AM9=""),"",IF(N(R9)=0,"",AM9/R9-1)) -> 0.03073402 | BA9: =IF(OR(T9="",AO9=""),"",AO9-T9) -> -0.010561746 | BB9: =IF(OR(V9="",AQ9=""),"",IF(N(V9)=0,"",AQ9/V9-1)) -> -0.033429337
A10: B0GXJ3VN4S | B10: SPU50039 | C10: 得伟-单包逆变器350W-修正波版-美规-黄色 | D10: AMZ5-US/HK5-US | E10: 2514.02 | F10: 6333.13 | G10: 150 | H10: 2486 | I10: 296639 | J10: 12555.05 | K10: 311 | L10: 293 | M10: 8253 | N10: -689.7 | O10: =IF(N(F10)=0,"",E10/F10) -> 0.39696327 | P10: =IF(N(J10)=0,"",E10/J10) -> 0.20023974 | Q10: =IF(N(E10)=0,"",F10/E10) -> 2.5191247 | R10: =IF(N(H10)=0,"",E10/H10) -> 1.0112711 | S10: =IF(N(I10)=0,"",H10/I10) -> 0.0083805568 | T10: =IF(N(H10)=0,"",G10/H10) -> 0.060337892 | U10: =IF(N(L10)=0,"",G10/L10) -> 0.51194539 | V10: =IF(N(K10)=0,"",J10/K10) -> 40.369936 | W10: =IF(N(30)=0,"",E10/30) -> 83.800667 | X10: =IF(N(30)=0,"",K10/30) -> 10.366667 | Y10: =IF(N(J10)=0,"",N10/J10) -> -0.05493407 | Z10: 1411.24 | AA10: 3744.5 | AB10: 89 | AC10: 1518 | AD10: 175574 | AE10: 6394.24 | AF10: 157 | AG10: 143 | AH10: 6662 | AI10: -277.48 | AJ10: =IF(N(AA10)=0,"",Z10/AA10) -> 0.37688343 | AK10: =IF(N(AE10)=0,"",Z10/AE10) -> 0.22070488 | AL10: =IF(N(Z10)=0,"",AA10/Z10) -> 2.6533403 | AM10: =IF(N(AC10)=0,"",Z10/AC10) -> 0.92967062 | AN10: =IF(N(AD10)=0,"",AC10/AD10) -> 0.0086459271 | AO10: =IF(N(AC10)=0,"",AB10/AC10) -> 0.058629776 | AP10: =IF(N(AG10)=0,"",AB10/AG10) -> 0.62237762 | AQ10: =IF(N(AF10)=0,"",AE10/AF10) -> 40.727643 | AR10: =IF(N(26)=0,"",Z10/26) -> 54.278462 | AS10: =IF(N(26)=0,"",AF10/26) -> 6.0384615 | AT10: =IF(N(AE10)=0,"",AI10/AE10) -> -0.043395306 | AU10: =IF(OR(W10="",AR10=""),"",IF(N(W10)=0,"",AR10/W10-1)) -> -0.35229081 | AV10: =IF(N(F10)=0,"",(AA10/26)/(F10/30)-1) -> -0.31778174 | AW10: =IF(OR(X10="",AS10=""),"",IF(N(X10)=0,"",AS10/X10-1)) -> -0.41751175 | AX10: =IF(OR(O10="",AJ10=""),"",AJ10-O10) -> -0.020079842 | AY10: =IF(OR(P10="",AK10=""),"",AK10-P10) -> 0.02046514 | AZ10: =IF(OR(R10="",AM10=""),"",IF(N(R10)=0,"",AM10/R10-1)) -> -0.080691021 | BA10: =IF(OR(T10="",AO10=""),"",AO10-T10) -> -0.0017081162 | BB10: =IF(OR(V10="",AQ10=""),"",IF(N(V10)=0,"",AQ10/V10-1)) -> 0.0088607429
A11: B0GXHN35JL | B11: SPU50039 | C11: 米沃奇-单包逆变器350W-修正波版-美规-红色 | D11: AMZ5-US | E11: 1799.96 | F11: 2674.04 | G11: 62 | H11: 1558 | I11: 170396 | J11: 5469.11 | K11: 139 | L11: 132 | M11: 4141 | N11: -1332.29 | O11: =IF(N(F11)=0,"",E11/F11) -> 0.67312381 | P11: =IF(N(J11)=0,"",E11/J11) -> 0.32911388 | Q11: =IF(N(E11)=0,"",F11/E11) -> 1.4856108 | R11: =IF(N(H11)=0,"",E11/H11) -> 1.1553017 | S11: =IF(N(I11)=0,"",H11/I11) -> 0.0091434071 | T11: =IF(N(H11)=0,"",G11/H11) -> 0.039794608 | U11: =IF(N(L11)=0,"",G11/L11) -> 0.46969697 | V11: =IF(N(K11)=0,"",J11/K11) -> 39.346115 | W11: =IF(N(30)=0,"",E11/30) -> 59.998667 | X11: =IF(N(30)=0,"",K11/30) -> 4.6333333 | Y11: =IF(N(J11)=0,"",N11/J11) -> -0.24360271 | Z11: 2071.66 | AA11: 2536.11 | AB11: 64 | AC11: 1894 | AD11: 201332 | AE11: 5080.73 | AF11: 127 | AG11: 127 | AH11: 3226 | AI11: -2342.14 | AJ11: =IF(N(AA11)=0,"",Z11/AA11) -> 0.8168652 | AK11: =IF(N(AE11)=0,"",Z11/AE11) -> 0.40774849 | AL11: =IF(N(Z11)=0,"",AA11/Z11) -> 1.2241922 | AM11: =IF(N(AC11)=0,"",Z11/AC11) -> 1.0938015 | AN11: =IF(N(AD11)=0,"",AC11/AD11) -> 0.0094073471 | AO11: =IF(N(AC11)=0,"",AB11/AC11) -> 0.033790919 | AP11: =IF(N(AG11)=0,"",AB11/AG11) -> 0.50393701 | AQ11: =IF(N(AF11)=0,"",AE11/AF11) -> 40.005748 | AR11: =IF(N(26)=0,"",Z11/26) -> 79.679231 | AS11: =IF(N(26)=0,"",AF11/26) -> 4.8846154 | AT11: =IF(N(AE11)=0,"",AI11/AE11) -> -0.46098494 | AU11: =IF(OR(W11="",AR11=""),"",IF(N(W11)=0,"",AR11/W11-1)) -> 0.32801669 | AV11: =IF(N(F11)=0,"",(AA11/26)/(F11/30)-1) -> 0.094329467 | AW11: =IF(OR(X11="",AS11=""),"",IF(N(X11)=0,"",AS11/X11-1)) -> 0.054233536 | AX11: =IF(OR(O11="",AJ11=""),"",AJ11-O11) -> 0.14374139 | AY11: =IF(OR(P11="",AK11=""),"",AK11-P11) -> 0.078634615 | AZ11: =IF(OR(R11="",AM11=""),"",IF(N(R11)=0,"",AM11/R11-1)) -> -0.053233014 | BA11: =IF(OR(T11="",AO11=""),"",AO11-T11) -> -0.0060036898 | BB11: =IF(OR(V11="",AQ11=""),"",IF(N(V11)=0,"",AQ11/V11-1)) -> 0.016764881
A12: B0DHZSTBSD | B12: SPU07060 | C12: 利优比-电源逆变器-200W | D12: HK8-US/AMZ8-US | E12: 1623.49 | F12: 6889.16 | G12: 178 | H12: 2245 | I12: 272913 | J12: 20654.79 | K12: 573 | L12: 560 | M12: 17204 | N12: 6947.83 | O12: =IF(N(F12)=0,"",E12/F12) -> 0.23565863 | P12: =IF(N(J12)=0,"",E12/J12) -> 0.078601138 | Q12: =IF(N(E12)=0,"",F12/E12) -> 4.2434262 | R12: =IF(N(H12)=0,"",E12/H12) -> 0.72315813 | S12: =IF(N(I12)=0,"",H12/I12) -> 0.0082260647 | T12: =IF(N(H12)=0,"",G12/H12) -> 0.079287305 | U12: =IF(N(L12)=0,"",G12/L12) -> 0.31785714 | V12: =IF(N(K12)=0,"",J12/K12) -> 36.046754 | W12: =IF(N(30)=0,"",E12/30) -> 54.116333 | X12: =IF(N(30)=0,"",K12/30) -> 19.1 | Y12: =IF(N(J12)=0,"",N12/J12) -> 0.33637863 | Z12: 475.8 | AA12: 2658.01 | AB12: 72 | AC12: 529 | AD12: 115060 | AE12: 25810.84 | AF12: 716 | AG12: 701 | AH12: 19046 | AI12: 7815.2 | AJ12: =IF(N(AA12)=0,"",Z12/AA12) -> 0.1790061 | AK12: =IF(N(AE12)=0,"",Z12/AE12) -> 0.018434115 | AL12: =IF(N(Z12)=0,"",AA12/Z12) -> 5.5864018 | AM12: =IF(N(AC12)=0,"",Z12/AC12) -> 0.89943289 | AN12: =IF(N(AD12)=0,"",AC12/AD12) -> 0.0045976013 | AO12: =IF(N(AC12)=0,"",AB12/AC12) -> 0.13610586 | AP12: =IF(N(AG12)=0,"",AB12/AG12) -> 0.10271041 | AQ12: =IF(N(AF12)=0,"",AE12/AF12) -> 36.048659 | AR12: =IF(N(26)=0,"",Z12/26) -> 18.3 | AS12: =IF(N(26)=0,"",AF12/26) -> 27.538462 | AT12: =IF(N(AE12)=0,"",AI12/AE12) -> 0.30278751 | AU12: =IF(OR(W12="",AR12=""),"",IF(N(W12)=0,"",AR12/W12-1)) -> -0.66183962 | AV12: =IF(N(F12)=0,"",(AA12/26)/(F12/30)-1) -> -0.55481733 | AW12: =IF(OR(X12="",AS12=""),"",IF(N(X12)=0,"",AS12/X12-1)) -> 0.44180427 | AX12: =IF(OR(O12="",AJ12=""),"",AJ12-O12) -> -0.05665253 | AY12: =IF(OR(P12="",AK12=""),"",AK12-P12) -> -0.060167023 | AZ12: =IF(OR(R12="",AM12=""),"",IF(N(R12)=0,"",AM12/R12-1)) -> 0.24375687 | BA12: =IF(OR(T12="",AO12=""),"",AO12-T12) -> 0.056818555 | BB12: =IF(OR(V12="",AQ12=""),"",IF(N(V12)=0,"",AQ12/V12-1)) -> 5.285611e-05
A13: B0GXJ1P8X2 | B13: SPU50039 | C13: 牧田-单包逆变器350W-修正波版-美规-蓝色 | D13: AMZ5-US/AMZ5-CA | E13: 822.37 | F13: 1329.94 | G13: 32 | H13: 985 | I13: 109415 | J13: 2765.1 | K13: 60 | L13: 59 | M13: 2374 | N13: -207.27 | O13: =IF(N(F13)=0,"",E13/F13) -> 0.6183512 | P13: =IF(N(J13)=0,"",E13/J13) -> 0.29741058 | Q13: =IF(N(E13)=0,"",F13/E13) -> 1.6172039 | R13: =IF(N(H13)=0,"",E13/H13) -> 0.8348934 | S13: =IF(N(I13)=0,"",H13/I13) -> 0.009002422 | T13: =IF(N(H13)=0,"",G13/H13) -> 0.03248731 | U13: =IF(N(L13)=0,"",G13/L13) -> 0.54237288 | V13: =IF(N(K13)=0,"",J13/K13) -> 46.085 | W13: =IF(N(30)=0,"",E13/30) -> 27.412333 | X13: =IF(N(30)=0,"",K13/30) -> 2 | Y13: =IF(N(J13)=0,"",N13/J13) -> -0.074959314 | Z13: 861.16 | AA13: 1069.49 | AB13: 25 | AC13: 1105 | AD13: 92376 | AE13: 1938.74 | AF13: 43 | AG13: 43 | AH13: 1813 | AI13: -602.47 | AJ13: =IF(N(AA13)=0,"",Z13/AA13) -> 0.80520622 | AK13: =IF(N(AE13)=0,"",Z13/AE13) -> 0.4441854 | AL13: =IF(N(Z13)=0,"",AA13/Z13) -> 1.2419179 | AM13: =IF(N(AC13)=0,"",Z13/AC13) -> 0.77933032 | AN13: =IF(N(AD13)=0,"",AC13/AD13) -> 0.011961981 | AO13: =IF(N(AC13)=0,"",AB13/AC13) -> 0.022624434 | AP13: =IF(N(AG13)=0,"",AB13/AG13) -> 0.58139535 | AQ13: =IF(N(AF13)=0,"",AE13/AF13) -> 45.086977 | AR13: =IF(N(26)=0,"",Z13/26) -> 33.121538 | AS13: =IF(N(26)=0,"",AF13/26) -> 1.6538462 | AT13: =IF(N(AE13)=0,"",AI13/AE13) -> -0.31075338 | AU13: =IF(OR(W13="",AR13=""),"",IF(N(W13)=0,"",AR13/W13-1)) -> 0.2082714 | AV13: =IF(N(F13)=0,"",(AA13/26)/(F13/30)-1) -> -0.072118349 | AW13: =IF(OR(X13="",AS13=""),"",IF(N(X13)=0,"",AS13/X13-1)) -> -0.17307692 | AX13: =IF(OR(O13="",AJ13=""),"",AJ13-O13) -> 0.18685502 | AY13: =IF(OR(P13="",AK13=""),"",AK13-P13) -> 0.14677482 | AZ13: =IF(OR(R13="",AM13=""),"",IF(N(R13)=0,"",AM13/R13-1)) -> -0.066551112 | BA13: =IF(OR(T13="",AO13=""),"",AO13-T13) -> -0.0098628753 | BB13: =IF(OR(V13="",AQ13=""),"",IF(N(V13)=0,"",AQ13/V13-1)) -> -0.021656141
A14: B0CYZYC9HX | B14: SPU07051 | C14: 牧田-电源逆变器200W | D14: AMZ5-US/HK5-US | E14: 1167.67 | F14: 2484.88 | G14: 70 | H14: 1282 | I14: 351469 | J14: 5836.23 | K14: 171 | L14: 160 | M14: 10464 | N14: 1307.65 | O14: =IF(N(F14)=0,"",E14/F14) -> 0.46991002 | P14: =IF(N(J14)=0,"",E14/J14) -> 0.20007265 | Q14: =IF(N(E14)=0,"",F14/E14) -> 2.128067 | R14: =IF(N(H14)=0,"",E14/H14) -> 0.91081903 | S14: =IF(N(I14)=0,"",H14/I14) -> 0.0036475479 | T14: =IF(N(H14)=0,"",G14/H14) -> 0.054602184 | U14: =IF(N(L14)=0,"",G14/L14) -> 0.4375 | V14: =IF(N(K14)=0,"",J14/K14) -> 34.13 | W14: =IF(N(30)=0,"",E14/30) -> 38.922333 | X14: =IF(N(30)=0,"",K14/30) -> 5.7 | Y14: =IF(N(J14)=0,"",N14/J14) -> 0.22405731 | Z14: 441.33 | AA14: 989.24 | AB14: 30 | AC14: 540 | AD14: 250071 | AE14: 4471.63 | AF14: 137 | AG14: 125 | AH14: 7600 | AI14: 1108.21 | AJ14: =IF(N(AA14)=0,"",Z14/AA14) -> 0.44613036 | AK14: =IF(N(AE14)=0,"",Z14/AE14) -> 0.098695554 | AL14: =IF(N(Z14)=0,"",AA14/Z14) -> 2.2414973 | AM14: =IF(N(AC14)=0,"",Z14/AC14) -> 0.81727778 | AN14: =IF(N(AD14)=0,"",AC14/AD14) -> 0.0021593867 | AO14: =IF(N(AC14)=0,"",AB14/AC14) -> 0.055555556 | AP14: =IF(N(AG14)=0,"",AB14/AG14) -> 0.24 | AQ14: =IF(N(AF14)=0,"",AE14/AF14) -> 32.639635 | AR14: =IF(N(26)=0,"",Z14/26) -> 16.974231 | AS14: =IF(N(26)=0,"",AF14/26) -> 5.2692308 | AT14: =IF(N(AE14)=0,"",AI14/AE14) -> 0.24783133 | AU14: =IF(OR(W14="",AR14=""),"",IF(N(W14)=0,"",AR14/W14-1)) -> -0.56389483 | AV14: =IF(N(F14)=0,"",(AA14/26)/(F14/30)-1) -> -0.54064954 | AW14: =IF(OR(X14="",AS14=""),"",IF(N(X14)=0,"",AS14/X14-1)) -> -0.075573549 | AX14: =IF(OR(O14="",AJ14=""),"",AJ14-O14) -> -0.023779653 | AY14: =IF(OR(P14="",AK14=""),"",AK14-P14) -> -0.1013771 | AZ14: =IF(OR(R14="",AM14=""),"",IF(N(R14)=0,"",AM14/R14-1)) -> -0.10270015 | BA14: =IF(OR(T14="",AO14=""),"",AO14-T14) -> 0.00095337147 | BB14: =IF(OR(V14="",AQ14=""),"",IF(N(V14)=0,"",AQ14/V14-1)) -> -0.0436673
A15: B0CYZVRNJ7 | B15: SPU07051 | C15: 牧田-电源逆变器200W | D15: AMZ8-US/HK8-CA/AMZ8-MX | E15: 832.23 | F15: 2017.21 | G15: 51 | H15: 1625 | I15: 127172 | J15: 4887.12 | K15: 148 | L15: 119 | M15: 2944 | N15: 497.82 | O15: =IF(N(F15)=0,"",E15/F15) -> 0.41256488 | P15: =IF(N(J15)=0,"",E15/J15) -> 0.17029048 | Q15: =IF(N(E15)=0,"",F15/E15) -> 2.4238612 | R15: =IF(N(H15)=0,"",E15/H15) -> 0.51214154 | S15: =IF(N(I15)=0,"",H15/I15) -> 0.01277797 | T15: =IF(N(H15)=0,"",G15/H15) -> 0.031384615 | U15: =IF(N(L15)=0,"",G15/L15) -> 0.42857143 | V15: =IF(N(K15)=0,"",J15/K15) -> 33.021081 | W15: =IF(N(30)=0,"",E15/30) -> 27.741 | X15: =IF(N(30)=0,"",K15/30) -> 4.9333333 | Y15: =IF(N(J15)=0,"",N15/J15) -> 0.10186367 | Z15: 765.76 | AA15: 2111.22 | AB15: 57 | AC15: 1499 | AD15: 133845 | AE15: 2841.41 | AF15: 79 | AG15: 78 | AH15: 2957 | AI15: 221.23 | AJ15: =IF(N(AA15)=0,"",Z15/AA15) -> 0.36270971 | AK15: =IF(N(AE15)=0,"",Z15/AE15) -> 0.2695 | AL15: =IF(N(Z15)=0,"",AA15/Z15) -> 2.7570257 | AM15: =IF(N(AC15)=0,"",Z15/AC15) -> 0.51084723 | AN15: =IF(N(AD15)=0,"",AC15/AD15) -> 0.011199522 | AO15: =IF(N(AC15)=0,"",AB15/AC15) -> 0.03802535 | AP15: =IF(N(AG15)=0,"",AB15/AG15) -> 0.73076923 | AQ15: =IF(N(AF15)=0,"",AE15/AF15) -> 35.967215 | AR15: =IF(N(26)=0,"",Z15/26) -> 29.452308 | AS15: =IF(N(26)=0,"",AF15/26) -> 3.0384615 | AT15: =IF(N(AE15)=0,"",AI15/AE15) -> 0.077859232 | AU15: =IF(OR(W15="",AR15=""),"",IF(N(W15)=0,"",AR15/W15-1)) -> 0.061688753 | AV15: =IF(N(F15)=0,"",(AA15/26)/(F15/30)-1) -> 0.20761997 | AW15: =IF(OR(X15="",AS15=""),"",IF(N(X15)=0,"",AS15/X15-1)) -> -0.38409563 | AX15: =IF(OR(O15="",AJ15=""),"",AJ15-O15) -> -0.049855166 | AY15: =IF(OR(P15="",AK15=""),"",AK15-P15) -> 0.099209524 | AZ15: =IF(OR(R15="",AM15=""),"",IF(N(R15)=0,"",AM15/R15-1)) -> -0.0025272447 | BA15: =IF(OR(T15="",AO15=""),"",AO15-T15) -> 0.0066407348 | BB15: =IF(OR(V15="",AQ15=""),"",IF(N(V15)=0,"",AQ15/V15-1)) -> 0.089219796
A16: B0F9FQ2FVF | B16: SPU07060 | C16: 利优比-电源逆变器-200W | D16: AMZ8-US | E16: 1392.59 | F16: 2608.69 | G16: 77 | H16: 2846 | I16: 204883 | J16: 3882.92 | K16: 121 | L16: 119 | M16: 3427 | N16: -14.5 | O16: =IF(N(F16)=0,"",E16/F16) -> 0.53382732 | P16: =IF(N(J16)=0,"",E16/J16) -> 0.35864504 | Q16: =IF(N(E16)=0,"",F16/E16) -> 1.8732649 | R16: =IF(N(H16)=0,"",E16/H16) -> 0.48931483 | S16: =IF(N(I16)=0,"",H16/I16) -> 0.013890855 | T16: =IF(N(H16)=0,"",G16/H16) -> 0.027055517 | U16: =IF(N(L16)=0,"",G16/L16) -> 0.64705882 | V16: =IF(N(K16)=0,"",J16/K16) -> 32.090248 | W16: =IF(N(30)=0,"",E16/30) -> 46.419667 | X16: =IF(N(30)=0,"",K16/30) -> 4.0333333 | Y16: =IF(N(J16)=0,"",N16/J16) -> -0.0037343031 | Z16: 90.55 | AA16: 97.32 | AB16: 3 | AC16: 189 | AD16: 16730 | AE16: 65.98 | AF16: 2 | AG16: 2 | AH16: 213 | AI16: 372.89 | AJ16: =IF(N(AA16)=0,"",Z16/AA16) -> 0.93043568 | AK16: =IF(N(AE16)=0,"",Z16/AE16) -> 1.3723856 | AL16: =IF(N(Z16)=0,"",AA16/Z16) -> 1.0747653 | AM16: =IF(N(AC16)=0,"",Z16/AC16) -> 0.47910053 | AN16: =IF(N(AD16)=0,"",AC16/AD16) -> 0.011297071 | AO16: =IF(N(AC16)=0,"",AB16/AC16) -> 0.015873016 | AP16: =IF(N(AG16)=0,"",AB16/AG16) -> 1.5 | AQ16: =IF(N(AF16)=0,"",AE16/AF16) -> 32.99 | AR16: =IF(N(26)=0,"",Z16/26) -> 3.4826923 | AS16: =IF(N(26)=0,"",AF16/26) -> 0.076923077 | AT16: =IF(N(AE16)=0,"",AI16/AE16) -> 5.6515611 | AU16: =IF(OR(W16="",AR16=""),"",IF(N(W16)=0,"",AR16/W16-1)) -> -0.92497378 | AV16: =IF(N(F16)=0,"",(AA16/26)/(F16/30)-1) -> -0.95695452 | AW16: =IF(OR(X16="",AS16=""),"",IF(N(X16)=0,"",AS16/X16-1)) -> -0.98092816 | AX16: =IF(OR(O16="",AJ16=""),"",AJ16-O16) -> 0.39660835 | AY16: =IF(OR(P16="",AK16=""),"",AK16-P16) -> 1.0137405 | AZ16: =IF(OR(R16="",AM16=""),"",IF(N(R16)=0,"",AM16/R16-1)) -> -0.020874697 | BA16: =IF(OR(T16="",AO16=""),"",AO16-T16) -> -0.011182501 | BB16: =IF(OR(V16="",AQ16=""),"",IF(N(V16)=0,"",AQ16/V16-1)) -> 0.028038177
... A66: B0FF34YY91 | B66: SPU07104 | C66: 组合-米沃奇-车载逆变器-300W-2个装 | D66: AMZ8-US | E66: 0 | F66: 0 | G66: 0 | H66: 0 | I66: 0 | J66: 132.22 | K66: 4 | L66: 4 | M66: 86 | N66: -45.71 | O66: =IF(N(F66)=0,"",E66/F66) | P66: =IF(N(J66)=0,"",E66/J66) -> 0 | Q66: =IF(N(E66)=0,"",F66/E66) | R66: =IF(N(H66)=0,"",E66/H66) | S66: =IF(N(I66)=0,"",H66/I66) | T66: =IF(N(H66)=0,"",G66/H66) | U66: =IF(N(L66)=0,"",G66/L66) -> 0 | V66: =IF(N(K66)=0,"",J66/K66) -> 33.055 | W66: =IF(N(30)=0,"",E66/30) -> 0 | X66: =IF(N(30)=0,"",K66/30) -> 0.13333333 | Y66: =IF(N(J66)=0,"",N66/J66) -> -0.34571169 | Z66: 0.01 | AA66: 0 | AB66: 0 | AC66: 0 | AD66: 0 | AE66: 270.69 | AF66: 10 | AG66: 9 | AH66: 98 | AI66: -66.34 | AJ66: =IF(N(AA66)=0,"",Z66/AA66) | AK66: =IF(N(AE66)=0,"",Z66/AE66) -> 3.6942628e-05 | AL66: =IF(N(Z66)=0,"",AA66/Z66) -> 0 | AM66: =IF(N(AC66)=0,"",Z66/AC66) | AN66: =IF(N(AD66)=0,"",AC66/AD66) | AO66: =IF(N(AC66)=0,"",AB66/AC66) | AP66: =IF(N(AG66)=0,"",AB66/AG66) -> 0 | AQ66: =IF(N(AF66)=0,"",AE66/AF66) -> 27.069 | AR66: =IF(N(26)=0,"",Z66/26) -> 0.00038461538 | AS66: =IF(N(26)=0,"",AF66/26) -> 0.38461538 | AT66: =IF(N(AE66)=0,"",AI66/AE66) -> -0.24507739 | AU66: =IF(OR(W66="",AR66=""),"",IF(N(W66)=0,"",AR66/W66-1)) | AV66: =IF(N(F66)=0,"",(AA66/26)/(F66/30)-1) | AW66: =IF(OR(X66="",AS66=""),"",IF(N(X66)=0,"",AS66/X66-1)) -> 1.8846154 | AX66: =IF(OR(O66="",AJ66=""),"",AJ66-O66) | AY66: =IF(OR(P66="",AK66=""),"",AK66-P66) -> 3.6942628e-05 | AZ66: =IF(OR(R66="",AM66=""),"",IF(N(R66)=0,"",AM66/R66-1)) | BA66: =IF(OR(T66="",AO66=""),"",AO66-T66) | BB66: =IF(OR(V66="",AQ66=""),"",IF(N(V66)=0,"",AQ66/V66-1)) -> -0.18109212
A67: B0DGFQYJL6 | B67: SPU07066 | C67: 得伟-电源逆变器-200W+4AH电池包+座充（美规） | E67: 0 | F67: 0 | G67: 0 | H67: 0 | I67: 0 | J67: 0 | K67: 0 | L67: 0 | M67: 0 | N67: -5132.39 | O67: =IF(N(F67)=0,"",E67/F67) | P67: =IF(N(J67)=0,"",E67/J67) | Q67: =IF(N(E67)=0,"",F67/E67) | R67: =IF(N(H67)=0,"",E67/H67) | S67: =IF(N(I67)=0,"",H67/I67) | T67: =IF(N(H67)=0,"",G67/H67) | U67: =IF(N(L67)=0,"",G67/L67) | V67: =IF(N(K67)=0,"",J67/K67) | W67: =IF(N(30)=0,"",E67/30) -> 0 | X67: =IF(N(30)=0,"",K67/30) -> 0 | Y67: =IF(N(J67)=0,"",N67/J67) | Z67: 0 | AA67: 0 | AB67: 0 | AC67: 0 | AD67: 0 | AE67: 0 | AF67: 0 | AG67: 0 | AH67: 0 | AI67: -50.86 | AJ67: =IF(N(AA67)=0,"",Z67/AA67) | AK67: =IF(N(AE67)=0,"",Z67/AE67) | AL67: =IF(N(Z67)=0,"",AA67/Z67) | AM67: =IF(N(AC67)=0,"",Z67/AC67) | AN67: =IF(N(AD67)=0,"",AC67/AD67) | AO67: =IF(N(AC67)=0,"",AB67/AC67) | AP67: =IF(N(AG67)=0,"",AB67/AG67) | AQ67: =IF(N(AF67)=0,"",AE67/AF67) | AR67: =IF(N(26)=0,"",Z67/26) -> 0 | AS67: =IF(N(26)=0,"",AF67/26) -> 0 | AT67: =IF(N(AE67)=0,"",AI67/AE67) | AU67: =IF(OR(W67="",AR67=""),"",IF(N(W67)=0,"",AR67/W67-1)) | AV67: =IF(N(F67)=0,"",(AA67/26)/(F67/30)-1) | AW67: =IF(OR(X67="",AS67=""),"",IF(N(X67)=0,"",AS67/X67-1)) | AX67: =IF(OR(O67="",AJ67=""),"",AJ67-O67) | AY67: =IF(OR(P67="",AK67=""),"",AK67-P67) | AZ67: =IF(OR(R67="",AM67=""),"",IF(N(R67)=0,"",AM67/R67-1)) | BA67: =IF(OR(T67="",AO67=""),"",AO67-T67) | BB67: =IF(OR(V67="",AQ67=""),"",IF(N(V67)=0,"",AQ67/V67-1))
A68: B0DRVS8P1D | B68: SPU07022 | C68: 米沃奇-电源逆变器-200W-2个装 | E68: 0 | F68: 0 | G68: 0 | H68: 0 | I68: 0 | J68: 0 | K68: 0 | L68: 0 | M68: 0 | N68: 0 | O68: =IF(N(F68)=0,"",E68/F68) | P68: =IF(N(J68)=0,"",E68/J68) | Q68: =IF(N(E68)=0,"",F68/E68) | R68: =IF(N(H68)=0,"",E68/H68) | S68: =IF(N(I68)=0,"",H68/I68) | T68: =IF(N(H68)=0,"",G68/H68) | U68: =IF(N(L68)=0,"",G68/L68) | V68: =IF(N(K68)=0,"",J68/K68) | W68: =IF(N(30)=0,"",E68/30) -> 0 | X68: =IF(N(30)=0,"",K68/30) -> 0 | Y68: =IF(N(J68)=0,"",N68/J68) | Z68: 0 | AA68: 0 | AB68: 0 | AC68: 0 | AD68: 0 | AE68: 0 | AF68: 0 | AG68: 0 | AH68: 0 | AI68: -510.13 | AJ68: =IF(N(AA68)=0,"",Z68/AA68) | AK68: =IF(N(AE68)=0,"",Z68/AE68) | AL68: =IF(N(Z68)=0,"",AA68/Z68) | AM68: =IF(N(AC68)=0,"",Z68/AC68) | AN68: =IF(N(AD68)=0,"",AC68/AD68) | AO68: =IF(N(AC68)=0,"",AB68/AC68) | AP68: =IF(N(AG68)=0,"",AB68/AG68) | AQ68: =IF(N(AF68)=0,"",AE68/AF68) | AR68: =IF(N(26)=0,"",Z68/26) -> 0 | AS68: =IF(N(26)=0,"",AF68/26) -> 0 | AT68: =IF(N(AE68)=0,"",AI68/AE68) | AU68: =IF(OR(W68="",AR68=""),"",IF(N(W68)=0,"",AR68/W68-1)) | AV68: =IF(N(F68)=0,"",(AA68/26)/(F68/30)-1) | AW68: =IF(OR(X68="",AS68=""),"",IF(N(X68)=0,"",AS68/X68-1)) | AX68: =IF(OR(O68="",AJ68=""),"",AJ68-O68) | AY68: =IF(OR(P68="",AK68=""),"",AK68-P68) | AZ68: =IF(OR(R68="",AM68=""),"",IF(N(R68)=0,"",AM68/R68-1)) | BA68: =IF(OR(T68="",AO68=""),"",AO68-T68) | BB68: =IF(OR(V68="",AQ68=""),"",IF(N(V68)=0,"",AQ68/V68-1))
A69: B0DSS2BJLP | B69: SPU07060 | C69: 利优比-电源逆变器-200W-2个装 | D69: AMZ8-US | E69: 0 | F69: 0 | G69: 0 | H69: 0 | I69: 0 | J69: 182.37 | K69: 3 | L69: 3 | M69: 195 | N69: -400.3 | O69: =IF(N(F69)=0,"",E69/F69) | P69: =IF(N(J69)=0,"",E69/J69) -> 0 | Q69: =IF(N(E69)=0,"",F69/E69) | R69: =IF(N(H69)=0,"",E69/H69) | S69: =IF(N(I69)=0,"",H69/I69) | T69: =IF(N(H69)=0,"",G69/H69) | U69: =IF(N(L69)=0,"",G69/L69) -> 0 | V69: =IF(N(K69)=0,"",J69/K69) -> 60.79 | W69: =IF(N(30)=0,"",E69/30) -> 0 | X69: =IF(N(30)=0,"",K69/30) -> 0.1 | Y69: =IF(N(J69)=0,"",N69/J69) -> -2.1949882 | Z69: 0 | AA69: 0 | AB69: 0 | AC69: 0 | AD69: 0 | AE69: 0 | AF69: 0 | AG69: 0 | AH69: 139 | AI69: -602.06 | AJ69: =IF(N(AA69)=0,"",Z69/AA69) | AK69: =IF(N(AE69)=0,"",Z69/AE69) | AL69: =IF(N(Z69)=0,"",AA69/Z69) | AM69: =IF(N(AC69)=0,"",Z69/AC69) | AN69: =IF(N(AD69)=0,"",AC69/AD69) | AO69: =IF(N(AC69)=0,"",AB69/AC69) | AP69: =IF(N(AG69)=0,"",AB69/AG69) | AQ69: =IF(N(AF69)=0,"",AE69/AF69) | AR69: =IF(N(26)=0,"",Z69/26) -> 0 | AS69: =IF(N(26)=0,"",AF69/26) -> 0 | AT69: =IF(N(AE69)=0,"",AI69/AE69) | AU69: =IF(OR(W69="",AR69=""),"",IF(N(W69)=0,"",AR69/W69-1)) | AV69: =IF(N(F69)=0,"",(AA69/26)/(F69/30)-1) | AW69: =IF(OR(X69="",AS69=""),"",IF(N(X69)=0,"",AS69/X69-1)) -> -1 | AX69: =IF(OR(O69="",AJ69=""),"",AJ69-O69) | AY69: =IF(OR(P69="",AK69=""),"",AK69-P69) | AZ69: =IF(OR(R69="",AM69=""),"",IF(N(R69)=0,"",AM69/R69-1)) | BA69: =IF(OR(T69="",AO69=""),"",AO69-T69) | BB69: =IF(OR(V69="",AQ69=""),"",IF(N(V69)=0,"",AQ69/V69-1))
A70: B0F9FPQ7QM | B70: SPU07021 | C70: 得伟-电源逆变器-200W | E70: 0 | F70: 0 | G70: 0 | H70: 0 | I70: 0 | J70: 0 | K70: 0 | L70: 0 | M70: 8 | N70: 5.39 | O70: =IF(N(F70)=0,"",E70/F70) | P70: =IF(N(J70)=0,"",E70/J70) | Q70: =IF(N(E70)=0,"",F70/E70) | R70: =IF(N(H70)=0,"",E70/H70) | S70: =IF(N(I70)=0,"",H70/I70) | T70: =IF(N(H70)=0,"",G70/H70) | U70: =IF(N(L70)=0,"",G70/L70) | V70: =IF(N(K70)=0,"",J70/K70) | W70: =IF(N(30)=0,"",E70/30) -> 0 | X70: =IF(N(30)=0,"",K70/30) -> 0 | Y70: =IF(N(J70)=0,"",N70/J70) | Z70: 0 | AA70: 0 | AB70: 0 | AC70: 0 | AD70: 0 | AE70: 0 | AF70: 0 | AG70: 0 | AH70: 0 | AI70: 0 | AJ70: =IF(N(AA70)=0,"",Z70/AA70) | AK70: =IF(N(AE70)=0,"",Z70/AE70) | AL70: =IF(N(Z70)=0,"",AA70/Z70) | AM70: =IF(N(AC70)=0,"",Z70/AC70) | AN70: =IF(N(AD70)=0,"",AC70/AD70) | AO70: =IF(N(AC70)=0,"",AB70/AC70) | AP70: =IF(N(AG70)=0,"",AB70/AG70) | AQ70: =IF(N(AF70)=0,"",AE70/AF70) | AR70: =IF(N(26)=0,"",Z70/26) -> 0 | AS70: =IF(N(26)=0,"",AF70/26) -> 0 | AT70: =IF(N(AE70)=0,"",AI70/AE70) | AU70: =IF(OR(W70="",AR70=""),"",IF(N(W70)=0,"",AR70/W70-1)) | AV70: =IF(N(F70)=0,"",(AA70/26)/(F70/30)-1) | AW70: =IF(OR(X70="",AS70=""),"",IF(N(X70)=0,"",AS70/X70-1)) | AX70: =IF(OR(O70="",AJ70=""),"",AJ70-O70) | AY70: =IF(OR(P70="",AK70=""),"",AK70-P70) | AZ70: =IF(OR(R70="",AM70=""),"",IF(N(R70)=0,"",AM70/R70-1)) | BA70: =IF(OR(T70="",AO70=""),"",AO70-T70) | BB70: =IF(OR(V70="",AQ70=""),"",IF(N(V70)=0,"",AQ70/V70-1))
A71: B0DGT8Q4BQ | B71: SPU07066 | C71: 得伟-电源逆变器-200W+4AH电池包+座充（美规） | E71: 0 | F71: 0 | G71: 0 | H71: 0 | I71: 0 | J71: 0 | K71: 0 | L71: 0 | M71: 0 | N71: -58.14 | O71: =IF(N(F71)=0,"",E71/F71) | P71: =IF(N(J71)=0,"",E71/J71) | Q71: =IF(N(E71)=0,"",F71/E71) | R71: =IF(N(H71)=0,"",E71/H71) | S71: =IF(N(I71)=0,"",H71/I71) | T71: =IF(N(H71)=0,"",G71/H71) | U71: =IF(N(L71)=0,"",G71/L71) | V71: =IF(N(K71)=0,"",J71/K71) | W71: =IF(N(30)=0,"",E71/30) -> 0 | X71: =IF(N(30)=0,"",K71/30) -> 0 | Y71: =IF(N(J71)=0,"",N71/J71) | Z71: 0 | AA71: 0 | AB71: 0 | AC71: 0 | AD71: 0 | AE71: 0 | AF71: 0 | AG71: 0 | AH71: 0 | AI71: -119.91 | AJ71: =IF(N(AA71)=0,"",Z71/AA71) | AK71: =IF(N(AE71)=0,"",Z71/AE71) | AL71: =IF(N(Z71)=0,"",AA71/Z71) | AM71: =IF(N(AC71)=0,"",Z71/AC71) | AN71: =IF(N(AD71)=0,"",AC71/AD71) | AO71: =IF(N(AC71)=0,"",AB71/AC71) | AP71: =IF(N(AG71)=0,"",AB71/AG71) | AQ71: =IF(N(AF71)=0,"",AE71/AF71) | AR71: =IF(N(26)=0,"",Z71/26) -> 0 | AS71: =IF(N(26)=0,"",AF71/26) -> 0 | AT71: =IF(N(AE71)=0,"",AI71/AE71) | AU71: =IF(OR(W71="",AR71=""),"",IF(N(W71)=0,"",AR71/W71-1)) | AV71: =IF(N(F71)=0,"",(AA71/26)/(F71/30)-1) | AW71: =IF(OR(X71="",AS71=""),"",IF(N(X71)=0,"",AS71/X71-1)) | AX71: =IF(OR(O71="",AJ71=""),"",AJ71-O71) | AY71: =IF(OR(P71="",AK71=""),"",AK71-P71) | AZ71: =IF(OR(R71="",AM71=""),"",IF(N(R71)=0,"",AM71/R71-1)) | BA71: =IF(OR(T71="",AO71=""),"",AO71-T71) | BB71: =IF(OR(V71="",AQ71=""),"",IF(N(V71)=0,"",AQ71/V71-1))
A72: B0FF2ZCH2T | B72: SPU07103 | C72: 组合-得伟-车载逆变器-300W-2个装 | E72: 0 | F72: 0 | G72: 0 | H72: 0 | I72: 0 | J72: 0 | K72: 0 | L72: 0 | M72: 0 | N72: 47.13 | O72: =IF(N(F72)=0,"",E72/F72) | P72: =IF(N(J72)=0,"",E72/J72) | Q72: =IF(N(E72)=0,"",F72/E72) | R72: =IF(N(H72)=0,"",E72/H72) | S72: =IF(N(I72)=0,"",H72/I72) | T72: =IF(N(H72)=0,"",G72/H72) | U72: =IF(N(L72)=0,"",G72/L72) | V72: =IF(N(K72)=0,"",J72/K72) | W72: =IF(N(30)=0,"",E72/30) -> 0 | X72: =IF(N(30)=0,"",K72/30) -> 0 | Y72: =IF(N(J72)=0,"",N72/J72) | Z72: 0 | AA72: 0 | AB72: 0 | AC72: 0 | AD72: 0 | AE72: 0 | AF72: 0 | AG72: 0 | AH72: 0 | AI72: 2.43 | AJ72: =IF(N(AA72)=0,"",Z72/AA72) | AK72: =IF(N(AE72)=0,"",Z72/AE72) | AL72: =IF(N(Z72)=0,"",AA72/Z72) | AM72: =IF(N(AC72)=0,"",Z72/AC72) | AN72: =IF(N(AD72)=0,"",AC72/AD72) | AO72: =IF(N(AC72)=0,"",AB72/AC72) | AP72: =IF(N(AG72)=0,"",AB72/AG72) | AQ72: =IF(N(AF72)=0,"",AE72/AF72) | AR72: =IF(N(26)=0,"",Z72/26) -> 0 | AS72: =IF(N(26)=0,"",AF72/26) -> 0 | AT72: =IF(N(AE72)=0,"",AI72/AE72) | AU72: =IF(OR(W72="",AR72=""),"",IF(N(W72)=0,"",AR72/W72-1)) | AV72: =IF(N(F72)=0,"",(AA72/26)/(F72/30)-1) | AW72: =IF(OR(X72="",AS72=""),"",IF(N(X72)=0,"",AS72/X72-1)) | AX72: =IF(OR(O72="",AJ72=""),"",AJ72-O72) | AY72: =IF(OR(P72="",AK72=""),"",AK72-P72) | AZ72: =IF(OR(R72="",AM72=""),"",IF(N(R72)=0,"",AM72/R72-1)) | BA72: =IF(OR(T72="",AO72=""),"",AO72-T72) | BB72: =IF(OR(V72="",AQ72=""),"",IF(N(V72)=0,"",AQ72/V72-1))
A73: B0FF358VHG | B73: SPU07104 | C73: 组合-米沃奇-车载逆变器-300W-2个装 | E73: 0 | F73: 0 | G73: 0 | H73: 0 | I73: 0 | J73: 0 | K73: 0 | L73: 0 | M73: 0 | N73: 8.04 | O73: =IF(N(F73)=0,"",E73/F73) | P73: =IF(N(J73)=0,"",E73/J73) | Q73: =IF(N(E73)=0,"",F73/E73) | R73: =IF(N(H73)=0,"",E73/H73) | S73: =IF(N(I73)=0,"",H73/I73) | T73: =IF(N(H73)=0,"",G73/H73) | U73: =IF(N(L73)=0,"",G73/L73) | V73: =IF(N(K73)=0,"",J73/K73) | W73: =IF(N(30)=0,"",E73/30) -> 0 | X73: =IF(N(30)=0,"",K73/30) -> 0 | Y73: =IF(N(J73)=0,"",N73/J73) | Z73: 0 | AA73: 0 | AB73: 0 | AC73: 0 | AD73: 0 | AE73: 0 | AF73: 0 | AG73: 0 | AH73: 0 | AI73: 0 | AJ73: =IF(N(AA73)=0,"",Z73/AA73) | AK73: =IF(N(AE73)=0,"",Z73/AE73) | AL73: =IF(N(Z73)=0,"",AA73/Z73) | AM73: =IF(N(AC73)=0,"",Z73/AC73) | AN73: =IF(N(AD73)=0,"",AC73/AD73) | AO73: =IF(N(AC73)=0,"",AB73/AC73) | AP73: =IF(N(AG73)=0,"",AB73/AG73) | AQ73: =IF(N(AF73)=0,"",AE73/AF73) | AR73: =IF(N(26)=0,"",Z73/26) -> 0 | AS73: =IF(N(26)=0,"",AF73/26) -> 0 | AT73: =IF(N(AE73)=0,"",AI73/AE73) | AU73: =IF(OR(W73="",AR73=""),"",IF(N(W73)=0,"",AR73/W73-1)) | AV73: =IF(N(F73)=0,"",(AA73/26)/(F73/30)-1) | AW73: =IF(OR(X73="",AS73=""),"",IF(N(X73)=0,"",AS73/X73-1)) | AX73: =IF(OR(O73="",AJ73=""),"",AJ73-O73) | AY73: =IF(OR(P73="",AK73=""),"",AK73-P73) | AZ73: =IF(OR(R73="",AM73=""),"",IF(N(R73)=0,"",AM73/R73-1)) | BA73: =IF(OR(T73="",AO73=""),"",AO73-T73) | BB73: =IF(OR(V73="",AQ73=""),"",IF(N(V73)=0,"",AQ73/V73-1))
A74: B0FH4Y3NF1 | B74: SPU070117 | C74: 组合-牧田-车载逆变器-300W | E74: 0 | F74: 0 | G74: 0 | H74: 0 | I74: 0 | J74: 0 | K74: 0 | L74: 0 | M74: 78 | N74: 11.93 | O74: =IF(N(F74)=0,"",E74/F74) | P74: =IF(N(J74)=0,"",E74/J74) | Q74: =IF(N(E74)=0,"",F74/E74) | R74: =IF(N(H74)=0,"",E74/H74) | S74: =IF(N(I74)=0,"",H74/I74) | T74: =IF(N(H74)=0,"",G74/H74) | U74: =IF(N(L74)=0,"",G74/L74) | V74: =IF(N(K74)=0,"",J74/K74) | W74: =IF(N(30)=0,"",E74/30) -> 0 | X74: =IF(N(30)=0,"",K74/30) -> 0 | Y74: =IF(N(J74)=0,"",N74/J74) | Z74: 0 | AA74: 0 | AB74: 0 | AC74: 0 | AD74: 0 | AE74: 0 | AF74: 0 | AG74: 0 | AH74: 0 | AI74: -12.04 | AJ74: =IF(N(AA74)=0,"",Z74/AA74) | AK74: =IF(N(AE74)=0,"",Z74/AE74) | AL74: =IF(N(Z74)=0,"",AA74/Z74) | AM74: =IF(N(AC74)=0,"",Z74/AC74) | AN74: =IF(N(AD74)=0,"",AC74/AD74) | AO74: =IF(N(AC74)=0,"",AB74/AC74) | AP74: =IF(N(AG74)=0,"",AB74/AG74) | AQ74: =IF(N(AF74)=0,"",AE74/AF74) | AR74: =IF(N(26)=0,"",Z74/26) -> 0 | AS74: =IF(N(26)=0,"",AF74/26) -> 0 | AT74: =IF(N(AE74)=0,"",AI74/AE74) | AU74: =IF(OR(W74="",AR74=""),"",IF(N(W74)=0,"",AR74/W74-1)) | AV74: =IF(N(F74)=0,"",(AA74/26)/(F74/30)-1) | AW74: =IF(OR(X74="",AS74=""),"",IF(N(X74)=0,"",AS74/X74-1)) | AX74: =IF(OR(O74="",AJ74=""),"",AJ74-O74) | AY74: =IF(OR(P74="",AK74=""),"",AK74-P74) | AZ74: =IF(OR(R74="",AM74=""),"",IF(N(R74)=0,"",AM74/R74-1)) | BA74: =IF(OR(T74="",AO74=""),"",AO74-T74) | BB74: =IF(OR(V74="",AQ74=""),"",IF(N(V74)=0,"",AQ74/V74-1))
A75: B0FDQC9491 | B75: SPU07103 | C75: 组合-得伟-车载逆变器-300W-2个装 | E75: 0 | F75: 0 | G75: 0 | H75: 0 | I75: 0 | J75: 0 | K75: 0 | L75: 0 | M75: 0 | N75: 3.5 | O75: =IF(N(F75)=0,"",E75/F75) | P75: =IF(N(J75)=0,"",E75/J75) | Q75: =IF(N(E75)=0,"",F75/E75) | R75: =IF(N(H75)=0,"",E75/H75) | S75: =IF(N(I75)=0,"",H75/I75) | T75: =IF(N(H75)=0,"",G75/H75) | U75: =IF(N(L75)=0,"",G75/L75) | V75: =IF(N(K75)=0,"",J75/K75) | W75: =IF(N(30)=0,"",E75/30) -> 0 | X75: =IF(N(30)=0,"",K75/30) -> 0 | Y75: =IF(N(J75)=0,"",N75/J75) | Z75: 0 | AA75: 0 | AB75: 0 | AC75: 0 | AD75: 0 | AE75: 0 | AF75: 0 | AG75: 0 | AH75: 0 | AI75: 0 | AJ75: =IF(N(AA75)=0,"",Z75/AA75) | AK75: =IF(N(AE75)=0,"",Z75/AE75) | AL75: =IF(N(Z75)=0,"",AA75/Z75) | AM75: =IF(N(AC75)=0,"",Z75/AC75) | AN75: =IF(N(AD75)=0,"",AC75/AD75) | AO75: =IF(N(AC75)=0,"",AB75/AC75) | AP75: =IF(N(AG75)=0,"",AB75/AG75) | AQ75: =IF(N(AF75)=0,"",AE75/AF75) | AR75: =IF(N(26)=0,"",Z75/26) -> 0 | AS75: =IF(N(26)=0,"",AF75/26) -> 0 | AT75: =IF(N(AE75)=0,"",AI75/AE75) | AU75: =IF(OR(W75="",AR75=""),"",IF(N(W75)=0,"",AR75/W75-1)) | AV75: =IF(N(F75)=0,"",(AA75/26)/(F75/30)-1) | AW75: =IF(OR(X75="",AS75=""),"",IF(N(X75)=0,"",AS75/X75-1)) | AX75: =IF(OR(O75="",AJ75=""),"",AJ75-O75) | AY75: =IF(OR(P75="",AK75=""),"",AK75-P75) | AZ75: =IF(OR(R75="",AM75=""),"",IF(N(R75)=0,"",AM75/R75-1)) | BA75: =IF(OR(T75="",AO75=""),"",AO75-T75) | BB75: =IF(OR(V75="",AQ75=""),"",IF(N(V75)=0,"",AQ75/V75-1))
A76: B0FLJHB244 | B76: SPU07051 | C76: 牧田-电源逆变器200W | E76: 0 | F76: 0 | G76: 0 | H76: 0 | I76: 0 | J76: 0 | K76: 0 | L76: 0 | M76: 0 | N76: -0.28 | O76: =IF(N(F76)=0,"",E76/F76) | P76: =IF(N(J76)=0,"",E76/J76) | Q76: =IF(N(E76)=0,"",F76/E76) | R76: =IF(N(H76)=0,"",E76/H76) | S76: =IF(N(I76)=0,"",H76/I76) | T76: =IF(N(H76)=0,"",G76/H76) | U76: =IF(N(L76)=0,"",G76/L76) | V76: =IF(N(K76)=0,"",J76/K76) | W76: =IF(N(30)=0,"",E76/30) -> 0 | X76: =IF(N(30)=0,"",K76/30) -> 0 | Y76: =IF(N(J76)=0,"",N76/J76) | Z76: 0 | AA76: 0 | AB76: 0 | AC76: 0 | AD76: 0 | AE76: 0 | AF76: 0 | AG76: 0 | AH76: 0 | AI76: 0 | AJ76: =IF(N(AA76)=0,"",Z76/AA76) | AK76: =IF(N(AE76)=0,"",Z76/AE76) | AL76: =IF(N(Z76)=0,"",AA76/Z76) | AM76: =IF(N(AC76)=0,"",Z76/AC76) | AN76: =IF(N(AD76)=0,"",AC76/AD76) | AO76: =IF(N(AC76)=0,"",AB76/AC76) | AP76: =IF(N(AG76)=0,"",AB76/AG76) | AQ76: =IF(N(AF76)=0,"",AE76/AF76) | AR76: =IF(N(26)=0,"",Z76/26) -> 0 | AS76: =IF(N(26)=0,"",AF76/26) -> 0 | AT76: =IF(N(AE76)=0,"",AI76/AE76) | AU76: =IF(OR(W76="",AR76=""),"",IF(N(W76)=0,"",AR76/W76-1)) | AV76: =IF(N(F76)=0,"",(AA76/26)/(F76/30)-1) | AW76: =IF(OR(X76="",AS76=""),"",IF(N(X76)=0,"",AS76/X76-1)) | AX76: =IF(OR(O76="",AJ76=""),"",AJ76-O76) | AY76: =IF(OR(P76="",AK76=""),"",AK76-P76) | AZ76: =IF(OR(R76="",AM76=""),"",IF(N(R76)=0,"",AM76/R76-1)) | BA76: =IF(OR(T76="",AO76=""),"",AO76-T76) | BB76: =IF(OR(V76="",AQ76=""),"",IF(N(V76)=0,"",AQ76/V76-1))
A77: B0H44FVSWW | B77: SPU07051 | C77: 工匠-逆变器-200W-美规-红黑 | E77: 0 | F77: 0 | G77: 0 | H77: 0 | I77: 0 | J77: 0 | K77: 0 | L77: 0 | M77: 0 | N77: 0 | O77: =IF(N(F77)=0,"",E77/F77) | P77: =IF(N(J77)=0,"",E77/J77) | Q77: =IF(N(E77)=0,"",F77/E77) | R77: =IF(N(H77)=0,"",E77/H77) | S77: =IF(N(I77)=0,"",H77/I77) | T77: =IF(N(H77)=0,"",G77/H77) | U77: =IF(N(L77)=0,"",G77/L77) | V77: =IF(N(K77)=0,"",J77/K77) | W77: =IF(N(30)=0,"",E77/30) -> 0 | X77: =IF(N(30)=0,"",K77/30) -> 0 | Y77: =IF(N(J77)=0,"",N77/J77) | Z77: 0 | AA77: 0 | AB77: 0 | AC77: 0 | AD77: 0 | AE77: 0 | AF77: 0 | AG77: 0 | AH77: 3 | AI77: 10.33 | AJ77: =IF(N(AA77)=0,"",Z77/AA77) | AK77: =IF(N(AE77)=0,"",Z77/AE77) | AL77: =IF(N(Z77)=0,"",AA77/Z77) | AM77: =IF(N(AC77)=0,"",Z77/AC77) | AN77: =IF(N(AD77)=0,"",AC77/AD77) | AO77: =IF(N(AC77)=0,"",AB77/AC77) | AP77: =IF(N(AG77)=0,"",AB77/AG77) | AQ77: =IF(N(AF77)=0,"",AE77/AF77) | AR77: =IF(N(26)=0,"",Z77/26) -> 0 | AS77: =IF(N(26)=0,"",AF77/26) -> 0 | AT77: =IF(N(AE77)=0,"",AI77/AE77) | AU77: =IF(OR(W77="",AR77=""),"",IF(N(W77)=0,"",AR77/W77-1)) | AV77: =IF(N(F77)=0,"",(AA77/26)/(F77/30)-1) | AW77: =IF(OR(X77="",AS77=""),"",IF(N(X77)=0,"",AS77/X77-1)) | AX77: =IF(OR(O77="",AJ77=""),"",AJ77-O77) | AY77: =IF(OR(P77="",AK77=""),"",AK77-P77) | AZ77: =IF(OR(R77="",AM77=""),"",IF(N(R77)=0,"",AM77/R77-1)) | BA77: =IF(OR(T77="",AO77=""),"",AO77-T77) | BB77: =IF(OR(V77="",AQ77=""),"",IF(N(V77)=0,"",AQ77/V77-1))
A78: 品类合计/均值 | E78: =SUM(E5:E77) -> 34165.36 | F78: =SUM(F5:F77) -> 80180.77 | G78: =SUM(G5:G77) -> 2153 | H78: =SUM(H5:H77) -> 45337 | I78: =SUM(I5:I77) -> 6129290 | J78: =SUM(J5:J77) -> 213471.15 | K78: =SUM(K5:K77) -> 6064 | L78: =SUM(L5:L77) -> 5584 | ... N78: =SUM(N5:N77) -> -25524.08 | O78: =IF(N(F78)=0,"",E78/F78) -> 0.42610416 | P78: =IF(N(J78)=0,"",E78/J78) -> 0.16004673 | Q78: =IF(N(E78)=0,"",F78/E78) -> 2.346844 | R78: =IF(N(H78)=0,"",E78/H78) -> 0.7535867 | S78: =IF(N(I78)=0,"",H78/I78) -> 0.0073967784 | T78: =IF(N(H78)=0,"",G78/H78) -> 0.047488806 | U78: =IF(N(L78)=0,"",G78/L78) -> 0.3855659 | V78: =IF(N(K78)=0,"",J78/K78) -> 35.203026 | W78: =IF(N(30)=0,"",E78/30) -> 1138.8453 | X78: =IF(N(30)=0,"",K78/30) -> 202.13333 | Y78: =IF(N(J78)=0,"",N78/J78) -> -0.11956688 | Z78: =SUM(Z5:Z77) -> 32021.91 | AA78: =SUM(AA5:AA77) -> 83159.75 | AB78: =SUM(AB5:AB77) -> 2458 | AC78: =SUM(AC5:AC77) -> 42707 | AD78: =SUM(AD5:AD77) -> 5591316 | AE78: =SUM(AE5:AE77) -> 251392.03 | AF78: =SUM(AF5:AF77) -> 7595 | AG78: =SUM(AG5:AG77) -> 6875 | ... AI78: =SUM(AI5:AI77) -> 4077.36 | AJ78: =IF(N(AA78)=0,"",Z78/AA78) -> 0.38506501 | AK78: =IF(N(AE78)=0,"",Z78/AE78) -> 0.12737838 | AL78: =IF(N(Z78)=0,"",AA78/Z78) -> 2.5969641 | AM78: =IF(N(AC78)=0,"",Z78/AC78) -> 0.74980472 | AN78: =IF(N(AD78)=0,"",AC78/AD78) -> 0.0076380945 | AO78: =IF(N(AC78)=0,"",AB78/AC78) -> 0.057554968 | AP78: =IF(N(AG78)=0,"",AB78/AG78) -> 0.35752727 | AQ78: =IF(N(AF78)=0,"",AE78/AF78) -> 33.099675 | AR78: =IF(N(26)=0,"",Z78/26) -> 1231.6119 | AS78: =IF(N(26)=0,"",AF78/26) -> 292.11538 | AT78: =IF(N(AE78)=0,"",AI78/AE78) -> 0.01621913 | AU78: =IF(OR(W78="",AR78=""),"",IF(N(W78)=0,"",AR78/W78-1)) -> 0.081456706 | AV78: =IF(N(F78)=0,"",(AA78/26)/(F78/30)-1) -> 0.19671534 | AW78: =IF(OR(X78="",AS78=""),"",IF(N(X78)=0,"",AS78/X78-1)) -> 0.44516186 | AX78: =IF(OR(O78="",AJ78=""),"",AJ78-O78) -> -0.041039154 | AY78: =IF(OR(P78="",AK78=""),"",AK78-P78) -> -0.03266835 | AZ78: =IF(OR(R78="",AM78=""),"",IF(N(R78)=0,"",AM78/R78-1)) -> -0.0050186387 | BA78: =IF(OR(T78="",AO78=""),"",AO78-T78) -> 0.010066162 | BB78: =IF(OR(V78="",AQ78=""),"",IF(N(V78)=0,"",AQ78/V78-1)) -> -0.059749161
A80: 高亮规则：红=ACOS/TACOS 超阈值、毛利为负、日均花费暴涨、ACOS 恶化；黄=CPC 偏高、广告CVR 偏低、价格变动超阈值、日均销量下滑≥20%；绿=ACOS 改善。阈值见「总览」。结算毛利润受回款结算时点影响，单月波动大，仅作参考。

Sheet SPU价格监控
A1: SPU 价格监控（美国站）
A2: 成交均价 = 销售额 ÷ 销量（含促销/优惠券后实收）；挂牌价 = 各 ASIN×店铺 当天最低在售价的中位数（衡量标价调整）。黄色=较上周变动 ≥ 价格变动阈值（见总览）。
N3: 周成交均价 | X3: 周挂牌价
A4: SPU | B4: 款名（品牌） | C4: 9月成交均价 | D4: 10月成交均价 | E4: 成交均价环比 | F4: 近7天成交均价 | G4: 9月挂牌价 | H4: 10月挂牌价 | I4: 挂牌价环比 | J4: 9月日均销量 | K4: 10月日均销量 | L4: 日均销量环比 | N4: 09/01-09/06 | O4: 09/07-09/13 | P4: 09/14-09/20 | Q4: 09/21-09/27 | R4: 09/28-10/04 | S4: 10/05-10/11 | T4: 10/12-10/18 | U4: 10/19-10/25 | V4: 10/26-10/26 | X4: 09/01-09/06 | Y4: 09/07-09/13 | Z4: 09/14-09/20 | AA4: 09/21-09/27 | AB4: 09/28-10/04 | AC4: 10/05-10/11 | AD4: 10/12-10/18 | AE4: 10/19-10/25 | AF4: 10/26-10/26
A5: SPU07021 | B5: 逆变器-200W（得伟） | C5: 26.538843 | D5: 27.60381 | E5: =IF(OR(C5="",D5=""),"",D5/C5-1) -> 0.040128585 | F5: 26.319117 | G5: 36.0525 | H5: 35.624231 | I5: =IF(OR(G5="",H5=""),"",H5/G5-1) -> -0.011879044 | J5: 58.5 | K5: 124.38462 | L5: =IF(N(J5)=0,"",K5/J5-1) -> 1.1262327 | N5: 31.85765 | O5: 24.570754 | P5: 23.285 | Q5: 30.124562 | R5: 31.660435 | S5: 32.472985 | T5: 26.59169 | U5: 26.215513 | V5: 20.99 | X5: 36.0525 | Y5: 32.615 | Z5: 34.579286 | AA5: 39.49 | AB5: 39.49 | AC5: 35.845714 | AD5: 34.49 | AE5: 34.49 | AF5: 34.49
A6: SPU07022 | B6: 逆变器-200W（米沃奇） | C6: 27.680889 | D6: 26.681969 | E6: =IF(OR(C6="",D6=""),"",D6/C6-1) -> -0.036086976 | F6: 24.30288 | G6: 40.226 | H6: 35.555769 | I6: =IF(OR(G6="",H6=""),"",H6/G6-1) -> -0.11609981 | J6: 38.633333 | K6: 62.307692 | L6: =IF(N(J6)=0,"",K6/J6-1) -> 0.61279618 | N6: 34.497086 | O6: 24.883658 | P6: 24.526602 | Q6: 30.215322 | R6: 30.282389 | S6: 30.600501 | T6: 26.272392 | U6: 24.121407 | X6: 41.81 | Y6: 40.85 | Z6: 40.51 | AA6: 39.99 | AB6: 34.204286 | AC6: 33.24 | AD6: 39.361429 | AE6: 35.958571 | AF6: 31.57
A7: SPU50039 | B7: 单包逆变器（得伟/米沃奇/牧田） | C7: 40.926021 | D7: 41.056503 | E7: =IF(OR(C7="",D7=""),"",D7/C7-1) -> 0.0031882348 | F7: 43.536875 | G7: 42.34 | H7: 42.99 | I7: =IF(OR(G7="",H7=""),"",H7/G7-1) -> 0.015351913 | J7: 18.933333 | K7: 13.307692 | L7: =IF(N(J7)=0,"",K7/J7-1) -> -0.29712893 | N7: 43.397798 | O7: 39.220769 | P7: 39.030588 | Q7: 42.949217 | R7: 42.748523 | S7: 39.141453 | T7: 42.961013 | U7: 43.424211 | X7: 42.49 | Y7: 41.99 | Z7: 41.99 | AA7: 42.632857 | AB7: 42.99 | AC7: 42.99 | AD7: 42.99 | AE7: 42.99 | AF7: 42.99
A8: SPU07060 | B8: 逆变器-200W（利优比） | C8: 39.298429 | D8: 40.645735 | E8: =IF(OR(C8="",D8=""),"",D8/C8-1) -> 0.034283978 | F8: 42.361667 | G8: 44.99 | H8: 44.99 | I8: =IF(OR(G8="",H8=""),"",H8/G8-1) -> 0 | J8: 40.1 | K8: 46.807692 | L8: =IF(N(J8)=0,"",K8/J8-1) -> 0.16727412 | N8: 40.457236 | O8: 39.38003 | P8: 39.061123 | Q8: 38.679547 | R8: 37.619793 | S8: 38.385078 | T8: 42.642838 | U8: 42.644968 | V8: 36.99 | X8: 44.99 | Y8: 44.99 | Z8: 44.99 | AA8: 44.99 | AB8: 44.99 | AC8: 44.99 | AD8: 44.99 | AE8: 44.99 | AF8: 44.99
A9: SPU07051 | B9: 逆变器-200W（牧田款）（牧田/工匠） | C9: 34.910936 | D9: 33.752682 | E9: =IF(OR(C9="",D9=""),"",D9/C9-1) -> -0.033177391 | F9: 36.490941 | G9: 35.99 | H9: 35.99 | I9: =IF(OR(G9="",H9=""),"",H9/G9-1) -> 0 | J9: 14.6 | K9: 14.769231 | L9: =IF(N(J9)=0,"",K9/J9-1) -> 0.011591149 | N9: 35.107 | O9: 33.058829 | P9: 35.022294 | Q9: 36.198608 | R9: 36.190488 | S9: 32.39208 | T9: 32.591071 | U9: 35.878155 | V9: 32.39 | X9: 35.99 | Y9: 35.99 | Z9: 35.99 | AA9: 35.99 | AB9: 35.99 | AC9: 35.99 | AD9: 35.99 | AE9: 35.99 | AF9: 35.99
A10: SPU07120 | B10: 逆变器-550W（得伟） | C10: 91.745429 | D10: 101.07526 | E10: =IF(OR(C10="",D10=""),"",D10/C10-1) -> 0.10169258 | F10: 106.78 | G10: 98.061667 | H10: 108.83615 | I10: =IF(OR(G10="",H10=""),"",H10/G10-1) -> 0.10987461 | J10: 3.5 | K10: 3.7307692 | L10: =IF(N(J10)=0,"",K10/J10-1) -> 0.065934066 | N10: 113.35667 | O10: 90.615625 | P10: 93.147895 | Q10: 87.453659 | R10: 89.734186 | S10: 99.862727 | T10: 106.9075 | U10: 106.7975 | X10: 114.09833 | Y10: 98.418571 | Z10: 93.347143 | AA10: 91.704286 | AB10: 92.704286 | AC10: 110.56143 | AD10: 111.99 | AE10: 111.99 | AF10: 111.99
A11: SPU07121 | B11: 逆变器-550W（米沃奇） | C11: 92.840727 | D11: 96.449091 | E11: =IF(OR(C11="",D11=""),"",D11/C11-1) -> 0.038866172 | F11: 101.17889 | G11: 98.138333 | H11: 100.51981 | I11: =IF(OR(G11="",H11=""),"",H11/G11-1) -> 0.024266505 | J11: 3.6666667 | K11: 3.8076923 | L11: =IF(N(J11)=0,"",K11/J11-1) -> 0.038461538 | N11: 110.0625 | O11: 96.913077 | P11: 93.695882 | Q11: 90.011739 | R11: 89.603725 | S11: 92.284828 | T11: 104.43269 | U11: 101.995 | V11: 89.99 | X11: 112.87333 | Y11: 98.418571 | Z11: 93.347143 | AA11: 91.704286 | AB11: 95.247143 | AC11: 103.97214 | AD11: 100.12571 | AE11: 100.09 | AF11: 100.09
A12: SPU07116 | B12: 电源逆变器350W-AC美标110V PD20W（米沃奇） | C12: 49.586154 | D12: 53.04 | E12: =IF(OR(C12="",D12=""),"",D12/C12-1) -> 0.069653439 | G12: 50.106667 | H12: 53.288077 | I12: =IF(OR(G12="",H12=""),"",H12/G12-1) -> 0.063492754 | J12: 0.86666667 | K12: 0.46153846 | L12: =IF(N(J12)=0,"",K12/J12-1) -> -0.46745562 | N12: 69.99 | O12: 55.49 | P12: 46.79 | Q12: 45.69 | R12: 47.323333 | S12: 54.59 | T12: 66.99 | X12: 55.781667 | Y12: 50.954286 | Z12: 51.347143 | AA12: 45.561429 | AB12: 45.632857 | AC12: 59.597143 | AD12: 54.704286 | AE12: 50.49 | AF12: 45.99
A13: SPU07130 | B13: 电源逆变器-550W（牧田） | C13: 96.46451 | D13: 101.61581 | E13: =IF(OR(C13="",D13=""),"",D13/C13-1) -> 0.053400952 | F13: 97.74 | G13: 95.473333 | H13: 97.000577 | I13: =IF(OR(G13="",H13=""),"",H13/G13-1) -> 0.015996546 | J13: 1.7 | K13: 1.1923077 | L13: =IF(N(J13)=0,"",K13/J13-1) -> -0.29864253 | N13: 113.63 | O13: 98.99 | P13: 93.323333 | Q13: 93.460588 | R13: 98.656667 | S13: 100.67 | T13: 103.18444 | U13: 97.74 | X13: 99.64 | Y13: 95.247143 | Z13: 93.89 | AA13: 93.604286 | AB13: 98.961429 | AC13: 97.104286 | AD13: 95.015 | AE13: 97.157857 | AF13: 91.515
A14: SPU07055 | B14: 逆变器-双向65W（得伟） | C14: 24.707187 | D14: 22.553158 | E14: =IF(OR(C14="",D14=""),"",D14/C14-1) -> -0.087182307 | F14: 21.808182 | G14: 20.223333 | H14: 26.99 | I14: =IF(OR(G14="",H14=""),"",H14/G14-1) -> 0.334597 | J14: 1.0666667 | K14: 1.4615385 | L14: =IF(N(J14)=0,"",K14/J14-1) -> 0.37019231 | N14: 25.05 | O14: 25.59 | P14: 23.39 | Q14: 25.797143 | R14: 23.69 | S14: 22.64 | T14: 23.49 | U14: 21.808182 | X14: 19.99 | Y14: 19.99 | Z14: 19.99 | AA14: 19.99 | AB14: 24.99 | AC14: 26.99 | AD14: 26.99 | AE14: 26.99 | AF14: 26.99
A15: SPU07115 | B15: 电源逆变器350W-AC美标110V PD20W（得伟） | C15: 49.230833 | D15: 47.019091 | E15: =IF(OR(C15="",D15=""),"",D15/C15-1) -> -0.044925959 | F15: 46.679333 | G15: 48.856833 | H15: 48.247692 | I15: =IF(OR(G15="",H15=""),"",H15/G15-1) -> -0.012467878 | J15: 1.2 | K15: 2.1153846 | L15: =IF(N(J15)=0,"",K15/J15-1) -> 0.76282051 | N15: 57.656667 | O15: 49.49 | P15: 51.63625 | Q15: 41.323333 | R15: 46.523333 | S15: 38.181 | T15: 49.08 | U15: 49.564444 | X15: 54.323333 | Y15: 49.204286 | Z15: 49.705 | AA15: 45.061429 | AB15: 46.154286 | AC15: 50.14 | AD15: 48.347143 | AE15: 46.847143 | AF15: 45.99
A16: SPU07104 | B16: 车载逆变器-300W（米沃奇） | C16: 23.470317 | D16: 21.950588 | E16: =IF(OR(C16="",D16=""),"",D16/C16-1) -> -0.064751115 | F16: 21.715714 | G16: 37.076667 | H16: 31.605385 | I16: =IF(OR(G16="",H16=""),"",H16/G16-1) -> -0.14756672 | J16: 2.1 | K16: 2.6153846 | L16: =IF(N(J16)=0,"",K16/J16-1) -> 0.24542125 | N16: 41.59 | O16: 23.678235 | P16: 20.49 | Q16: 25.80625 | R16: 20.565 | S16: 21.46 | T16: 22.709583 | U16: 21.715714 | V16: 37.99 | X16: 43.99 | Y16: 40.218571 | Z16: 36.99 | AA16: 31.132857 | AB16: 29.99 | AC16: 35.99 | AD16: 29.99 | AE16: 29.99 | AF16: 29.99
A17: SPU07103 | B17: 车载逆变器-300W（得伟） | C17: 29.502195 | D17: 27.155 | E17: =IF(OR(C17="",D17=""),"",D17/C17-1) -> -0.079560016 | F17: 26.99 | G17: 31.156667 | H17: 29.99 | I17: =IF(OR(G17="",H17=""),"",H17/G17-1) -> -0.03744517 | J17: 1.3666667 | K17: 0.38461538 | L17: =IF(N(J17)=0,"",K17/J17-1) -> -0.71857411 | N17: 30.836154 | O17: 29.19 | P17: 28.99 | Q17: 27.49 | R17: 29.99 | S17: 26.54 | T17: 26.99 | U17: 26.99 | X17: 34.99 | Y17: 30.704286 | Z17: 29.99 | AA17: 29.99 | AB17: 29.99 | AC17: 29.99 | AD17: 29.99 | AE17: 29.99 | AF17: 29.99
A18: SPU07056 | B18: 逆变器-双向100W（得伟） | C18: 27.837049 | D18: 28.21165 | E18: =IF(OR(C18="",D18=""),"",D18/C18-1) -> 0.013456933 | F18: 28.99 | G18: 26.99 | H18: 26.99 | I18: =IF(OR(G18="",H18=""),"",H18/G18-1) -> 0 | J18: 4.0666667 | K18: 3.9615385 | L18: =IF(N(J18)=0,"",K18/J18-1) -> -0.025851198 | N18: 27.9796 | O18: 28.656667 | P18: 27.655385 | Q18: 28.132857 | R18: 27.691 | S18: 27.812821 | T18: 28.17125 | U18: 28.884737 | X18: 26.99 | Y18: 26.99 | Z18: 26.99 | AA18: 26.99 | AB18: 26.99 | AC18: 26.99 | AD18: 26.99 | AE18: 26.99 | AF18: 26.99
A19: SPU07066 | B19: 逆变器-200W+电池/充电器（得伟） | D19: 59.99 | E19: =IF(OR(C19="",D19=""),"",D19/C19-1) | G19: 59.99 | H19: 59.99 | I19: =IF(OR(G19="",H19=""),"",H19/G19-1) -> 0 | J19: 0 | K19: 0.19230769 | L19: =IF(N(J19)=0,"",K19/J19-1) | R19: 59.99 | S19: 59.99 | X19: 59.99 | Y19: 59.99 | Z19: 59.99 | AA19: 59.99 | AB19: 59.99 | AC19: 59.99 | AD19: 59.99 | AE19: 59.99 | AF19: 59.99
A20: SPU070117 | B20: 车载逆变器-300W（牧田） | E20: =IF(OR(C20="",D20=""),"",D20/C20-1) | G20: 26.99 | H20: 26.99 | I20: =IF(OR(G20="",H20=""),"",H20/G20-1) -> 0 | J20: 0 | K20: 0 | L20: =IF(N(J20)=0,"",K20/J20-1) | X20: 26.99 | Y20: 26.99 | Z20: 26.99 | AA20: 26.99 | AB20: 26.99 | AC20: 26.99 | AD20: 26.99 | AE20: 26.99 | AF20: 26.99
A22: 环比列：红=涨价、绿=降价（≥阈值）；日均销量环比≤-20% 标黄。成交均价受促销/Coupon/秒杀影响，挂牌价反映主动调价。
A24: 图表数据（周成交均价，主力 SPU）
A25: 周 | B25: SPU07021 | C25: SPU07022 | D25: SPU50039 | E25: SPU07060 | F25: SPU07051 | G25: SPU07120 | H25: SPU07121 | I25: SPU07116
A26: 09/01-09/06 | B26: 31.85765 | C26: 34.497086 | D26: 43.397798 | E26: 40.457236 | F26: 35.107 | G26: 113.35667 | H26: 110.0625 | I26: 69.99
A27: 09/07-09/13 | B27: 24.570754 | C27: 24.883658 | D27: 39.220769 | E27: 39.38003 | F27: 33.058829 | G27: 90.615625 | H27: 96.913077 | I27: 55.49
A28: 09/14-09/20 | B28: 23.285 | C28: 24.526602 | D28: 39.030588 | E28: 39.061123 | F28: 35.022294 | G28: 93.147895 | H28: 93.695882 | I28: 46.79
A29: 09/21-09/27 | B29: 30.124562 | C29: 30.215322 | D29: 42.949217 | E29: 38.679547 | F29: 36.198608 | G29: 87.453659 | H29: 90.011739 | I29: 45.69
A30: 09/28-10/04 | B30: 31.660435 | C30: 30.282389 | D30: 42.748523 | E30: 37.619793 | F30: 36.190488 | G30: 89.734186 | H30: 89.603725 | I30: 47.323333
A31: 10/05-10/11 | B31: 32.472985 | C31: 30.600501 | D31: 39.141453 | E31: 38.385078 | F31: 32.39208 | G31: 99.862727 | H31: 92.284828 | I31: 54.59
A32: 10/12-10/18 | B32: 26.59169 | C32: 26.272392 | D32: 42.961013 | E32: 42.642838 | F32: 32.591071 | G32: 106.9075 | H32: 104.43269 | I32: 66.99
A33: 10/19-10/25 | B33: 26.215513 | C33: 24.121407 | D33: 43.424211 | E33: 42.644968 | F33: 35.878155 | G33: 106.7975 | H33: 101.995
A34: 10/26-10/26 | B34: 20.99 | E34: 36.99 | F34: 32.39 | H34: 89.99

Sheet 价格变动明细
A1: ASIN×店铺 挂牌价变动明细（美国/加拿大，日环比变动 ≥ 5%）
A2: 挂牌价取当天最低在售价；“后7天”含变价当天。用于核对调价是否带来销量变化。
A4: SPU | B4: 款名（品牌） | C4: ASIN | D4: 店铺 | E4: 日期 | F4: 前一日挂牌价 | G4: 当日挂牌价 | H4: 变动幅度 | I4: 前7天日均销量 | J4: 后7天日均销量 | K4: 销量变化
A5: SPU07021 | B5: 逆变器-200W（得伟） | C5: B0CQ2MHKJ5 | D5: HK8-CA | E5: 2026-10-11 | F5: 27.76 | G5: 24.98 | H5: =G5/F5-1 -> -0.10014409 | I5: 1.5714286 | J5: 2.8571429 | K5: =IF(OR(I5="",J5=""),"",J5-I5) -> 1.2857143
A6: SPU07021 | B6: 逆变器-200W（得伟） | C6: B0CQ2MHKJ5 | D6: HK8-CA | E6: 2026-10-25 | F6: 24.98 | G6: 27.76 | H6: =G6/F6-1 -> 0.11128903 | I6: 1.8571429 | J6: 0.5 | K6: =IF(OR(I6="",J6=""),"",J6-I6) -> -1.3571429
A7: SPU07021 | B7: 逆变器-200W（得伟） | C7: B0CQ2MHKJ5 | D7: HK8-US | E7: 2026-09-22 | F7: 29.99 | G7: 27.54 | H7: =G7/F7-1 -> -0.081693898 | I7: 2.5714286 | J7: 10.857143 | K7: =IF(OR(I7="",J7=""),"",J7-I7) -> 8.2857143
A8: SPU07021 | B8: 逆变器-200W（得伟） | C8: B0CQ2MHKJ5 | D8: HK8-US | E8: 2026-09-26 | F8: 27.54 | G8: 26.09 | H8: =G8/F8-1 -> -0.05265069 | I8: 7 | J8: 15.285714 | K8: =IF(OR(I8="",J8=""),"",J8-I8) -> 8.2857143
A9: SPU07021 | B9: 逆变器-200W（得伟） | C9: B0CQ2MHKJ5 | D9: HK8-US | E9: 2026-10-06 | F9: 26.09 | G9: 29.99 | H9: =G9/F9-1 -> 0.14948256 | I9: 19.714286 | J9: 27.714286 | K9: =IF(OR(I9="",J9=""),"",J9-I9) -> 8
A10: SPU07021 | B10: 逆变器-200W（得伟） | C10: B0CQ4Q6WB9 | D10: AMZ5-US | E10: 2026-09-08 | F10: 29.99 | G10: 20.99 | H10: =G10/F10-1 -> -0.30010003 | I10: 13.142857 | J10: 61 | K10: =IF(OR(I10="",J10=""),"",J10-I10) -> 47.857143
A11: SPU07021 | B11: 逆变器-200W（得伟） | C11: B0CQ4Q6WB9 | D11: AMZ5-US | E11: 2026-09-22 | F11: 20.99 | G11: 29.99 | H11: =G11/F11-1 -> 0.42877561 | I11: 79.571429 | J11: 11 | K11: =IF(OR(I11="",J11=""),"",J11-I11) -> -68.571429
A12: SPU07021 | B12: 逆变器-200W（得伟） | C12: B0CQ4Q6WB9 | D12: HK5-US | E12: 2026-10-13 | F12: 29.99 | G12: 20.99 | H12: =G12/F12-1 -> -0.30010003 | I12: 2.8571429 | J12: 147.85714 | K12: =IF(OR(I12="",J12=""),"",J12-I12) -> 145
A13: SPU07021 | B13: 逆变器-200W（得伟） | C13: B0DKBP9KDS | D13: HK8-CA | E13: 2026-10-11 | F13: 51.37 | G13: 46.23 | H13: =G13/F13-1 -> -0.1000584 | I13: 0.71428571 | J13: 1.4285714 | K13: =IF(OR(I13="",J13=""),"",J13-I13) -> 0.71428571
A14: SPU07021 | B14: 逆变器-200W（得伟） | C14: B0DKBP9KDS | D14: HK8-CA | E14: 2026-10-25 | F14: 46.23 | G14: 51.37 | H14: =G14/F14-1 -> 0.11118321 | I14: 1 | J14: 0 | K14: =IF(OR(I14="",J14=""),"",J14-I14) -> -1
A15: SPU07021 | B15: 逆变器-200W（得伟） | C15: B0DRVSGQCC | D15: AMZ15-US | E15: 2026-10-06 | F15: 46.99 | G15: 39.82 | H15: =G15/F15-1 -> -0.15258566 | I15: 0.42857143 | J15: 1.5714286 | K15: =IF(OR(I15="",J15=""),"",J15-I15) -> 1.1428571
A16: SPU07021 | B16: 逆变器-200W（得伟） | C16: B0DRVSGQCC | D16: AMZ15-US | E16: 2026-10-08 | F16: 39.82 | G16: 37.82 | H16: =G16/F16-1 -> -0.050226017 | I16: 0.71428571 | J16: 2.2857143 | K16: =IF(OR(I16="",J16=""),"",J16-I16) -> 1.5714286
... A164: SPU50039 | B164: 单包逆变器（得伟/米沃奇/牧田） | C164: B0GXJ3VN4S | D164: AMZ5-US | E164: 2026-09-21 | F164: 38.69 | G164: 42.99 | H164: =G164/F164-1 -> 0.11113983 | I164: 12.142857 | J164: 7.2857143 | K164: =IF(OR(I164="",J164=""),"",J164-I164) -> -4.8571429

Sheet SPU日成交均价
A1: SPU 日成交均价（美国站，销售额÷销量；无销量日为空）
A3: 日期 | B3: SPU07021 | C3: SPU07022 | D3: SPU50039 | E3: SPU07060 | F3: SPU07051 | G3: SPU07120 | H3: SPU07121 | I3: SPU07116 | J3: SPU07130 | K3: SPU07055 | L3: SPU07115 | M3: SPU07104 | N3: SPU07103 | O3: SPU07056 | P3: SPU07066 | Q3: SPU070117
A4: 2026-09-01 | B4: 29.802093 | C4: 34.3 | D4: 43.923333 | E4: 38.123333 | F4: 33.63 | H4: 110.19 | J4: 115.99 | K4: 25.64 | L4: 61.615 | M4: 29.99 | N4: 29.99 | O4: 26.238571
A5: 2026-09-02 | B5: 32.665472 | C5: 37.570667 | D5: 43.523333 | E5: 39.935128 | F5: 36.479091 | G5: 116.99 | I5: 69.99 | K5: 26.99 | N5: 29.49 | O5: 27.99
A6: 2026-09-03 | B6: 33.390294 | C6: 31.901765 | D6: 42.835238 | E6: 42.31875 | F6: 34.394348 | G6: 113.565 | J6: 110.09 | K6: 26.99 | L6: 36.49 | O6: 29.39
A7: 2026-09-04 | B7: 30.693438 | C7: 33.701154 | D7: 43.479286 | E7: 41.747347 | F7: 38.128571 | G7: 111.14 | H7: 113.42333 | L7: 66.49 | M7: 53.19 | N7: 29.69 | O7: 26.99
A8: 2026-09-05 | B8: 35.086875 | C8: 33.34 | D8: 43.365 | E8: 38.278293 | F8: 34.241667 | G8: 115.99 | H8: 104.68333 | L8: 66.49 | N8: 43.99 | O8: 30.99
A9: 2026-09-06 | B9: 28.700435 | C9: 34.626364 | D9: 43.418571 | E9: 41.351702 | F9: 33.31 | G9: 110.65667 | H9: 115.99 | J9: 115.99 | K9: 22.815 | O9: 26.99
A10: 2026-09-07 | B10: 33.444688 | C10: 31.319565 | D10: 39.895 | E10: 40.915532 | F10: 33.990556 | G10: 99.99 | H10: 99.99 | I10: 66.49 | J10: 115.99 | K10: 26.99 | L10: 36.49 | M10: 19.94 | N10: 29.99 | O10: 28.99
A11: 2026-09-08 | B11: 23.718814 | C11: 24.5 | D11: 39.282857 | E11: 37.284043 | F11: 31.432308 | G11: 99.99 | H11: 99.99 | I11: 39.99 | J11: 99.99 | M11: 19.94 | N11: 29.99 | O11: 26.99
A12: 2026-09-09 | B12: 23.195616 | C12: 24.924545 | D12: 39.96 | E12: 38.85087 | F12: 31.228667 | G12: 99.99 | H12: 99.99 | K12: 26.99 | M12: 19.94 | O12: 32.99
A13: 2026-09-10 | B13: 24.017534 | C13: 23.8025 | D13: 39.24 | E13: 35.832093 | F13: 35.59 | G13: 96.74 | H13: 95.99 | J13: 96.49 | L13: 52.156667 | M13: 18.99 | N13: 29.99 | O13: 30.99
A14: 2026-09-11 | B14: 23.274262 | C14: 25.731224 | D14: 38.69 | E14: 42.29 | F14: 32.602727 | G14: 95.99 | H14: 96.49 | J14: 96.49 | L14: 48.24 | M14: 26.99
A15: 2026-09-12 | B15: 25.34443 | C15: 22.434444 | D15: 39.231176 | E15: 39.725556 | F15: 33.199375 | G15: 61.993333 | H15: 94.99 | I15: 56.99 | J15: 94.99 | M15: 21.99 | N15: 29.99 | O15: 28.99
A16: 2026-09-13 | B16: 23.70908 | C16: 23.968 | D16: 38.631667 | E16: 40.150392 | F16: 32.790455 | G16: 93.656667 | H16: 93.99 | I16: 56.99 | J16: 92.99 | K16: 24.656667 | L16: 56.99 | M16: 32.656667 | N16: 28.49 | O16: 26.99
A17: 2026-09-14 | B17: 25.045667 | C17: 24.000317 | D17: 38.986154 | E17: 39.022619 | F17: 32.963846 | G17: 93.656667 | H17: 93.656667 | J17: 93.49 | K17: 19.99 | L17: 36.49 | M17: 17.99 | N17: 29.99 | O17: 29.99
A18: 2026-09-15 | B18: 23.553514 | C18: 23.176441 | D18: 39.568333 | E18: 38.647895 | F18: 34.719412 | G18: 93.99 | H18: 92.99 | J18: 92.99 | K18: 26.99 | L18: 56.99 | M18: 17.99 | N18: 26.99 | O18: 26.99
A19: 2026-09-16 | B19: 23.148416 | C19: 23.999412 | D19: 39.532857 | E19: 40.743333 | F19: 36.279333 | G19: 94.99 | H19: 94.99 | I19: 56.99 | J19: 93.99 | L19: 56.99 | N19: 29.99 | O19: 27.765
A20: 2026-09-17 | B20: 21.484359 | C20: 25.603636 | D20: 39.061212 | E20: 37.856667 | F20: 36.13 | G20: 92.99 | H20: 94.99 | I20: 56.99 | J20: 93.99 | K20: 21.99 | M20: 24.323333 | O20: 26.744545
A21: 2026-09-18 | B21: 23.297831 | C21: 24.08 | D21: 38.343846 | E21: 38.323333 | F21: 35.51 | G21: 92.49 | K21: 23.49 | M21: 17.99 | N21: 26.99 | O21: 26.99
A22: 2026-09-19 | B22: 23.294348 | C22: 24.962973 | D22: 38.304286 | E22: 38.432647 | F22: 36.600769 | G22: 93.323333 | H22: 93.74 | K22: 26.99 | L22: 56.99 | M22: 17.99 | O22: 28.323333
A23: 2026-09-20 | B23: 22.904894 | C23: 25.944545 | D23: 38.609231 | E23: 39.550526 | F23: 35.121429 | G23: 91.24 | H23: 92.49 | I23: 39.99 | J23: 92.99 | L23: 45.825 | M23: 23.847143 | N23: 29.99 | O23: 27.847143
A24: 2026-09-21 | B24: 22.326947 | C24: 23.320189 | D24: 43.731667 | E24: 36.882308 | F24: 30.700909 | G24: 88.99 | H24: 88.99 | I24: 34.99 | J24: 94.99 | K24: 26.99 | M24: 17.99 | N24: 26.656667 | O24: 26.99
A25: 2026-09-22 | B25: 36.670909 | C25: 31.557647 | D25: 44.131667 | E25: 38.118462 | F25: 44.563333 | G25: 89.847143 | H25: 90.49 | I25: 34.99 | J25: 92.99 | K25: 26.99 | M25: 33.447143 | O25: 32.99
A26: 2026-09-23 | B26: 32.923636 | C26: 31.3025 | D26: 43.070435 | E26: 39.465 | F26: 33.578 | G26: 89.99 | H26: 88.99 | I26: 56.99 | J26: 92.99 | K26: 26.99 | L26: 56.99 | M26: 23.17 | O26: 28.19
A27: 2026-09-24 | B27: 31.70087 | C27: 29.419 | D27: 43.101111 | E27: 40.334242 | F27: 35.461111 | G27: 88.99 | H27: 88.99 | I27: 45.99 | J27: 92.99 | K27: 26.315 | L27: 33.99 | M27: 17.09 | O27: 32.99
A28: 2026-09-25 | B28: 34.17 | C28: 35.64 | D28: 42.91 | E28: 40.226061 | F28: 35.698571 | G28: 90.101111 | H28: 89.74 | I28: 56.99 | J28: 92.99 | K28: 19.99 | L28: 41.656667 | M28: 17.09 | N28: 29.99 | O28: 26.99
A29: 2026-09-26 | B29: 31.149459 | C29: 33.011842 | D29: 43.74 | E29: 36.884828 | F29: 35.29 | G29: 88.99 | H29: 89.561429 | J29: 92.99 | L29: 40.656667 | M29: 28.99 | O29: 26.99
A30: 2026-09-27 | B30: 29.446111 | C30: 33.836154 | D30: 39.172727 | E30: 39.003889 | F30: 36.483333 | G30: 76.848571 | H30: 92.561429 | I30: 44.49 | J30: 92.99 | L30: 33.99 | M30: 17.09 | O30: 28.49
A31: 2026-09-28 | B31: 30.235161 | C31: 29.86129 | D31: 42.717273 | E31: 36.945161 | F31: 34.180769 | G31: 91.39 | H31: 88.99 | I31: 53.99 | L31: 43.99 | M31: 23.723333 | O31: 26.99
A32: 2026-09-29 | B32: 33.198 | C32: 31.675763 | D32: 43.353636 | E32: 38.257742 | F32: 38.443571 | G32: 90.323333 | H32: 92.115 | I32: 47.656667 | J32: 92.99 | K32: 19.99 | O32: 26.99
A33: 2026-09-30 | B33: 31.29 | C33: 29.213214 | D33: 42.878889 | E33: 39.602162 | F33: 37.59 | G33: 88.99 | H33: 88.99 | I33: 53.99 | K33: 25.74 | L33: 33.99 | M33: 17.09 | O33: 26.72
A34: 2026-10-01 | B34: 32.447576 | C34: 31.036552 | D34: 42.49 | E34: 40.138438 | F34: 35.900588 | G34: 88.99 | H34: 89.276364 | J34: 109.99 | K34: 23.49 | L34: 37.99 | M34: 23.04 | N34: 29.99 | O34: 25.675
A35: 2026-10-02 | B35: 29.379474 | C35: 29.35 | D35: 42.573333 | E35: 37.486875 | F35: 33.939 | G35: 90.323333 | H35: 89.62 | I35: 34.99 | L35: 47.323333 | M35: 20.065 | O35: 30.225714 | P35: 59.99
A36: 2026-10-03 | B36: 33.672979 | C36: 28.647778 | D36: 42.435455 | E36: 34.51381 | F36: 35.038 | G36: 88.99 | H36: 88.99 | I36: 52.49 | J36: 92.99 | L36: 57.99 | M36: 21.056667 | O36: 27.847143
A37: 2026-10-04 | B37: 31.652222 | C37: 30.517778 | D37: 42.918125 | E37: 37.130541 | F37: 37.19 | G37: 88.99 | H37: 88.99 | I37: 34.99 | K37: 22.323333 | L37: 69.99 | M37: 17.09 | O37: 28.99 | P37: 59.99
A38: 2026-10-05 | B38: 28.731667 | C38: 28.887321 | D38: 42.573333 | E38: 35.26619 | F38: 38.115 | G38: 88.99 | H38: 88.99 | I38: 34.99 | J38: 92.99 | K38: 23.49 | M38: 17.09 | O38: 27.611429
A39: 2026-10-06 | B39: 33.987479 | C39: 29.154384 | D39: 34.708919 | E39: 36.4536 | F39: 31.334872 | G39: 92.101111 | H39: 82.573333 | K39: 21.59 | L39: 41.79 | M39: 23.85 | N39: 23.99 | O39: 25.236667 | P39: 59.99
A40: 2026-10-07 | B40: 29.346753 | C40: 28.430625 | D40: 35.498333 | E40: 37.45383 | F40: 29.695882 | G40: 110.19 | H40: 91.78375 | I40: 51.29 | J40: 110.19 | K40: 21.59 | L40: 27.86 | M40: 25.54 | N40: 27.815 | O40: 26.615
A41: 2026-10-08 | B41: 34.587955 | C41: 32.049474 | D41: 43.675 | E41: 39.74 | F41: 34.593 | G41: 113.59 | I41: 66.49 | K41: 26.99 | O41: 29.99 | P41: 59.99
A42: 2026-10-09 | B42: 32.310615 | C42: 32.642778 | D42: 42.66 | E42: 40.19 | F42: 36.1075 | G42: 113.59 | H42: 110.19 | I42: 61.74 | J42: 94.99 | K42: 26.99 | M42: 17.09 | O42: 28.79
A43: 2026-10-10 | B43: 34.187627 | C43: 33.808205 | D43: 43.460588 | E43: 44.036512 | F43: 37.539231 | G43: 110.19 | H43: 110.19 | L43: 32.29 | M43: 24.953333 | O43: 28.19
A44: 2026-10-11 | B44: 32.618734 | C44: 33.881892 | D44: 42.954286 | E44: 39.974545 | F44: 29.966923 | H44: 100.215 | J44: 102.59 | K44: 22.323333 | L44: 49.39 | O44: 28.49
A45: 2026-10-12 | B45: 36.213506 | C45: 33.086346 | D45: 43.24 | E45: 40.620769 | F45: 34.535455 | G45: 106.99 | H45: 103.54 | J45: 110.19 | L45: 31.33 | M45: 16.99 | O45: 28.0775
A46: 2026-10-13 | B46: 26.96959 | C46: 29.989048 | D46: 40.440588 | E46: 40.636167 | F46: 33.378235 | G46: 106.99 | H46: 110.19 | J46: 92.79 | L46: 43.49 | M46: 30.616 | O46: 28.99
A47: 2026-10-14 | B47: 27.116429 | C47: 25.494382 | D47: 45.728889 | E47: 43.722131 | F47: 30.265789 | G47: 106.99 | H47: 106.69429 | J47: 98.156667 | K47: 26.99 | L47: 53.323333 | M47: 16.99 | O47: 26.99
A48: 2026-10-15 | B48: 26.309031 | C48: 23.642059 | D48: 42.517778 | E48: 42.786078 | F48: 33.051 | G48: 106.605 | H48: 110.19 | J48: 96.6525 | K48: 23.49 | L48: 63.99 | M48: 11.326667 | O48: 28.99
A49: 2026-10-16 | B49: 26.478182 | C49: 26.394179 | D49: 44.49 | E49: 43.456792 | F49: 31.918333 | G49: 106.99 | H49: 103.45667 | I49: 63.99 | J49: 92.14 | L49: 47.7825 | M49: 16.99 | N49: 29.99 | O49: 32.99
A50: 2026-10-17 | B50: 25.027273 | C50: 24.585333 | D50: 43.14 | E50: 44.0525 | F50: 31.506667 | G50: 106.99 | H50: 102.11 | J50: 110.09 | K50: 19.99 | M50: 16.99 | O50: 26.99
A51: 2026-10-18 | B51: 24.69234 | C51: 25.119032 | D51: 43.79 | E51: 44.38359 | F51: 34.444667 | G51: 106.99 | H51: 99.0225 | I51: 69.99 | J51: 110.09 | K51: 23.49 | L51: 63.99 | M51: 25.99 | N51: 23.99 | O51: 26.99
A52: 2026-10-19 | B52: 25.716558 | C52: 23.185979 | D52: 42.823333 | E52: 44.292326 | F52: 32.953158 | G52: 106.99 | H52: 104.68 | L52: 63.99 | M52: 37.99 | O52: 26.99
A53: 2026-10-20 | B53: 26.745313 | C53: 23.925783 | D53: 41.965 | E53: 40.404103 | F53: 33.9 | G53: 106.99 | H53: 103.45667 | K53: 19.99 | L53: 39.99 | M53: 27.99 | N53: 23.99 | O53: 28.99
A54: 2026-10-21 | B54: 26.549869 | C54: 26.160316 | D54: 45.54 | E54: 43.214681 | F54: 36.825238 | G54: 106.4125 | H54: 97.335 | J54: 92.79 | K54: 18.99 | O54: 26.99
A55: 2026-10-22 | B55: 27.233115 | C55: 24.276506 | D55: 45.49 | E55: 43.425 | F55: 37.548947 | G55: 106.99 | H55: 103.7625 | J55: 100.215 | K55: 24.19 | L55: 45.99 | M55: 16.23 | O55: 32.99
A56: 2026-10-23 | B56: 24.974233 | C56: 23.24025 | D56: 41.99 | E56: 41.722292 | F56: 33.945556 | G56: 106.99 | H56: 102.03333 | K56: 19.99 | L56: 45.99 | M56: 16.23 | O56: 30.99
A57: 2026-10-24 | B57: 26.734837 | C57: 24.272083 | D57: 43.656667 | E57: 41.682308 | F57: 43.402727 | G57: 106.528 | H57: 100.09 | J57: 90.24 | K57: 19.99 | L57: 49.424 | M57: 25.99 | N57: 26.99 | O57: 28.49
A58: 2026-10-25 | B58: 25.806438 | C58: 23.662184 | D58: 42.24 | E58: 43.362115 | F58: 32.504 | G58: 106.99 | H58: 101.62 | J58: 101.49 | L58: 51.713333 | M58: 21.67 | N58: 29.99 | O58: 28.99
A59: 2026-10-26 | B59: 20.99 | E59: 36.99 | F59: 32.39 | H59: 89.99 | M59: 37.99
